Workbook

Sheet Summary
A2: Investments | B2: Actual Investment ('000 G$) | C2: ENPV ('000 g$) | D2: EIRR (%) | E2: FNPV ('000 G$) | F2: FIRR (%) | G2: BM implementation
A3: A. Total investment in various activity (Additional financing)
A4: Cassavs | B4: =('Cool Reflective Roof Coating'!F12+'Cool Reflective Roof Coating'!F21)/1000 -> 5650 | C4: ='Cool Reflective Roof Coating'!G68/1000 -> 4966.6541 | D4: ='Cool Reflective Roof Coating'!G67 -> 0.25239453 | E4: ='Cool Reflective Roof Coating'!G31/1000 -> 5500.63 | F4: ='Cool Reflective Roof Coating'!G30 -> 0.28445843 | G4: =L7/(B4*100) -> 813.80531 | K4: Total additional financing= US$ 11million | L4: 9000000 | O4: Total financing= US$ 10million | P4: 9000000
A5: Spice processing | B5: =('Ceiling Installation + Roof Ins'!F12+'Ceiling Installation + Roof Ins'!F23)/1000 -> 8908 | C5: ='Ceiling Installation + Roof Ins'!G72/1000 -> 3000.1885 | D5: ='Cross Ventilation Improvements'!G69 -> 0.16945185 | E5: ='Ceiling Installation + Roof Ins'!G33/1000 -> 5248.7725 | F5: ='Ceiling Installation + Roof Ins'!G32 -> 0.32578271 | G5: =L8/(B5*100) -> 387.12393 | K5: Total(G$) | L5: ='Additional financing total'!V13 -> 2299000000 | O5: Total(G$) | P5: =P4*208 -> 1872000000
A6: poultry | B6: =('Cross Ventilation Improvements'!H12+'Cross Ventilation Improvements'!H20)/1000 -> 5650.71 | C6: ='Cross Ventilation Improvements'!G70/1000 -> 24528.25 | D6: ='Ceiling Installation + Roof Ins'!G71 -> 0.27935087 | E6: ='Cross Ventilation Improvements'!G70/1000 -> 24528.25 | F6: ='Cross Ventilation Improvements'!G29 -> 0.16676295 | G6: =L9/(B6*100) -> 406.85153 | K6: Additional financing | L6: budget(G$) | M6: Budget(%) | O6: Additional financing | P6: budget(G$) | Q6: Budget(%)
A7: cattle | B7: =('External Shading (Awnings, Over'!G13+'External Shading (Awnings, Over'!G23)/1000 -> 360 | C7: ='External Shading (Awnings, Over'!G65/1000 -> 586.74751 | D7: ='External Shading (Awnings, Over'!G64 -> 0.33955408 | E7: ='External Shading (Awnings, Over'!G32/1000 -> 905.00181 | F7: ='External Shading (Awnings, Over'!G31 -> 0.32300371 | G7: =L10/(B7*100) -> 6386.1111 | K7: Cassava | L7: =L5*0.2 -> 459800000 | M7: 0.2 | O7: peanut TF | P7: =P5*0.2 -> 374400000 | Q7: 0.2
A8: Cassava processing | B8: =('Efficient Fans (DC or Energy-Ef'!F13+'Efficient Fans (DC or Energy-Ef'!F23)/1000 -> 7043.9 | C8: ='Efficient Fans (DC or Energy-Ef'!G67/1000 -> 2348.9085 | D8: ='Efficient Fans (DC or Energy-Ef'!G66 -> 0.20146258 | E8: =-('Efficient Fans (DC or Energy-Ef'!G33)/1000 -> 5643.3445 | F8: ='Efficient Fans (DC or Energy-Ef'!G32 -> 0.21726914 | G8: =L11/(B8*100) -> 326.38169 | K8: Spice processing | L8: =L5*0.15 -> 344850000 | M8: 0.15 | O8: cassava TF | P8: =P5*0.2 -> 374400000 | Q8: 0.2
A9: Honey | B9: =(Honey!F12+Honey!H27)/1000 -> 718.66667 | C9: =Honey!G71/1000 -> 197.7827 | D9: =Honey!G70 -> 0.36311265 | E9: =Honey!G32/1000 -> 215.44541 | F9: =Honey!G31 -> 0.35865753 | G9: =L12/(B9*100) -> 3198.9796 | K9: poutry | L9: =L5*0.1 -> 229900000 | M9: 0.1 | O9: poutry breedingTF | P9: =P5*0.15 -> 280800000 | Q9: 0.15
A10: School kitchen garden | B10: =('School kitchen gardening'!G10+'School kitchen gardening'!G20)/1000 -> 504.9 | C10: ='School kitchen gardening'!G64/1000 -> 146.54142 | D10: ='School kitchen gardening'!G63 -> 0.16984724 | E10: ='School kitchen gardening'!G31/1000 -> 149.87188 | F10: ='School kitchen gardening'!G30 -> 0.18940992 | G10: =L13/(B10*100) -> 4553.3769 | K10: Cattle | L10: =L5*0.1 -> 229900000 | M10: 0.25 | O10: Cattle breeding TF | P10: =P5*0.1 -> 187200000 | Q10: 0.25
A11: Total 1 unit investment cost(additional Financing) | B11: =SUM(B4:B10)*1000 -> 28836177 | C11: =(SUM(C4:C10)/SUM(B4:B10))*B11 -> 35775073 | D11: =(D4*B4+D5*B5+D6*B6+D7*B7+D9*B9+D10*B10)/(SUM(B4:B10)) -> 0.1728034 | E11: =(SUM(E4:E10)/SUM(B4:B10))*B11 -> 42191317 | F11: =(F4*B4+F5*B5+F6*B6+F7*B7+F9*B9+F10*B10)/SUM(B4:B10) -> 0.20534141 | K11: Cassava processing | L11: =L5*0.1 -> 229900000 | M11: 0.1 | O11: Cassava processing TF | P11: =P5*0.1 -> 187200000 | Q11: 0.1
A12: B. Total investment in various activity (Total financing) | K12: Honey | L12: =L5*0.1 -> 229900000 | M12: 0.1 | O12: guest house TF | P12: =P5*0.1 -> 187200000 | Q12: 0.1
A13: peanut TF | B13: =('Peanut TF'!F11+'Peanut TF'!F21)/1000 -> 671.5 | C13: ='Peanut TF'!G32/1000 -> 545.16928 | D13: ='Peanut TF'!G65 -> 0.27723132 | E13: ='Peanut TF'!G66/1000 -> 587.57698 | F13: ='Peanut TF'!G31 -> 0.29104771 | G13: =P7/(B13*100) -> 5575.5771 | K13: School kitchen garden | L13: =L5*0.1 -> 229900000 | M13: 0.1
A14: Cassava TF | B14: =('Cassava TF'!F12+'Cassava TF'!F21)/1000 -> 4650 | C14: ='Cassava TF'!G31/1000 -> 3755.6957 | D14: ='Cassava TF'!G30 -> 0.21348721 | E14: ='Cassava TF'!G68/1000 -> 2705.9999 | F14: ='Cassava TF'!G30 -> 0.21348721 | G14: =P8/(E14*100) -> 1383.5921
A15: Cassava processing TF | B15: =('Cassava processing TF'!F13+'Cassava processing TF'!F23)/1000 -> 6470.81 | C15: ='Cassava processing TF'!G33/1000 -> 2374.0297 | D15: ='Cassava processing TF'!G66 -> 0.23377797 | E15: ='Cassava processing TF'!G67/1000 -> 7829.0322 | F15: ='Efficient Fans (DC or Energy-Ef'!G32 -> 0.21726914 | G15: =P11/(B15*100) -> 289.29918
A16: cattle breeding TF | B16: =('cattle breeding TF'!F13+'cattle breeding TF'!G22)/1000 -> 3348 | C16: ='cattle breeding TF'!G65/1000 -> 3767.5349 | D16: ='cattle breeding TF'!G64 -> 0.19550723 | E16: ='cattle breeding TF'!G32/1000 -> 3594.7774 | F16: ='cattle breeding TF'!G31 -> 0.23765602 | G16: =P10/(B16*100) -> 559.13978
A17: poultry breeding TF | B17: =('Poutry breeding TF'!E11+'Poutry breeding TF'!F20)/1000 -> 5500.71 | C17: ='Poutry breeding TF'!G70/1000 -> 2990.5342 | D17: ='Poutry breeding TF'!G69 -> 0.16945185 | E17: ='Poutry breeding TF'!G30/1000 -> 2878.0265 | F17: ='Poutry breeding TF'!G29 -> 0.21018031 | G17: =P9/(B17*100) -> 510.47956
A18: guest house | B18: =-(GH!D7) -> 400000 | C18: =GH!D22/1000 -> 1918.5773 | D18: =GH!D23 -> 0.21393484 | E18: =-(GH!D27)/1000 -> -1234.7878 | F18: =GH!D28 -> 0.17820161 | G18: =P12/(B18) -> 468
A19: Total 1 unit investment cost(Total Financing) | B19: =SUM(B13:B18)*1000 -> 420641020 | C19: =(SUM(C13:C18)/SUM(B13:B18))*B19 -> 15351541 | D19: =(D13*B13+D14*B14+D15*B15+D16*B16+D17*B17+D18*B18)/(SUM(B13:B18)) -> 0.21360781 | E19: =(SUM(E13:E18)/SUM(B13:B18))*B19 -> 16360625 | F19: =(F13*B13+F14*B14+F15*B15+F16*B16+F17*B17+F18*B18)/SUM(B13:B18) -> 0.1802642
B21: =SUM(B4:B10) -> 28836.177
A23: =

Sheet prices and other data
D3: 2025 million usd
C4: Total export f.o.b | D4: 8280000000 | E4: 1989.77
C5: Total import c.i.f | D5: =4160*208 -> 865280 | E5: 3522.2
C6: Export duties | D6: =N11 -> ~US$10.09 billion
C7: Import duties | D7: =D5*0.2 -> 173056
C8: VAT on imports | D8: =D5*0.1 -> 86528
C9: Excise duties on imports | D9: =0.03*D5 -> 25958.4 | M9: Variable | N9: Recent Mozambique Value | O9: Notes / Suggested Use in EFA
M10: Total exports (f.o.b.) | N10: ~US$8.28 billion | O10: WITS/World Bank merchandise exports (World Integrated Trade Solution)
C11: Conversion factor | D11: 0.9 | M11: Total imports (c.i.f.) | N11: ~US$10.09 billion | O11: WITS/World Bank merchandise imports (World Integrated Trade Solution)
M12: Export duties | N12: Very limited / low | O12: Mozambique relies much more on import taxation than export duties (Trading Economics)
M13: Import duties | N13: Typically 0%–20% | O13: Depends on tariff classification (PwC Tax Summaries)
C14: VAT Tax rate (fixed for last 5 Years) | D14: 0.14 | M14: VAT on imports | N14: 16% VAT | O14: Standard VAT rate applied to imports and domestic goods
M15: Excise duties on imports | N15: Product specific | O15: Tobacco, alcohol, luxury items, vehicles, etc. (PwC Tax Summaries)
C16: Official Exchange Rate (2022) | D16: 64 | M16: Conversion factor | N16: 0.90–0.95 (typical WB assumption) | O16: Often used in EFA when estimating shadow pricing/tradable adjustments
M17: VAT tax rate | N17: 0.16 | O17: Fixed standard VAT rate in recent years
M18: Official exchange rate (2022) | N18: ~63–64 MZN per US$ | O18: Metical remained relatively stable since 2021 (IMF)
M19: Currency | N19: Mozambican Metical (MZN) | O19: Standard national currency
M20: Interest rate / discount rate for NPV | N20: 10%–12% commonly used | O20: WB economic analysis often uses 6–12%; financial analysis may use local borrowing costs
M21: Wage of labor – Family labor | N21: Shadow wage often below market wage | O21: Frequently adjusted downward in economic analysis
C22: BASIC DATA | M22: Wage of labor – Hired labor | N22: Market wage | O22: Use local construction/labor survey rates
C23: Currency | D23: MZN
C24: Exchange rate | D24: 1 | E24: USD = | F24: 64 | G24: MZN
C25: Interest rate (NPV) | D25: 0.14 | E25: 14%
C27: WAGE OF LABOR
C28: Tipo de mano de obra | E28: Wage MZN | G28: FC
E29: financial | F29: economic
C30: Family | D30: day | E30: 750 | F30: 750 | G30: 1
C31: Hired | D31: day | E31: 900 | F31: 900 | G31: 1

Sheet Cool   Reflective Roof Coating
B1: FINANCIAL
C2: Unit | D2: Quantity | E2: Price | F2: Amount | G2: Year
B3: REVENUE | G3: 1 | H3: =G3+1 -> 2 | I3: =H3+1 -> 3 | J3: =I3+1 -> 4 | K3: =J3+1 -> 5 | L3: =K3+1 -> 6 | M3: =L3+1 -> 7 | N3: =M3+1 -> 8 | O3: =N3+1 -> 9 | P3: =O3+1 -> 10 | Q3: 11 | R3: 12 | S3: 13 | T3: 14 | U3: 15
B4: Energy saved | C4: lbs | D4: 10000 | E4: 650 | F4: =D4*E4 -> 6500000 | G4: =F4*0.5 -> 3250000 | H4: =F4 -> 6500000 | I4: =F4 -> 6500000 | J4: =F4 -> 6500000 | K4: =J4 -> 6500000 | L4: =K4 -> 6500000 | M4: =L4 -> 6500000 | N4: =M4 -> 6500000 | O4: =N4 -> 6500000 | P4: =O4 -> 6500000 | Q4: =P4 -> 6500000 | R4: =Q4 -> 6500000 | ... U4: =T4 -> 6500000
B6: Sub-total Revenue | F6: =SUM(F4:F5) -> 6500000 | G6: =SUM(G4:G5) -> 3250000 | H6: =SUM(H4:H5) -> 6500000 | I6: =SUM(I4:I5) -> 6500000 | J6: =SUM(J4:J5) -> 6500000 | K6: =SUM(K4:K5) -> 6500000 | L6: =SUM(L4:L5) -> 6500000 | M6: =SUM(M4:M5) -> 6500000 | ... U6: =SUM(U4:U5) -> 6500000
B8: CAPEX
B9: Investment Costs
B10: Installment and other | C10: lumpsum | D10: 10 | E10: 100000 | F10: =D10*E10 -> 1000000 | G10: =D10*E10 -> 1000000 | H10: =G10 -> 1000000 | I10: 0 | J10: 0 | L10: =G10 -> 1000000 | O10: =L10 -> 1000000 | P10: =K10 -> 0 | T10: =O10 -> 1000000
B11: Other Fixed Cost | C11: lumpsum | D11: 1 | E11: 50000 | F11: =D11*E11 -> 50000 | G11: =D11*E11 -> 50000 | H11: 0 | I11: 0 | J11: 0 | K11: 0
B12: Sub-total Investment | F12: =SUM(F10:F11) -> 1050000 | G12: =SUM(G10:G11) -> 1050000 | H12: =SUM(H10:H11) -> 1000000 | I12: =SUM(I10:I11) -> 0 | J12: =SUM(J10:J11) -> 0 | K12: =SUM(K10:K11) -> 0 | M12: =SUM(M10:M11) -> 0 | N12: =SUM(N10:N11) -> 0 | P12: =SUM(P10:P11) -> 0 | R12: =SUM(R10:R11) -> 0 | S12: =SUM(S10:S11) -> 0 | T12: =SUM(T10:T11) -> 1000000 | U12: =SUM(U10:U11) -> 0
F13: =D13*E13 -> 0
B14: OPEX – Cool Reflective Roof | F14: =D14*E14 -> 0
B15: OPEX – Cool Reflective Roof | C15: MZK | E15: 1000000 | F15: =E15 -> 1000000 | G15: =F15 -> 1000000 | H15: =F15 -> 1000000 | I15: =H15 -> 1000000 | J15: =I15 -> 1000000 | K15: =J15 -> 1000000 | L15: =K15 -> 1000000 | M15: =L15 -> 1000000 | N15: =M15 -> 1000000 | O15: =N15 -> 1000000 | P15: =O15 -> 1000000 | ... U15: =T15 -> 1000000
B16: Wages and Labor | C16: MZK | D16: 2000 | E16: 900 | F16: =D16*E16 -> 1800000 | G16: =F16*0.75 -> 1350000 | H16: =F16 -> 1800000 | I16: =H16 -> 1800000 | J16: =I16 -> 1800000 | K16: =J16 -> 1800000 | L16: =K16 -> 1800000 | M16: =L16 -> 1800000 | N16: =M16 -> 1800000 | O16: =N16 -> 1800000 | P16: =O16 -> 1800000 | ... U16: =T16 -> 1800000
B17: Roof Maintenance | C17: MZK | D17: 12 | E17: 45000 | F17: =D17*E17 -> 540000 | G17: =F17 -> 540000 | H17: =D17*E17*1 -> 540000 | I17: =D17*E17*1 -> 540000 | J17: =D17*E17 -> 540000 | K17: =J17 -> 540000 | L17: =K17 -> 540000 | M17: =L17 -> 540000 | N17: =M17 -> 540000 | O17: =N17 -> 540000 | P17: =O17 -> 540000 | Q17: =P17 -> 540000 | R17: =Q17 -> 540000 | ... U17: =T17 -> 540000
B18: Reflective Coating Reapplication | C18: MZK | D18: 12 | E18: 55000 | F18: =D18*E18 -> 660000 | G18: =F18 -> 660000 | H18: =F18 -> 660000 | I18: =H18 -> 660000 | J18: =I18 -> 660000 | K18: =J18 -> 660000 | L18: =K18 -> 660000 | M18: =L18 -> 660000 | N18: =M18 -> 660000 | O18: =N18 -> 660000 | P18: =O18 -> 660000 | ... U18: =T18 -> 660000
B19: Cleaning and Repair | C19: MZK | D19: 100 | E19: 1000 | F19: =D19*E19 -> 100000 | G19: =F19 -> 100000 | H19: =G19 -> 100000 | I19: =H19 -> 100000 | J19: =I19 -> 100000 | K19: =J19 -> 100000 | L19: =K19 -> 100000 | M19: =L19 -> 100000 | N19: =M19 -> 100000 | ... U19: =T19 -> 100000
B20: Equipment and Material Replacement | C20: MZK | D20: 1 | E20: 500000 | F20: =D20*E20 -> 500000 | G20: =F20 -> 500000 | H20: =F20 -> 500000 | I20: =F20 -> 500000 | J20: =F20 -> 500000 | K20: =J20 -> 500000 | L20: =K20 -> 500000 | M20: =L20 -> 500000 | N20: =M20 -> 500000 | O20: =N20 -> 500000 | P20: =O20 -> 500000 | Q20: =P20 -> 500000 | R20: =Q20 -> 500000 | ... U20: =T20 -> 500000
B21: Sub-total for Operating costs | F21: =SUM(F15:F20) -> 4600000 | G21: =SUM(G15:G20) -> 4150000 | H21: =SUM(H15:H20) -> 4600000 | I21: =SUM(I15:I20) -> 4600000 | J21: =SUM(J15:J20) -> 4600000 | K21: =SUM(K15:K20) -> 4600000 | L21: =SUM(L15:L20) -> 4600000 | M21: =SUM(M15:M20) -> 4600000 | ... U21: =SUM(U15:U20) -> 4600000
B23: Fixed costs
B24: Depreciation | C24: MZK/annum | D24: 1 | E24: =E11/12 -> 4166.6667 | F24: =D24*E24 -> 4166.6667 | G24: =F24 -> 4166.6667 | H24: =D24*E24 -> 4166.6667 | I24: =H24 -> 4166.6667 | J24: =I24 -> 4166.6667 | K24: =J24 -> 4166.6667 | L24: =K24 -> 4166.6667 | M24: =L24 -> 4166.6667 | N24: =M24 -> 4166.6667 | O24: =N24 -> 4166.6667 | P24: =O24 -> 4166.6667 | ... U24: =T24 -> 4166.6667 | V24: =SUM(H24:U24) -> 58333.333
B25: Sub-total for Fixed costs | F25: =SUM(F24:F24) -> 4166.6667 | G25: =SUM(G24:G24) -> 4166.6667 | H25: =SUM(H24:H24) -> 4166.6667 | I25: =SUM(I24:I24) -> 4166.6667 | J25: =SUM(J24:J24) -> 4166.6667 | K25: =SUM(K24:K24) -> 4166.6667 | L25: =SUM(L24:L24) -> 4166.6667 | M25: =SUM(M24:M24) -> 4166.6667 | ... U25: =SUM(U24:U24) -> 4166.6667
B26: TOTAL COSTS | F26: =F12+F21+F25 -> 5654166.7 | G26: =G12+G21+G25 -> 5204166.7 | H26: =H12+H21+H25 -> 5604166.7 | I26: =I12+I21+I25 -> 4604166.7 | J26: =J12+J21+J25 -> 4604166.7 | K26: =K12+K21+K25 -> 4604166.7 | L26: =L12+L21+L25 -> 4604166.7 | M26: =M12+M21+M25 -> 4604166.7 | ... U26: =U12+U21+U25 -> 4604166.7
B28: GROSS MARGIN | C28: MZK/annum | G28: =G6-G12-G21 -> -1950000 | H28: =H6-H12-H21 -> 900000 | I28: =I6-I12-I21 -> 1900000 | J28: =J6-J12-J21 -> 1900000 | K28: =K6-K12-K21 -> 1900000 | L28: =L6-L12-L21 -> 1900000 | M28: =M6-M12-M21 -> 1900000 | N28: =N6-N12-N21 -> 1900000 | ... U28: =U6-U12-U21 -> 1900000
B29: NET MARGIN BEFORE PROFIT TAX | C29: MZK/annum | G29: =G28-G25 -> -1954166.7 | H29: =-(H28-H25) -> -895833.33 | I29: =-(I28-I25) -> -1895833.3 | J29: =J28-J25 -> 1895833.3 | K29: =K28-K25 -> 1895833.3 | L29: =L28-L25 -> 1895833.3 | M29: =M28-M25 -> 1895833.3 | N29: =N28-N25 -> 1895833.3 | O29: =O28-O25 -> 1895833.3 | P29: =P28-P25 -> 1895833.3 | Q29: =Q28-Q25 -> 1895833.3 | ... U29: =U28-U25 -> 1895833.3
B30: FIRR | G30: =IRR(G29:U29) -> 0.28445843
B31: FNPV | G31: =NPV(0.1,G29:U29) -> 5500630
B39: ECONOMIC
C40: Unit | D40: Quantity | E40: Price | F40: Amount | G40: Year
B41: REVENUE | G41: 1 | H41: =G41+1 -> 2 | I41: =H41+1 -> 3 | J41: =I41+1 -> 4 | K41: =J41+1 -> 5 | L41: =K41+1 -> 6 | M41: =L41+1 -> 7 | N41: =M41+1 -> 8 | O41: =N41+1 -> 9 | P41: =O41+1 -> 10 | Q41: 11 | R41: 12 | S41: 13 | T41: 14 | U41: 15
B42: =B4 -> Energy saved | C42: KWH/h | D42: =D4 -> 10000 | E42: =E4*0.92 -> 598 | F42: =D42*E42 -> 5980000 | G42: =F42*0.5 -> 2990000 | H42: =F42 -> 5980000 | I42: =F42 -> 5980000 | J42: =F42 -> 5980000 | K42: =J42 -> 5980000 | L42: =K42 -> 5980000 | M42: =L42 -> 5980000 | N42: =M42 -> 5980000 | O42: =N42 -> 5980000 | P42: =O42 -> 5980000 | Q42: =P42 -> 5980000 | R42: =Q42 -> 5980000 | ... U42: =T42 -> 5980000
B43: Sub-total Revenue | D43: =D6 -> 0 | E43: =E6*0.9 -> 0 | F43: =SUM(F42:F42) -> 5980000 | G43: =SUM(G42:G42) -> 2990000 | H43: =SUM(H42:H42) -> 5980000 | I43: =SUM(I42:I42) -> 5980000 | J43: =SUM(J42:J42) -> 5980000 | K43: =SUM(K42:K42) -> 5980000 | L43: =SUM(L42:L42) -> 5980000 | M43: =SUM(M42:M42) -> 5980000 | ... U43: =SUM(U42:U42) -> 5980000
D44: =D7 -> 0 | E44: =E7*0.9 -> 0
B45: COSTS | D45: =D8 -> 0 | E45: =E8*0.9 -> 0
B46: Investment Costs | D46: =D9 -> 0 | E46: =E9*0.9 -> 0
B47: installment cost | C47: lumpsum | D47: =D10 -> 10 | E47: =E10*0.9 -> 90000 | F47: =D47*E47 -> 900000 | G47: =D47*E47 -> 900000 | H47: 0 | I47: 0 | J47: 0 | P47: =K47 -> 0
B48: Other Fixed Cost | C48: lumpsum | D48: =D11 -> 1 | E48: =E11*0.9 -> 45000 | F48: =D48*E48 -> 45000 | G48: =D48*E48 -> 45000 | H48: 0 | I48: 0 | J48: 0 | K48: 0
B49: Sub-total Investment | D49: =D12 -> 0 | E49: =E12*0.9 -> 0 | F49: =SUM(F47:F48) -> 945000 | G49: =SUM(G47:G48) -> 945000 | H49: =SUM(H47:H48) -> 0 | I49: =SUM(I47:I48) -> 0 | J49: =SUM(J47:J48) -> 0 | K49: =SUM(K47:K48) -> 0 | L49: =SUM(L47:L48) -> 0 | M49: =SUM(M47:M48) -> 0 | ... U49: =SUM(U47:U48) -> 0
D50: =D13 -> 0 | E50: =E13*0.9 -> 0 | F50: =D50*E50 -> 0
B51: Operating costs | D51: =D14 -> 0 | E51: =E14*0.9 -> 0 | F51: =D51*E51 -> 0
B52: OPEX – Cool Reflective Roof | C52: MZK | D52: =D15 -> 0 | E52: =E15*0.9 -> 900000 | F52: =E52 -> 900000 | G52: =F52 -> 900000 | H52: =F52 -> 900000 | I52: =H52 -> 900000 | J52: =I52 -> 900000 | K52: =J52 -> 900000 | L52: =K52 -> 900000 | M52: =L52 -> 900000 | N52: =M52 -> 900000 | O52: =N52 -> 900000 | P52: =O52 -> 900000 | ... U52: =T52 -> 900000
B53: Wages and Labor | C53: MZK | D53: =D16 -> 2000 | E53: =E16*0.9 -> 810 | F53: =D53*E53 -> 1620000 | G53: =F53*0.75 -> 1215000 | H53: =D53*E53*1 -> 1620000 | I53: =D53*E53*1 -> 1620000 | J53: =D53*E53 -> 1620000 | K53: =J53 -> 1620000 | L53: =K53 -> 1620000 | M53: =L53 -> 1620000 | N53: =M53 -> 1620000 | O53: =N53 -> 1620000 | P53: =O53 -> 1620000 | Q53: =P53 -> 1620000 | R53: =Q53 -> 1620000 | ... U53: =T53 -> 1620000
B54: Roof Maintenance | C54: MZK | D54: =D17 -> 12 | E54: =E17*0.9 -> 40500 | F54: =D54*E54 -> 486000 | G54: =F54 -> 486000 | H54: =F54 -> 486000 | I54: =H54 -> 486000 | J54: =I54 -> 486000 | K54: =J54 -> 486000 | L54: =K54 -> 486000 | M54: =L54 -> 486000 | N54: =M54 -> 486000 | O54: =N54 -> 486000 | P54: =O54 -> 486000 | ... U54: =T54 -> 486000
B55: Reflective Coating Reapplication | C55: MZK | D55: =D18 -> 12 | E55: =E18*0.9 -> 49500 | F55: =D55*E55 -> 594000 | G55: =F55 -> 594000 | H55: =F55 -> 594000 | I55: =F55 -> 594000 | J55: =F55 -> 594000 | K55: =J55 -> 594000 | L55: =K55 -> 594000 | M55: =L55 -> 594000 | N55: =M55 -> 594000 | O55: =N55 -> 594000 | P55: =O55 -> 594000 | Q55: =P55 -> 594000 | R55: =Q55 -> 594000 | ... U55: =T55 -> 594000
B56: Cleaning and Repair | C56: MZK | D56: =D19 -> 100 | E56: =E19*0.9 -> 900 | F56: =D56*E56 -> 90000 | G56: =F56 -> 90000 | H56: =D56*E56*1 -> 90000 | I56: =D56*E56*1 -> 90000 | J56: =D56*E56 -> 90000 | K56: =J56 -> 90000 | L56: =K56 -> 90000 | M56: =L56 -> 90000 | N56: =M56 -> 90000 | O56: =N56 -> 90000 | P56: =O56 -> 90000 | Q56: =P56 -> 90000 | R56: =Q56 -> 90000 | ... U56: =T56 -> 90000
B57: Equipment and Material Replacement | C57: MZk | D57: =D20 -> 1 | E57: =E20*0.9 -> 450000 | F57: =D57*E57 -> 450000 | G57: =F57 -> 450000 | H57: =D57*E57*1 -> 450000 | I57: =D57*E57*1 -> 450000 | J57: =D57*E57 -> 450000 | K57: =J57 -> 450000 | L57: =K57 -> 450000 | M57: =L57 -> 450000 | N57: =M57 -> 450000 | O57: =N57 -> 450000 | P57: =O57 -> 450000 | Q57: =P57 -> 450000 | R57: =Q57 -> 450000 | ... U57: =T57 -> 450000
B58: Sub-total for Operating costs | D58: =D21 -> 0 | F58: =SUM(F52:F57) -> 4140000 | G58: =SUM(G52:G57) -> 3735000 | H58: =SUM(H52:H57) -> 4140000 | I58: =SUM(I52:I57) -> 4140000 | J58: =SUM(J52:J57) -> 4140000 | K58: =SUM(K52:K57) -> 4140000 | L58: =SUM(L52:L57) -> 4140000 | M58: =SUM(M52:M57) -> 4140000 | ... U58: =SUM(U52:U57) -> 4140000
D59: =D22 -> 0
B60: Fixed costs | D60: =D23 -> 0
B61: Depreciation (Shed) | C61: MZK | D61: =D24 -> 1 | E61: =E24*0.9 -> 3750 | F61: =D61*E61 -> 3750 | G61: 0 | H61: =D61*E61 -> 3750 | I61: =H61 -> 3750 | J61: =I61 -> 3750 | K61: =J61 -> 3750 | L61: =K61 -> 3750 | M61: =L61 -> 3750 | N61: =M61 -> 3750 | O61: =N61 -> 3750 | P61: =O61 -> 3750 | ... U61: =T61 -> 3750 | V61: =SUM(H61:U61) -> 52500
B62: Sub-total for Fixed costs | F62: =SUM(F61:F61) -> 3750 | G62: =SUM(G61:G61) -> 0 | H62: =SUM(H61:H61) -> 3750 | I62: =SUM(I61:I61) -> 3750 | J62: =SUM(J61:J61) -> 3750 | K62: =SUM(K61:K61) -> 3750 | L62: =SUM(L61:L61) -> 3750 | M62: =SUM(M61:M61) -> 3750 | ... U62: =SUM(U61:U61) -> 3750
B63: TOTAL COSTS | F63: =F49+F58+F62 -> 5088750 | G63: =G49+G58+G62 -> 4680000 | H63: =H49+H58+H62 -> 4143750 | I63: =I49+I58+I62 -> 4143750 | J63: =J49+J58+J62 -> 4143750 | K63: =K49+K58+K62 -> 4143750 | L63: =L49+L58+L62 -> 4143750 | M63: =M49+M58+M62 -> 4143750 | ... U63: =U49+U58+U62 -> 4143750
B65: GROSS MARGIN | C65: MZK | G65: =G43-G49-G58 -> -1690000 | H65: =H43-H49-H58 -> 1840000 | I65: =I43-I49-I58 -> 1840000 | J65: =J43-J49-J58 -> 1840000 | K65: =K43-K49-K58 -> 1840000 | L65: =L43-L49-L58 -> 1840000 | M65: =M43-M49-M58 -> 1840000 | N65: =N43-N49-N58 -> 1840000 | ... U65: =U43-U49-U58 -> 1840000
B66: NET MARGIN | C66: MZK | G66: =G65-G62 -> -1690000 | H66: =-(H65-H62) -> -1836250 | I66: =-(I65-I62) -> -1836250 | J66: =J65-J62 -> 1836250 | K66: =K65-K62 -> 1836250 | L66: =L65-L62 -> 1836250 | M66: =M65-M62 -> 1836250 | N66: =N65-N62 -> 1836250 | O66: =O65-O62 -> 1836250 | P66: =P65-P62 -> 1836250 | Q66: =Q65-Q62 -> 1836250 | ... U66: =U65-U62 -> 1836250
B67: EIRR | G67: =IRR(G66:U66) -> 0.25239453
B68: ENPV | G68: =NPV(0.1,G66:U66) -> 4966654.1

Sheet Ceiling Installation + Roof Ins
B1: FINANCIAL
C2: Unit | D2: Quantity | E2: Price | F2: Amount | G2: Year
B3: REVENUE | G3: 1 | H3: =G3+1 -> 2 | I3: =H3+1 -> 3 | J3: =I3+1 -> 4 | K3: =J3+1 -> 5 | L3: =K3+1 -> 6 | M3: =L3+1 -> 7 | N3: =M3+1 -> 8 | O3: =N3+1 -> 9 | P3: =O3+1 -> 10 | Q3: 11 | R3: 12 | S3: 13 | T3: 14 | U3: 15
B4: Enegy saved | C4: lumpsum | F4: 4400000 | H4: =F4 -> 4400000 | I4: =F4 -> 4400000 | J4: =F4 -> 4400000 | K4: =J4 -> 4400000 | L4: =K4 -> 4400000 | M4: =L4 -> 4400000 | N4: =M4 -> 4400000 | O4: =N4 -> 4400000 | P4: =O4 -> 4400000 | Q4: =P4 -> 4400000 | R4: =Q4 -> 4400000 | ... U4: =T4 -> 4400000
B5: Productivity cost | C5: lumpsum | F5: 4600000 | H5: =F5 -> 4600000 | I5: =H5 -> 4600000 | J5: =H5 -> 4600000 | K5: =J5 -> 4600000 | L5: =K5 -> 4600000 | M5: =L5 -> 4600000 | N5: =M5 -> 4600000 | O5: =N5 -> 4600000 | P5: =O5 -> 4600000 | Q5: =P5 -> 4600000 | R5: =Q5 -> 4600000 | ... U5: =T5 -> 4600000
B6: Sub-total Revenue | F6: =SUM(F4:F5) -> 9000000 | G6: =SUM(G4:G5) -> 0 | H6: =SUM(H4:H5) -> 9000000 | I6: =SUM(I4:I5) -> 9000000 | J6: =SUM(J4:J5) -> 9000000 | K6: =SUM(K4:K5) -> 9000000 | L6: =SUM(L4:L5) -> 9000000 | M6: =SUM(M4:M5) -> 9000000 | ... U6: =SUM(U4:U5) -> 9000000
B8: COSTS
B9: Investment Costs
B10: Fixed Capital | C10: lumpsum | D10: 1 | E10: 1000000 | F10: =D10*E10 -> 1000000 | G10: =D10*E10 -> 1000000 | H10: 0 | I10: 0 | J10: 0 | P10: =K10 -> 0
B11: Cash in hand | C11: lumpsum | D11: 1 | E11: 300000 | F11: =D11*E11 -> 300000 | G11: =D11*E11 -> 300000 | H11: 0 | I11: 0 | J11: 0 | K11: 0
B12: Sub-total Investment | F12: =SUM(F10:F11) -> 1300000 | G12: =SUM(G10:G11) -> 1300000 | H12: =SUM(H10:H11) -> 0 | I12: =SUM(I10:I11) -> 0 | J12: =SUM(J10:J11) -> 0 | K12: =SUM(K10:K11) -> 0 | L12: =SUM(L10:L11) -> 0 | M12: =SUM(M10:M11) -> 0 | ... U12: =SUM(U10:U11) -> 0
F13: =D13*E13 -> 0
B14: Operating costs | F14: =D14*E14 -> 0
B15: Wages and Labor | C15: MZK | F15: =F4*0.8 -> 3520000 | G15: =F15*0.5 -> 1760000 | H15: =F15 -> 3520000 | I15: =H15 -> 3520000 | J15: =I15 -> 3520000 | K15: =J15 -> 3520000 | L15: =K15 -> 3520000 | M15: =L15 -> 3520000 | N15: =M15 -> 3520000 | O15: =N15 -> 3520000 | P15: =O15 -> 3520000 | ... U15: =T15 -> 3520000
B16: Ceiling Maintenance | C16: MZK | F16: 3000000 | H16: =F16 -> 3000000 | I16: =H16 -> 3000000 | J16: =I16 -> 3000000 | K16: =J16 -> 3000000 | L16: =K16 -> 3000000 | M16: =L16 -> 3000000 | N16: =M16 -> 3000000 | O16: =N16 -> 3000000 | P16: =O16 -> 3000000 | ... U16: =T16 -> 3000000
B17: Insulation Repair | C17: MZK | D17: 200 | E17: 4500 | F17: =D17*E17 -> 900000 | G17: =F17*0.75 -> 675000 | H17: =F17 -> 900000 | I17: =H17 -> 900000 | J17: =I17 -> 900000 | K17: =J17 -> 900000 | L17: =K17 -> 900000 | M17: =L17 -> 900000 | N17: =M17 -> 900000 | O17: =N17 -> 900000 | P17: =O17 -> 900000 | ... U17: =T17 -> 900000
B18: Cleaning and Minor Repair | C18: MZK | F18: 100000 | G18: =F18 -> 100000 | H18: =G18 -> 100000 | I18: =H18 -> 100000 | J18: =I18 -> 100000 | K18: =J18 -> 100000 | L18: =K18 -> 100000 | M18: =L18 -> 100000 | N18: =M18 -> 100000 | ... U18: =T18 -> 100000
B20: other | C20: MZK | F20: =F4*0.01 -> 44000 | G20: =F20 -> 44000 | H20: =F20 -> 44000 | I20: =H20 -> 44000 | J20: =I20 -> 44000 | K20: =J20 -> 44000 | L20: =K20 -> 44000 | M20: =L20 -> 44000 | N20: =M20 -> 44000 | O20: =N20 -> 44000 | P20: =O20 -> 44000 | ... U20: =T20 -> 44000
B21: Material Replacement | C21: MZK | F21: =F4*0.01 -> 44000 | G21: =F21 -> 44000 | H21: =G21 -> 44000 | I21: =H21 -> 44000 | J21: =I21 -> 44000 | K21: =J21 -> 44000 | L21: =K21 -> 44000 | M21: =L21 -> 44000 | N21: =M21 -> 44000 | ... U21: =T21 -> 44000
B23: Sub-total for Operating costs | F23: =SUM(F15:F22) -> 7608000 | G23: =SUM(G15:G22) -> 2623000 | H23: =SUM(H15:H22) -> 7608000 | I23: =SUM(I15:I22) -> 7608000 | J23: =SUM(J15:J22) -> 7608000 | K23: =SUM(K15:K22) -> 7608000 | L23: =SUM(L15:L22) -> 7608000 | M23: =SUM(M15:M22) -> 7608000 | ... U23: =SUM(U15:U22) -> 7608000
B25: Fixed costs
B26: Depreciation | C26: MZK/annum | D26: 1 | E26: =E10/15 -> 66666.667 | F26: =D26*E26 -> 66666.667 | G26: =F26 -> 66666.667 | H26: =D26*E26 -> 66666.667 | I26: =H26 -> 66666.667 | J26: =I26 -> 66666.667 | K26: =J26 -> 66666.667 | L26: =K26 -> 66666.667 | M26: =L26 -> 66666.667 | N26: =M26 -> 66666.667 | O26: =N26 -> 66666.667 | P26: =O26 -> 66666.667 | ... U26: =T26 -> 66666.667 | V26: =SUM(H26:U26) -> 933333.33
B27: Sub-total for Fixed costs | F27: =SUM(F26:F26) -> 66666.667 | G27: =SUM(G26:G26) -> 66666.667 | H27: =SUM(H26:H26) -> 66666.667 | I27: =SUM(I26:I26) -> 66666.667 | J27: =SUM(J26:J26) -> 66666.667 | K27: =SUM(K26:K26) -> 66666.667 | L27: =SUM(L26:L26) -> 66666.667 | M27: =SUM(M26:M26) -> 66666.667 | ... U27: =SUM(U26:U26) -> 66666.667
B28: TOTAL COSTS | F28: =F12+F23+F27 -> 8974666.7 | G28: =G12+G23+G27 -> 3989666.7 | H28: =H12+H23+H27 -> 7674666.7 | I28: =I12+I23+I27 -> 7674666.7 | J28: =J12+J23+J27 -> 7674666.7 | K28: =K12+K23+K27 -> 7674666.7 | L28: =L12+L23+L27 -> 7674666.7 | M28: =M12+M23+M27 -> 7674666.7 | ... U28: =U12+U23+U27 -> 7674666.7
B30: GROSS MARGIN | C30: MZK/annum | G30: =G6-G12-G23 -> -3923000 | H30: =H6-H12-H23 -> 1392000 | I30: =I6-I12-I23 -> 1392000 | J30: =J6-J12-J23 -> 1392000 | K30: =K6-K12-K23 -> 1392000 | L30: =L6-L12-L23 -> 1392000 | M30: =M6-M12-M23 -> 1392000 | N30: =N6-N12-N23 -> 1392000 | ... U30: =U6-U12-U23 -> 1392000
B31: NET MARGIN BEFORE PROFIT TAX | C31: MZK/annum | G31: =G30-G27 -> -3989666.7 | H31: =H30-H27 -> 1325333.3 | I31: =I30-I27 -> 1325333.3 | J31: =J30-J27 -> 1325333.3 | K31: =K30-K27 -> 1325333.3 | L31: =L30-L27 -> 1325333.3 | M31: =M30-M27 -> 1325333.3 | N31: =N30-N27 -> 1325333.3 | ... U31: =U30-U27 -> 1325333.3
B32: FIRR | G32: =IRR(G31:U31) -> 0.32578271
B33: FNPV | G33: =NPV(0.1,G31:U31) -> 5248772.5
B41: ECONOMIC
C42: Unit | D42: Quantity | E42: Price | F42: Amount | G42: Year
B43: REVENUE | G43: 1 | H43: =G43+1 -> 2 | I43: =H43+1 -> 3 | J43: =I43+1 -> 4 | K43: =J43+1 -> 5 | L43: =K43+1 -> 6 | M43: =L43+1 -> 7 | N43: =M43+1 -> 8 | O43: =N43+1 -> 9 | P43: =O43+1 -> 10 | Q43: 11 | R43: 12 | S43: 13 | T43: 14 | U43: 15
B44: Enegy saved | C44: lumpsum | F44: =F4*0.9 -> 3960000 | G44: =F44*0.5 -> 1980000 | H44: =F44 -> 3960000 | I44: =F44 -> 3960000 | J44: =F44 -> 3960000 | K44: =J44 -> 3960000 | L44: =K44 -> 3960000 | M44: =L44 -> 3960000 | N44: =M44 -> 3960000 | O44: =N44 -> 3960000 | P44: =O44 -> 3960000 | Q44: =P44 -> 3960000 | R44: =Q44 -> 3960000 | ... U44: =T44 -> 3960000
B45: Productivity cost | C45: lumpsum | F45: =F5*0.9 -> 4140000 | H45: =F45 -> 4140000 | I45: =H45 -> 4140000 | J45: =I45 -> 4140000 | K45: =J45 -> 4140000 | L45: =K45 -> 4140000 | M45: =L45 -> 4140000 | N45: =M45 -> 4140000 | O45: =N45 -> 4140000 | P45: =O45 -> 4140000 | ... U45: =T45 -> 4140000
B47: Sub-total Revenue | D47: =D6 -> 0 | E47: =E6*0.9 -> 0 | F47: =SUM(F44:F46) -> 8100000 | G47: =SUM(G44:G46) -> 1980000 | H47: =SUM(H44:H46) -> 8100000 | I47: =SUM(I44:I46) -> 8100000 | J47: =SUM(J44:J46) -> 8100000 | K47: =SUM(K44:K46) -> 8100000 | L47: =SUM(L44:L46) -> 8100000 | M47: =SUM(M44:M46) -> 8100000 | ... U47: =SUM(U44:U46) -> 8100000
D48: =D7 -> 0 | E48: =E7*0.9 -> 0
B49: CAPEX | D49: =D8 -> 0 | E49: =E8*0.9 -> 0
B50: Investment Costs | D50: =D9 -> 0 | E50: =E9*0.9 -> 0
B51: Fixed Capital | C51: Nos. | D51: =D10 -> 1 | E51: =E10*0.9 -> 900000 | F51: =D51*E51 -> 900000 | G51: =D51*E51 -> 900000 | H51: 0 | I51: 0 | J51: 0 | P51: =K51 -> 0
B52: Installment | C52: lumpsum | D52: =D11 -> 1 | E52: =E11*0.9 -> 270000 | F52: =D52*E52 -> 270000 | G52: =D52*E52 -> 270000 | H52: 0 | I52: 0 | J52: 0 | K52: 0
B53: Sub-total Investment | D53: =D12 -> 0 | E53: =E12*0.9 -> 0 | F53: =SUM(F51:F52) -> 1170000 | G53: =SUM(G51:G52) -> 1170000 | H53: =SUM(H51:H52) -> 0 | I53: =SUM(I51:I52) -> 0 | J53: =SUM(J51:J52) -> 0 | K53: =SUM(K51:K52) -> 0 | L53: =SUM(L51:L52) -> 0 | M53: =SUM(M51:M52) -> 0 | ... U53: =SUM(U51:U52) -> 0
D54: =D13 -> 0 | E54: =E13*0.9 -> 0 | F54: =D54*E54 -> 0
B55: OPEX | D55: =D14 -> 0 | E55: =E14*0.9 -> 0 | F55: =D55*E55 -> 0
B56: Wages and Labor | C56: MZK | F56: =F15 -> 3520000 | G56: =F56*0.5 -> 1760000 | H56: =F56 -> 3520000 | I56: =H56 -> 3520000 | J56: =I56 -> 3520000 | K56: =J56 -> 3520000 | L56: =K56 -> 3520000 | M56: =L56 -> 3520000 | N56: =M56 -> 3520000 | O56: =N56 -> 3520000 | P56: =O56 -> 3520000 | ... U56: =T56 -> 3520000
B57: Ceiling Maintenance | C57: MZK | F57: =F16*0.9 -> 2700000 | H57: =F57 -> 2700000 | I57: =H57 -> 2700000 | J57: =I57 -> 2700000 | K57: =J57 -> 2700000 | L57: =K57 -> 2700000 | M57: =L57 -> 2700000 | N57: =M57 -> 2700000 | O57: =N57 -> 2700000 | P57: =O57 -> 2700000 | ... U57: =T57 -> 2700000
B58: Insulation Repair | C58: MZK | F58: =F17*0.9 -> 810000 | G58: =F58*0.75 -> 607500 | H58: =F58 -> 810000 | I58: =H58 -> 810000 | J58: =I58 -> 810000 | K58: =J58 -> 810000 | L58: =K58 -> 810000 | M58: =L58 -> 810000 | N58: =M58 -> 810000 | O58: =N58 -> 810000 | P58: =O58 -> 810000 | ... U58: =T58 -> 810000
B59: Cleaning and Minor Repair | C59: MZK | F59: =F18*0.9 -> 90000 | G59: =F59 -> 90000 | H59: =F59 -> 90000 | I59: =F59 -> 90000 | J59: =F59 -> 90000 | K59: =J59 -> 90000 | L59: =K59 -> 90000 | M59: =L59 -> 90000 | N59: =M59 -> 90000 | O59: =N59 -> 90000 | P59: =O59 -> 90000 | Q59: =P59 -> 90000 | R59: =Q59 -> 90000 | ... U59: =T59 -> 90000
B60: Material Replacement | C60: MZK | F60: =F20*0.9 -> 39600 | G60: =F60 -> 39600 | H60: =F60 -> 39600 | I60: =F60 -> 39600 | J60: =F60 -> 39600 | K60: =J60 -> 39600 | L60: =K60 -> 39600 | M60: =L60 -> 39600 | N60: =M60 -> 39600 | O60: =N60 -> 39600 | P60: =O60 -> 39600 | Q60: =P60 -> 39600 | R60: =Q60 -> 39600 | ... U60: =T60 -> 39600
B61: other | C61: MZk | F61: =F21*0.8 -> 35200 | G61: =F61 -> 35200 | H61: =F61 -> 35200 | I61: =F61 -> 35200 | J61: =F61 -> 35200 | K61: =J61 -> 35200 | L61: =K61 -> 35200 | M61: =L61 -> 35200 | N61: =M61 -> 35200 | O61: =N61 -> 35200 | P61: =O61 -> 35200 | Q61: =P61 -> 35200 | R61: =Q61 -> 35200 | ... U61: =T61 -> 35200
B62: Sub-total for Operating costs | D62: =D23 -> 0 | F62: =SUM(F56:F61) -> 7194800 | G62: =SUM(G56:G61) -> 2532300 | H62: =SUM(H56:H61) -> 7194800 | I62: =SUM(I56:I61) -> 7194800 | J62: =SUM(J56:J61) -> 7194800 | K62: =SUM(K56:K61) -> 7194800 | L62: =SUM(L56:L61) -> 7194800 | M62: =SUM(M56:M61) -> 7194800 | ... U62: =SUM(U56:U61) -> 7194800
D63: =D24 -> 0
B64: Fixed costs | D64: =D25 -> 0
B65: Depreciation | C65: MZK/annum | D65: =D26 -> 1 | F65: =D65*E65 -> 0 | G65: 0 | H65: =D65*E65 -> 0 | I65: =H65 -> 0 | J65: =I65 -> 0 | K65: =J65 -> 0 | L65: =K65 -> 0 | M65: =L65 -> 0 | N65: =M65 -> 0 | O65: =N65 -> 0 | P65: =O65 -> 0 | ... U65: =T65 -> 0 | V65: =SUM(H65:U65) -> 0
B66: Sub-total for Fixed costs | F66: =SUM(F65:F65) -> 0 | G66: =SUM(G65:G65) -> 0 | H66: =SUM(H65:H65) -> 0 | I66: =SUM(I65:I65) -> 0 | J66: =SUM(J65:J65) -> 0 | K66: =SUM(K65:K65) -> 0 | L66: =SUM(L65:L65) -> 0 | M66: =SUM(M65:M65) -> 0 | ... U66: =SUM(U65:U65) -> 0
B67: TOTAL COSTS | F67: =F53+F62+F66 -> 8364800 | G67: =G53+G62+G66 -> 3702300 | H67: =H53+H62+H66 -> 7194800 | I67: =I53+I62+I66 -> 7194800 | J67: =J53+J62+J66 -> 7194800 | K67: =K53+K62+K66 -> 7194800 | L67: =L53+L62+L66 -> 7194800 | M67: =M53+M62+M66 -> 7194800 | ... U67: =U53+U62+U66 -> 7194800
B69: GROSS MARGIN | C69: MZK/annum | G69: =G47-G53-G62 -> -1722300 | H69: =H47-H53-H62 -> 905200 | I69: =I47-I53-I62 -> 905200 | J69: =J47-J53-J62 -> 905200 | K69: =K47-K53-K62 -> 905200 | L69: =L47-L53-L62 -> 905200 | M69: =M47-M53-M62 -> 905200 | N69: =N47-N53-N62 -> 905200 | ... U69: =U47-U53-U62 -> 905200
B70: NET MARGIN | C70: MZK/annum | G70: =G69-G66 -> -1722300 | H70: =-(H69-H66) -> -905200 | I70: =I69-I66 -> 905200 | J70: =J69-J66 -> 905200 | K70: =K69-K66 -> 905200 | L70: =L69-L66 -> 905200 | M70: =M69-M66 -> 905200 | N70: =N69-N66 -> 905200 | O70: =O69-O66 -> 905200 | P70: =P69-P66 -> 905200 | ... U70: =U69-U66 -> 905200
B71: EIRR | G71: =IRR(G70:U70) -> 0.27935087
B72: ENPV | G72: =NPV(0.1,G70:U70) -> 3000188.5

Sheet Cross Ventilation Improvements
B1: FINANCIAL
C2: Unit | D2: Quantity | E2: Price | F2: Amount | G2: Year
B3: REVENUE | D3: With Project | G3: 1 | H3: =G3+1 -> 2 | I3: =H3+1 -> 3 | J3: =I3+1 -> 4 | K3: =J3+1 -> 5 | L3: =K3+1 -> 6 | M3: =L3+1 -> 7 | N3: =M3+1 -> 8 | O3: =N3+1 -> 9 | P3: =O3+1 -> 10 | Q3: 11 | R3: 12 | S3: 13 | T3: 14 | U3: 15
B4: Energy saved | C4: KWH/hr | D4: 1000 | E4: 2500 | H4: =I4 -> 2500000 | I4: =J4 -> 2500000 | J4: =D4*E4 -> 2500000 | K4: =J4*1.2 -> 3000000 | L4: =K4*1.2 -> 3600000 | M4: =L4*1.2 -> 4320000 | N4: =M4*1.2 -> 5184000 | O4: =N4*1.2 -> 6220800 | P4: =O4*1.2 -> 7464960 | Q4: =P4*1.2 -> 8957952 | R4: =Q4*1.2 -> 10749542 | ... U4: =T4*1.2 -> 18575209
B5: Time saved /productivity | C5: Hr | D5: 520 | E5: 100 | F5: =D5*E5 -> 52000 | G5: =F5 -> 52000 | H5: =F5 -> 52000 | I5: =H5 -> 52000 | J5: =I5 -> 52000 | K5: =J5 -> 52000 | L5: =K5 -> 52000 | M5: =L5 -> 52000 | N5: =M5 -> 52000 | O5: =N5 -> 52000 | P5: =O5 -> 52000 | ... U5: =T5 -> 52000
B6: Sub-total Revenue | F6: =SUM(F4:F5) -> 52000 | G6: =SUM(G4:G5) -> 52000 | H6: =SUM(H4:H5) -> 2552000 | I6: =SUM(I4:I5) -> 2552000 | J6: =SUM(J4:J5) -> 2552000 | K6: =SUM(K4:K5) -> 3052000 | L6: =SUM(L4:L5) -> 3652000 | M6: =SUM(M4:M5) -> 4372000 | ... U6: =SUM(U4:U5) -> 18627209
B8: CAPEX
B9: Investment Costs
B10: Cost of capital | C10: Nos. | D10: 500 | E10: 300 | F10: =D10*E10 -> 150000 | G10: =F10 -> 150000 | H10: =G10 -> 150000 | I10: 0 | J10: 0 | K10: 0
B11: Intallation | C11: lumpsum | D11: 1 | E11: 60000 | F11: =D11*E11 -> 60000 | G11: =F11 -> 60000 | H11: =G11 -> 60000 | I11: 0 | J11: 0 | K11: 0
B12: Sub-total Investment | F12: 0 | G12: 0 | H12: =SUM(H10:H11) -> 210000 | I12: =SUM(I10:I11) -> 0 | J12: =SUM(J10:J11) -> 0 | K12: =SUM(K10:K11) -> 0
F13: =D13*E13 -> 0
B14: OPEX | F14: =D14*E14 -> 0
B15: Wages and Labor | C15: MZK | D15: 10710 | E15: 1 | F15: =D15*E15 -> 10710 | G15: =F15 -> 10710 | H15: =F15 -> 10710 | I15: =H15 -> 10710 | J15: =I15 -> 10710 | K15: =J15 -> 10710 | L15: =K15 -> 10710 | M15: =L15 -> 10710 | N15: =M15 -> 10710 | O15: =N15 -> 10710 | P15: =O15 -> 10710 | ... T15: =S15 -> 10710 | U15: =T15*0.5 -> 5355
B16: Window and Vent Maintenance | C16: MZK | D16: 2000 | E16: 900 | F16: =D16*E16 -> 1800000 | G16: =F16 -> 1800000 | H16: =F16 -> 1800000 | I16: =H16 -> 1800000 | J16: =H16 -> 1800000 | K16: =J16 -> 1800000 | L16: =J16 -> 1800000 | M16: =L16 -> 1800000 | N16: =L16 -> 1800000 | O16: =N16 -> 1800000 | P16: =N16 -> 1800000 | Q16: =P16 -> 1800000 | R16: =P16 -> 1800000 | S16: =R16 -> 1800000 | T16: =R16 -> 1800000 | U16: =T16 -> 1800000
B17: Cleaning and Repair | C17: MZK | F17: 1000000 | G17: =F17 -> 1000000 | H17: =F17 -> 1000000 | I17: =H17 -> 1000000 | J17: =I17 -> 1000000 | K17: =J17 -> 1000000 | L17: =K17 -> 1000000 | M17: =L17 -> 1000000 | N17: =M17 -> 1000000 | O17: =N17 -> 1000000 | P17: =O17 -> 1000000 | ... U17: =T17 -> 1000000
B18: Ventilation Component Replacement | C18: MZK | F18: 2080000 | G18: =F18 -> 2080000 | H18: =G18 -> 2080000 | I18: =H18 -> 2080000 | J18: =I18 -> 2080000 | K18: =J18 -> 2080000 | L18: =K18 -> 2080000 | M18: =L18 -> 2080000 | N18: =M18 -> 2080000 | ... U18: =T18 -> 2080000
B19: Building Maintenance | C19: MZK | F19: 550000 | G19: =F19 -> 550000 | H19: =F19 -> 550000 | I19: =H19 -> 550000 | J19: =I19 -> 550000 | K19: =J19 -> 550000 | L19: =K19 -> 550000 | M19: =L19 -> 550000 | N19: =M19 -> 550000 | O19: =N19 -> 550000 | P19: =O19 -> 550000 | ... U19: =T19 -> 550000
B20: Sub-total for Operating costs | F20: =SUM(F15:F19) -> 5440710 | G20: =SUM(G15:G19) -> 5440710 | H20: =SUM(H15:H19) -> 5440710 | I20: =SUM(I15:I19) -> 5440710 | J20: =SUM(J15:J19) -> 5440710 | K20: =SUM(K15:K19) -> 5440710 | L20: =SUM(L15:L19) -> 5440710 | M20: =SUM(M15:M19) -> 5440710 | ... U20: =SUM(U15:U19) -> 5435355
B22: Fixed costs
B23: Depreciation | C23: MZK/annum | D23: 1 | E23: =E11/15 -> 4000 | F23: =D23*E23 -> 4000 | G23: =F23 -> 4000 | H23: =D23*E23 -> 4000 | I23: =H23 -> 4000 | J23: =I23 -> 4000 | K23: =J23 -> 4000 | L23: =K23 -> 4000 | M23: =L23 -> 4000 | N23: =M23 -> 4000 | O23: =N23 -> 4000 | P23: =O23 -> 4000 | ... U23: =T23 -> 4000 | V23: =SUM(H23:U23) -> 56000
B24: Sub-total for Fixed costs | F24: =F15 -> 10710 | G24: =G15 -> 10710 | H24: =H15 -> 10710 | I24: =I15 -> 10710 | J24: =J15 -> 10710 | K24: =K15 -> 10710 | L24: =L15 -> 10710 | M24: =M15 -> 10710 | ... U24: =U15 -> 5355
B25: TOTAL COSTS | F25: =F12+F20+F24 -> 5451420 | G25: =G12+G20+G24 -> 5451420 | H25: =H12+H20+H24 -> 5661420 | I25: =I12+I20+I24 -> 5451420 | J25: =J12+J20+J24 -> 5451420 | K25: =K12+K20+K24 -> 5451420 | L25: =L12+L20+L24 -> 5451420 | M25: =M12+M20+M24 -> 5451420 | ... U25: =U12+U20+U24 -> 5440710
B27: GROSS MARGIN | C27: MZK/annum | I27: =-(I6-I12-I20) -> 2888710 | J27: =J6-J12-J20 -> -2888710 | K27: =K6-K12-K20 -> -2388710 | L27: =L6-L12-L20 -> -1788710 | M27: =M6-M12-M20 -> -1068710 | N27: =N6-N12-N20 -> -204710 | O27: =O6-O12-O20 -> 832090 | P27: =P6-P12-P20 -> 2076250 | Q27: =Q6-Q12-Q20 -> 3569242 | ... U27: =U6-U12-U20 -> 13191854
B28: NET MARGIN | C28: MZK/annum | G28: =H28 -> -2878000 | H28: =I28 -> -2878000 | I28: =-(I27-I24) -> -2878000 | J28: =I28 -> -2878000 | K28: =K27-K24 -> -2399420 | L28: =L27-L24 -> -1799420 | M28: =(M27-M24) -> -1079420 | N28: =N27-N24 -> -215420 | O28: =O27-O24 -> 821380 | P28: =P27-P24 -> 2065540 | Q28: =Q27-Q24 -> 3558532 | R28: =R27-R24 -> 5350122.4 | S28: =S27-S24 -> 7500030.9 | T28: =T27-T24 -> 10079921 | U28: =U27-U24 -> 13186499
B29: FIRR | G29: =IRR(I28:U28) -> 0.16676295
B30: FNPV | G30: =-(NPV(0.1,G28:U28)) -> 202606.48
B41: ECONOMIC
C42: Unit | D42: Quantity | E42: Price | F42: Amount | G42: Year
B43: REVENUE | D43: With Project | G43: 1 | H43: =G43+1 -> 2 | I43: =H43+1 -> 3 | J43: =I43+1 -> 4 | K43: =J43+1 -> 5 | L43: =K43+1 -> 6 | M43: =L43+1 -> 7 | N43: =M43+1 -> 8 | O43: =N43+1 -> 9 | P43: =O43+1 -> 10 | Q43: 11 | R43: 12 | S43: 13 | T43: 14 | U43: 15
B44: Energy saved | C44: KWH/h | D44: =D4 -> 1000 | E44: =E4*0.9 -> 2250 | G44: 0 | H44: =F44 -> 0 | I44: =D44*E44*10 -> 22500000 | J44: =I44 -> 22500000 | K44: =J44 -> 22500000 | L44: =K44 -> 22500000 | M44: =L44 -> 22500000 | N44: =M44 -> 22500000 | O44: =N44 -> 22500000 | P44: =O44 -> 22500000 | Q44: =P44 -> 22500000 | ... U44: =T44 -> 22500000
B45: Time saved /productivity | C45: No | D45: =D5 -> 520 | E45: =E5*0.9 -> 90 | G45: =F45 -> 0 | H45: =F45 -> 0 | I45: =E45*D45 -> 46800 | J45: =I45 -> 46800 | K45: =J45 -> 46800 | L45: =K45 -> 46800 | M45: =L45 -> 46800 | N45: =M45 -> 46800 | O45: =N45 -> 46800 | P45: =O45 -> 46800 | Q45: =P45 -> 46800 | ... U45: =T45 -> 46800
B46: Sub-total Revenue | F46: =SUM(F44:F45) -> 0 | G46: =SUM(G44:G45) -> 0 | H46: =SUM(H44:H45) -> 0 | I46: =SUM(I44:I45) -> 22546800 | J46: =SUM(J44:J45) -> 22546800 | K46: =SUM(K44:K45) -> 22546800 | L46: =SUM(L44:L45) -> 22546800 | M46: =SUM(M44:M45) -> 22546800 | ... U46: =SUM(U44:U45) -> 22546800
B48: CAPEX
B49: Investment Costs
B50: Capital Investment | C50: Nos. | D50: =D10 -> 500 | E50: =E10*0.9 -> 270 | F50: =D50*E50 -> 135000 | G50: =D50*E50 -> 135000 | H50: =G50 -> 135000 | I50: 0 | J50: 0 | K50: 0
B51: Intallation cost | C51: lumpsum | D51: 1 | E51: =E11*0.9 -> 54000 | F51: =D51*E51 -> 54000 | G51: =D51*E51 -> 54000 | H51: =G51 -> 54000 | I51: 0 | J51: 0 | K51: 0
B52: Sub-total Investment | F52: =SUM(F50:F51) -> 189000 | G52: =SUM(G50:G51) -> 189000 | H52: =SUM(H50:H51) -> 189000 | I52: =SUM(I50:I51) -> 0 | J52: =SUM(J50:J51) -> 0 | K52: =SUM(K50:K51) -> 0
F53: =D53*E53 -> 0
B54: OPEX | F54: =D54*E54 -> 0
B55: Wages and Labor | C55: MZK | D55: 10700 | E55: =E15 -> 1 | F55: =D55*E55 -> 10700 | G55: =F55 -> 10700 | H55: =F55 -> 10700 | I55: =H55 -> 10700 | J55: =I55 -> 10700 | K55: =J55 -> 10700 | L55: =K55 -> 10700 | M55: =L55 -> 10700 | N55: =M55 -> 10700 | O55: =N55 -> 10700 | P55: =O55 -> 10700 | ... T55: =S55 -> 10700 | U55: =T55*0.5 -> 5350
B56: Window and Vent Maintenance | C56: MZK | D56: =D16*0.9 -> 1800 | E56: =E16 -> 900 | F56: =D56*E56 -> 1620000 | G56: =F56 -> 1620000 | H56: =F56 -> 1620000 | I56: =H56 -> 1620000 | J56: =H56 -> 1620000 | K56: =J56 -> 1620000 | L56: =J56 -> 1620000 | M56: =L56 -> 1620000 | N56: =L56 -> 1620000 | O56: =N56 -> 1620000 | P56: =N56 -> 1620000 | Q56: =P56 -> 1620000 | R56: =P56 -> 1620000 | S56: =R56 -> 1620000 | T56: =R56 -> 1620000 | U56: =T56 -> 1620000
B57: Cleaning and Repair | C57: MZK | E57: =E17*0.9 -> 0 | F57: =F17*0.9 -> 900000 | G57: =G17*0.9 -> 900000 | H57: =F57 -> 900000 | I57: =H57 -> 900000 | J57: =I57 -> 900000 | K57: =J57 -> 900000 | L57: =K57 -> 900000 | M57: =L57 -> 900000 | N57: =M57 -> 900000 | O57: =N57 -> 900000 | P57: =O57 -> 900000 | ... U57: =T57 -> 900000
B58: Ventilation Component Replacement | C58: MZK | F58: =F18*0.9 -> 1872000 | G58: =F58 -> 1872000 | H58: =G58 -> 1872000 | I58: =H58 -> 1872000 | J58: =I58 -> 1872000 | K58: =J58 -> 1872000 | L58: =K58 -> 1872000 | M58: =L58 -> 1872000 | N58: =M58 -> 1872000 | ... U58: =T58 -> 1872000
B59: Building Maintenance | C59: MZK | D59: 1 | E59: =E19*0.9 -> 0 | F59: =F19*0.9 -> 495000 | G59: =G19*0.9 -> 495000 | H59: =G59 -> 495000 | I59: =H59 -> 495000 | J59: =I59 -> 495000 | K59: =J59 -> 495000 | L59: =K59 -> 495000 | M59: =L59 -> 495000 | N59: =M59 -> 495000 | O59: =N59 -> 495000 | ... U59: =T59 -> 495000
B60: Sub-total for Operating costs | F60: =SUM(F55:F59) -> 4897700 | G60: =SUM(G55:G59) -> 4897700 | H60: =SUM(H55:H59) -> 4897700 | I60: =SUM(I55:I59) -> 4897700 | J60: =SUM(J55:J59) -> 4897700 | K60: =SUM(K55:K59) -> 4897700 | L60: =SUM(L55:L59) -> 4897700 | M60: =SUM(M55:M59) -> 4897700 | ... U60: =SUM(U55:U59) -> 4892350
B62: Fixed costs
B63: Depreciation | F63: =E23 -> 4000 | G63: =F63 -> 4000 | H63: =G63 -> 4000 | I63: =H63 -> 4000 | J63: =I63 -> 4000 | K63: =J63 -> 4000 | L63: =K63 -> 4000 | M63: =L63 -> 4000 | N63: =M63 -> 4000 | ... U63: =T63 -> 4000 | V63: =SUM(H63:U63) -> 56000
B64: Sub-total for Fixed costs | F64: =F24*0.9 -> 9639 | G64: =F64 -> 9639 | H64: =G64 -> 9639 | I64: =H64 -> 9639 | J64: =I64 -> 9639 | K64: =J64 -> 9639 | L64: =K64 -> 9639 | M64: =L64 -> 9639 | N64: =M64 -> 9639 | ... U64: =T64 -> 9639
B65: TOTAL COSTS | F65: =F52+F60+F64 -> 5096339 | G65: =G52+G60+G64 -> 5096339 | H65: =H52+H60+H64 -> 5096339 | I65: =I52+I60+I64 -> 4907339 | J65: =J52+J60+J64 -> 4907339 | K65: =K52+K60+K64 -> 4907339 | L65: =L52+L60+L64 -> 4907339 | M65: =M52+M60+M64 -> 4907339 | ... U65: =U52+U60+U64 -> 4901989
B67: GROSS MARGIN | C67: MZK/annum | I67: =I46-I52-I60 -> 17649100 | J67: =J46-J52-J60 -> 17649100 | K67: =K46-K52-K60 -> 17649100 | L67: =L46-L52-L60 -> 17649100 | M67: =M46-M52-M60 -> 17649100 | N67: =N46-N52-N60 -> 17649100 | O67: =O46-O52-O60 -> 17649100 | P67: =P46-P52-P60 -> 17649100 | ... U67: =U46-U52-U60 -> 17654450
B68: NET MARGIN | C68: MZK/annum | G68: =H68 -> 17639461 | H68: =I68 -> 17639461 | I68: =I67-I64 -> 17639461 | J68: =-(J67-J64) -> -17639461 | K68: =K67-K64 -> 17639461 | L68: =-(L67-L64) -> -17639461 | M68: =-(M67-M64) -> -17639461 | N68: =-(N67-N64) -> -17639461 | O68: =N68 -> -17639461 | P68: =O68 -> -17639461 | Q68: =P68 -> -17639461 | R68: =Q68 -> -17639461 | S68: =R68 -> -17639461 | T68: =S68 -> -17639461 | U68: =T68 -> -17639461
B69: EIRR | G69: =IRR(G68:U68) -> 0.16945185
B70: ENPV | G70: =-(NPV(0.1,G68:U68)) -> 24528250

Sheet External Shading (Awnings, Over
B1: FINANCIAL
C2: Unit | D2: Quantity | E2: Price | F2: Amount | G2: Year
B3: REVENUE | G3: 1 | H3: =G3+1 -> 2 | I3: =H3+1 -> 3 | J3: =I3+1 -> 4 | K3: =J3+1 -> 5 | L3: =K3+1 -> 6 | M3: =L3+1 -> 7 | N3: =M3+1 -> 8 | O3: =N3+1 -> 9 | P3: =O3+1 -> 10 | Q3: 11 | R3: 12 | S3: 13 | T3: 14 | U3: 15
B4: Milk | C4: Liter | D4: 0 | E4: 0 | F4: =D4*E4 -> 0 | H4: =F4 -> 0 | I4: =F4 -> 0 | J4: =F4 -> 0 | K4: =J4 -> 0 | L4: =K4 -> 0 | M4: =L4 -> 0 | N4: =M4 -> 0 | O4: =N4 -> 0 | P4: =O4 -> 0 | Q4: =P4 -> 0 | R4: =Q4 -> 0 | ... U4: =T4 -> 0
B5: - Manure | C5: Bags | D5: 50 | E5: 1000 | F5: =D5*E5 -> 50000 | G5: =F5 -> 50000 | H5: =D5*E5 -> 50000 | I5: =D5*E5 -> 50000 | J5: =D5*E5 -> 50000 | K5: =J5 -> 50000 | L5: =K5 -> 50000 | M5: =L5 -> 50000 | N5: =M5 -> 50000 | O5: =N5 -> 50000 | P5: =O5 -> 50000 | Q5: =P5 -> 50000 | R5: =Q5 -> 50000 | ... U5: =T5 -> 50000
B6: Selling of animal | C6: Nos | D6: 2 | E6: 150000 | F6: =E6*D6 -> 300000 | J6: =F6 -> 300000 | K6: =J6 -> 300000 | L6: =K6 -> 300000 | M6: =L6 -> 300000 | N6: =J6 -> 300000 | O6: =K6 -> 300000 | P6: =L6 -> 300000 | Q6: =M6 -> 300000 | R6: =N6 -> 300000 | S6: =O6 -> 300000 | T6: =P6 -> 300000 | U6: =Q6 -> 300000
B7: Sub-total Revenue | F7: =SUM(F4:F6) -> 350000 | G7: =SUM(G4:G6) -> 50000 | H7: =SUM(H4:H6) -> 50000 | I7: =SUM(I4:I6) -> 50000 | J7: =SUM(J4:J6) -> 350000 | K7: =SUM(K4:K6) -> 350000 | L7: =SUM(L4:L6) -> 350000 | M7: =SUM(M4:M6) -> 350000 | ... U7: =SUM(U4:U6) -> 350000
B9: COSTS
B10: Investment Costs
B11: Animal Cost | C11: lumpsum | D11: 2 | E11: 100000 | F11: =D11*E11 -> 200000 | G11: =D11*E11 -> 200000 | H11: 0 | I11: 0 | J11: 0 | P11: =K11 -> 0
B12: Other Fixed Cost | C12: lumpsum | D12: 2 | E12: 80000 | F12: =D12*E12 -> 160000 | G12: =D12*E12 -> 160000 | H12: 0 | I12: 0 | J12: 0 | K12: 0
B13: Sub-total Investment | F13: =SUM(F11:F12) -> 360000 | G13: =SUM(G11:G12) -> 360000 | H13: =SUM(H11:H12) -> 0 | I13: =SUM(I11:I12) -> 0 | J13: =SUM(J11:J12) -> 0 | K13: =SUM(K11:K12) -> 0 | L13: =SUM(L11:L12) -> 0 | M13: =SUM(M11:M12) -> 0 | ... U13: =SUM(U11:U12) -> 0
F14: =D14*E14 -> 0
B15: Operating costs | F15: =D15*E15 -> 0
B16: Fooder (Hay and Grains & Seeds) | C16: G$ | D16: 2 | E16: 10000 | F16: =D16*E16 -> 20000 | G16: =F16 -> 20000 | H16: =F16 -> 20000 | I16: =H16 -> 20000 | J16: =I16 -> 20000 | K16: =J16 -> 20000 | L16: =K16 -> 20000 | M16: =L16 -> 20000 | N16: =M16 -> 20000 | O16: =N16 -> 20000 | P16: =O16 -> 20000 | ... U16: =T16 -> 20000
B17: Wages and Salary | C17: G$ | D17: 0 | E17: 1000 | F17: =15*E17 -> 15000 | G17: =F17 -> 15000 | H17: =F17 -> 15000 | I17: =H17 -> 15000 | J17: =I17 -> 15000 | K17: =J17 -> 15000 | L17: =K17 -> 15000 | M17: =L17 -> 15000 | N17: =M17 -> 15000 | O17: =N17 -> 15000 | P17: =O17 -> 15000 | ... U17: =T17 -> 15000
B18: Veterinary Expenses | C18: G$ | D18: 2 | E18: 10000 | F18: 3000 | G18: =F18 -> 3000 | H18: =D18*E18*1 -> 20000 | I18: =D18*E18*1 -> 20000 | J18: =D18*E18 -> 20000 | K18: =J18 -> 20000 | L18: =K18 -> 20000 | M18: =L18 -> 20000 | N18: =M18 -> 20000 | O18: =N18 -> 20000 | P18: =O18 -> 20000 | Q18: =P18 -> 20000 | R18: =Q18 -> 20000 | ... U18: =T18 -> 20000
B19: herd management and sanitation | C19: G$ | D19: 2 | E19: 300 | F19: =D19*E19 -> 600 | G19: =F19 -> 600 | H19: =F19 -> 600 | I19: =H19 -> 600 | J19: =I19 -> 600 | K19: =J19 -> 600 | L19: =K19 -> 600 | M19: =L19 -> 600 | N19: =M19 -> 600 | O19: =N19 -> 600 | P19: =O19 -> 600 | ... U19: =T19 -> 600
B20: Vaccination and medication | C20: G$ | D20: 2 | E20: 8000 | F20: =D20*E20 -> 16000 | G20: =F20 -> 16000 | H20: =G20 -> 16000 | I20: =H20 -> 16000 | J20: =I20 -> 16000 | K20: =J20 -> 16000 | L20: =K20 -> 16000 | M20: =L20 -> 16000 | N20: =M20 -> 16000 | ... U20: =T20 -> 16000
B21: coral maintenance | C21: G4 | D21: 1 | E21: 15000 | F21: =D21*E21 -> 15000 | G21: =F21 -> 15000 | H21: =F21 -> 15000 | I21: =F21 -> 15000 | J21: =F21 -> 15000 | K21: =J21 -> 15000 | L21: =K21 -> 15000 | M21: =L21 -> 15000 | N21: =M21 -> 15000 | O21: =N21 -> 15000 | P21: =O21 -> 15000 | Q21: =P21 -> 15000 | R21: =Q21 -> 15000 | ... U21: =T21 -> 15000
B22: Sub-total for Operating costs | F22: =SUM(F16:F21) -> 69600 | G22: =SUM(G16:G21) -> 69600 | H22: =SUM(H16:H21) -> 86600 | I22: =SUM(I16:I21) -> 86600 | J22: =SUM(J16:J21) -> 86600 | K22: =SUM(K16:K21) -> 86600 | L22: =SUM(L16:L21) -> 86600 | M22: =SUM(M16:M21) -> 86600 | ... U22: =SUM(U16:U21) -> 86600
B24: Fixed costs
B25: Depreciation | C25: G$/annum | D25: 1 | E25: =E12/15 -> 5333.3333 | F25: =D25*E25 -> 5333.3333 | G25: =F25 -> 5333.3333 | H25: =D25*E25 -> 5333.3333 | I25: =H25 -> 5333.3333 | J25: =I25 -> 5333.3333 | K25: =J25 -> 5333.3333 | L25: =K25 -> 5333.3333 | M25: =L25 -> 5333.3333 | N25: =M25 -> 5333.3333 | O25: =N25 -> 5333.3333 | P25: =O25 -> 5333.3333 | ... U25: =T25 -> 5333.3333 | V25: =SUM(H25:U25) -> 74666.667
B26: Sub-total for Fixed costs | F26: =SUM(F25:F25) -> 5333.3333 | G26: =SUM(G25:G25) -> 5333.3333 | H26: =SUM(H25:H25) -> 5333.3333 | I26: =SUM(I25:I25) -> 5333.3333 | J26: =SUM(J25:J25) -> 5333.3333 | K26: =SUM(K25:K25) -> 5333.3333 | L26: =SUM(L25:L25) -> 5333.3333 | M26: =SUM(M25:M25) -> 5333.3333 | ... U26: =SUM(U25:U25) -> 5333.3333
B27: TOTAL COSTS | F27: =F13+F22+F26 -> 434933.33 | G27: =G13+G22+G26 -> 434933.33 | H27: =H13+H22+H26 -> 91933.333 | I27: =I13+I22+I26 -> 91933.333 | J27: =J13+J22+J26 -> 91933.333 | K27: =K13+K22+K26 -> 91933.333 | L27: =L13+L22+L26 -> 91933.333 | M27: =M13+M22+M26 -> 91933.333 | ... U27: =U13+U22+U26 -> 91933.333
B29: GROSS MARGIN | C29: G$/annum | G29: =G7-G13-G22 -> -379600 | H29: =H7-H13-H22 -> -36600 | I29: =I7-I13-I22 -> -36600 | J29: =J7-J13-J22 -> 263400 | K29: =K7-K13-K22 -> 263400 | L29: =L7-L13-L22 -> 263400 | M29: =M7-M13-M22 -> 263400 | N29: =N7-N13-N22 -> 263400 | ... U29: =U7-U13-U22 -> 263400
B30: NET MARGIN BEFORE PROFIT TAX | C30: G$/annum | G30: =G29-G26 -> -384933.33 | H30: =H29-H26 -> -41933.333 | I30: =I29-I26 -> -41933.333 | J30: =J29-J26 -> 258066.67 | K30: =K29-K26 -> 258066.67 | L30: =L29-L26 -> 258066.67 | M30: =M29-M26 -> 258066.67 | N30: =N29-N26 -> 258066.67 | ... U30: =U29-U26 -> 258066.67
B31: FIRR | G31: =IRR(G30:U30) -> 0.32300371
B32: FNPV | G32: =NPV(0.1,G30:U30) -> 905001.81
B34: ECONOMIC
C35: Unit | D35: Quantity | E35: Price | F35: Amount | G35: Year
B36: REVENUE | G36: 1 | H36: =G36+1 -> 2 | I36: =H36+1 -> 3 | J36: =I36+1 -> 4 | K36: =J36+1 -> 5 | L36: =K36+1 -> 6 | M36: =L36+1 -> 7 | N36: =M36+1 -> 8 | O36: =N36+1 -> 9 | P36: =O36+1 -> 10 | Q36: 11 | R36: 12 | S36: 13 | T36: 14 | U36: 15
B37: Milk | C37: Liter | D37: 0 | E37: =E4*0.9 -> 0 | F37: =D37*E37 -> 0 | H37: =F37 -> 0 | I37: =F37 -> 0 | J37: =F37 -> 0 | K37: =J37 -> 0 | L37: =K37 -> 0 | M37: =L37 -> 0 | N37: =M37 -> 0 | O37: =N37 -> 0 | P37: =O37 -> 0 | Q37: =P37 -> 0 | R37: =Q37 -> 0 | ... U37: =T37 -> 0
B38: - Manure | C38: Bags | D38: =D5 -> 50 | E38: =E5*0.9 -> 900 | F38: =D38*E38 -> 45000 | G38: =F38 -> 45000 | H38: =D38*E38 -> 45000 | I38: =D38*E38 -> 45000 | J38: =D38*E38 -> 45000 | K38: =J38 -> 45000 | L38: =K38 -> 45000 | M38: =L38 -> 45000 | N38: =M38 -> 45000 | O38: =N38 -> 45000 | P38: =O38 -> 45000 | Q38: =P38 -> 45000 | R38: =Q38 -> 45000 | ... U38: =T38 -> 45000
B39: Selling of animal | C39: Nos. | D39: =D6 -> 2 | E39: =E6 -> 150000 | F39: =D39*E39 -> 300000 | G39: =F39 -> 300000 | H39: =G39 -> 300000 | I39: =H39 -> 300000 | J39: =I39 -> 300000 | K39: =J39 -> 300000 | L39: =K39 -> 300000 | M39: =L39 -> 300000 | N39: =M39 -> 300000 | ... P39: =O39 -> 300000 | U39: =P39 -> 300000
B40: Sub-total Revenue | D40: =D7 -> 0 | E40: =E7*0.9 -> 0 | F40: =SUM(F37:F39) -> 345000 | G40: =SUM(G37:G39) -> 345000 | H40: =SUM(H37:H39) -> 345000 | I40: =SUM(I37:I39) -> 345000 | J40: =SUM(J37:J39) -> 345000 | K40: =SUM(K37:K39) -> 345000 | L40: =SUM(L37:L39) -> 345000 | M40: =SUM(M37:M39) -> 345000 | ... U40: =SUM(U37:U39) -> 345000
D41: =D8 -> 0 | E41: =E8*0.9 -> 0
B42: COSTS | D42: =D9 -> 0 | E42: =E9*0.9 -> 0
B43: Investment Costs | D43: =D10 -> 0 | E43: =E10*0.9 -> 0
B44: Animal Cost | C44: Nos. | D44: =D11 -> 2 | E44: =E11*0.9 -> 90000 | F44: =D44*E44 -> 180000 | G44: =D44*E44 -> 180000 | H44: 0 | I44: 0 | J44: 0 | P44: =K44 -> 0
B45: Other Fixed Cost | C45: lumpsum | D45: =D12 -> 2 | E45: =E12*0.9 -> 72000 | F45: =D45*E45 -> 144000 | G45: =D45*E45 -> 144000 | H45: 0 | I45: 0 | J45: 0 | K45: 0
B46: Sub-total Investment | D46: =D13 -> 0 | E46: =E13*0.9 -> 0 | F46: =SUM(F44:F45) -> 324000 | G46: =SUM(G44:G45) -> 324000 | H46: =SUM(H44:H45) -> 0 | I46: =SUM(I44:I45) -> 0 | J46: =SUM(J44:J45) -> 0 | K46: =SUM(K44:K45) -> 0 | L46: =SUM(L44:L45) -> 0 | M46: =SUM(M44:M45) -> 0 | ... U46: =SUM(U44:U45) -> 0
D47: =D14 -> 0 | E47: =E14*0.9 -> 0 | F47: =D47*E47 -> 0
B48: Operating costs | D48: =D15 -> 0 | E48: =E15*0.9 -> 0 | F48: =D48*E48 -> 0
B49: Fooder (Hay and Grains & Seeds) | D49: 2 | E49: =E16*0.9 -> 9000 | F49: =D49*E49 -> 18000 | G49: =F49 -> 18000 | H49: =G49 -> 18000 | I49: =H49 -> 18000 | J49: =I49 -> 18000 | K49: =J49 -> 18000 | L49: =K49 -> 18000 | M49: =L49 -> 18000 | N49: =M49 -> 18000 | ... U49: =T49 -> 18000
B50: Wages and Salary | C50: G$ | D50: 2 | E50: =E17 -> 1000 | F50: =D50*E50 -> 2000 | G50: =F50 -> 2000 | H50: =D50*E50*1 -> 2000 | I50: =D50*E50*1 -> 2000 | J50: =D50*E50 -> 2000 | K50: =J50 -> 2000 | L50: =K50 -> 2000 | M50: =L50 -> 2000 | N50: =M50 -> 2000 | O50: =N50 -> 2000 | P50: =O50 -> 2000 | Q50: =P50 -> 2000 | R50: =Q50 -> 2000 | ... U50: =T50 -> 2000
B51: Veterinary Expenses | C51: G$ | D51: 2 | E51: =E18*0.9 -> 9000 | F51: =D51*E51 -> 18000 | G51: =F51*0.5 -> 9000 | H51: =F51 -> 18000 | I51: =H51 -> 18000 | J51: =I51 -> 18000 | K51: =J51 -> 18000 | L51: =K51 -> 18000 | M51: =L51 -> 18000 | N51: =M51 -> 18000 | O51: =N51 -> 18000 | P51: =O51 -> 18000 | ... U51: =T51 -> 18000
B52: Herd management and sanitation | C52: G$ | D52: 2 | E52: =E19*0.9 -> 270 | F52: =D52*E52 -> 540 | G52: =F52 -> 540 | H52: =F52 -> 540 | I52: =F52 -> 540 | J52: =F52 -> 540 | K52: =J52 -> 540 | L52: =K52 -> 540 | M52: =L52 -> 540 | N52: =M52 -> 540 | O52: =N52 -> 540 | P52: =O52 -> 540 | Q52: =P52 -> 540 | R52: =Q52 -> 540 | ... U52: =T52 -> 540
B53: Vaccination and medication | C53: G$ | D53: 2 | E53: =E20*0.9 -> 7200 | F53: =D53*E53 -> 14400 | G53: =F53 -> 14400 | H53: =D53*E53*1 -> 14400 | I53: =D53*E53*1 -> 14400 | J53: =D53*E53 -> 14400 | K53: =J53 -> 14400 | L53: =K53 -> 14400 | M53: =L53 -> 14400 | N53: =M53 -> 14400 | O53: =N53 -> 14400 | P53: =O53 -> 14400 | Q53: =P53 -> 14400 | R53: =Q53 -> 14400 | ... U53: =T53 -> 14400
B54: coral maintenance | C54: G$ | D54: 1 | E54: =E21*0.9 -> 13500 | F54: =D54*E54 -> 13500 | G54: =F54 -> 13500 | H54: =D54*E54*1 -> 13500 | I54: =D54*E54*1 -> 13500 | J54: =D54*E54 -> 13500 | K54: =J54 -> 13500 | L54: =K54 -> 13500 | M54: =L54 -> 13500 | N54: =M54 -> 13500 | O54: =N54 -> 13500 | P54: =O54 -> 13500 | Q54: =P54 -> 13500 | R54: =Q54 -> 13500 | ... U54: =T54 -> 13500
B55: Sub-total for Operating costs | D55: =D22 -> 0 | F55: =SUM(F49:F54) -> 66440 | G55: =SUM(G49:G54) -> 57440 | H55: =SUM(H49:H54) -> 66440 | I55: =SUM(I49:I54) -> 66440 | J55: =SUM(J49:J54) -> 66440 | K55: =SUM(K49:K54) -> 66440 | L55: =SUM(L49:L54) -> 66440 | M55: =SUM(M49:M54) -> 66440 | ... U55: =SUM(U49:U54) -> 66440
D56: =D23 -> 0
B57: Fixed costs | D57: =D24 -> 0
B58: Depreciation (Shed) | C58: G$/annum | D58: =D25 -> 1 | F58: =D58*E58 -> 0 | G58: 0 | H58: =D58*E58 -> 0 | I58: =H58 -> 0 | J58: =I58 -> 0 | K58: =J58 -> 0 | L58: =K58 -> 0 | M58: =L58 -> 0 | N58: =M58 -> 0 | O58: =N58 -> 0 | P58: =O58 -> 0 | ... U58: =T58 -> 0 | V58: =SUM(H58:U58) -> 0
B59: Sub-total for Fixed costs | F59: =SUM(F58:F58) -> 0 | G59: =SUM(G58:G58) -> 0 | H59: =SUM(H58:H58) -> 0 | I59: =SUM(I58:I58) -> 0 | J59: =SUM(J58:J58) -> 0 | K59: =SUM(K58:K58) -> 0 | L59: =SUM(L58:L58) -> 0 | M59: =SUM(M58:M58) -> 0 | ... U59: =SUM(U58:U58) -> 0
B60: TOTAL COSTS | F60: =F46+F55+F59 -> 390440 | G60: =G46+G55+G59 -> 381440 | H60: =H46+H55+H59 -> 66440 | I60: =I46+I55+I59 -> 66440 | J60: =J46+J55+J59 -> 66440 | K60: =K46+K55+K59 -> 66440 | L60: =L46+L55+L59 -> 66440 | M60: =M46+M55+M59 -> 66440 | ... U60: =U46+U55+U59 -> 66440
B62: GROSS MARGIN | C62: G$/annum | G62: =G40-G46-G55 -> -36440 | H62: =H40-H46-H55 -> 278560 | I62: =I40-I46-I55 -> 278560 | J62: =J40-J46-J55 -> 278560 | K62: =K40-K46-K55 -> 278560 | L62: =L40-L46-L55 -> 278560 | M62: =M40-M46-M55 -> 278560 | N62: =N40-N46-N55 -> 278560 | ... U62: =U40-U46-U55 -> 278560
B63: NET MARGIN | C63: G$/annum | G63: =G62-G59 -> -36440 | H63: =-(H62-H59) -> -278560 | I63: =-(I62-I59) -> -278560 | J63: =J62-J59 -> 278560 | K63: =K62-K59 -> 278560 | L63: =L62-L59 -> 278560 | M63: =M62-M59 -> 278560 | N63: =N62-N59 -> 278560 | O63: =O62-O59 -> 278560 | P63: =P62-P59 -> 278560 | Q63: =Q62-Q59 -> -21440 | ... U63: =U62-U59 -> 278560
B64: EIRR | G64: =IRR(G63:U63) -> 0.33955408
B65: ENPV | G65: =NPV(0.1,G63:U63) -> 586747.51

Sheet Efficient Fans (DC or Energy-Ef
B1: FINANCIAL
C2: Unit | D2: Quantity | E2: Price | F2: Amount | G2: Year
B3: REVENUE | G3: 1 | H3: =G3+1 -> 2 | I3: =H3+1 -> 3 | J3: =I3+1 -> 4 | K3: =J3+1 -> 5 | L3: =K3+1 -> 6 | M3: =L3+1 -> 7 | N3: =M3+1 -> 8 | O3: =N3+1 -> 9 | P3: =O3+1 -> 10 | Q3: 11 | R3: 12 | S3: 13 | T3: 14 | U3: 15
B4: Sales from cassava bread | C4: kg | D4: 8000 | E4: 600 | F4: 0 | G4: 0 | H4: =I4 -> 4800000 | I4: =J4 -> 4800000 | J4: =D4*E4 -> 4800000 | K4: =J4 -> 4800000 | L4: =K4 -> 4800000 | M4: =L4 -> 4800000 | N4: =M4 -> 4800000 | O4: =N4 -> 4800000 | P4: =O4 -> 4800000 | Q4: =P4 -> 4800000 | R4: =Q4 -> 4800000 | ... U4: =T4 -> 4800000
B5: Sales from other diversification (Cassava jam, Cassava chips, Cassava cake) | C5: Lumpsum | D5: 1 | E5: 350000 | F5: 0 | H5: =E5 -> 350000 | I5: =E5 -> 350000 | J5: =I5 -> 350000 | K5: =J5 -> 350000 | L5: =K5 -> 350000 | M5: =L5 -> 350000 | N5: =M5 -> 350000 | O5: =N5 -> 350000 | P5: =O5 -> 350000 | Q5: =P5 -> 350000 | ... U5: =T5 -> 350000
K6: =J6 -> 0 | L6: =K6 -> 0 | M6: =L6 -> 0 | N6: =M6 -> 0 | O6: =N6 -> 0 | P6: =O6 -> 0 | Q6: =P6 -> 0 | R6: =Q6 -> 0 | ... U6: =T6 -> 0
G7: =F7 -> 0 | H7: =F7 -> 0 | I7: =G7 -> 0 | J7: =H7 -> 0 | K7: =J7 -> 0 | L7: =K7 -> 0 | M7: =L7 -> 0 | N7: =M7 -> 0 | O7: =N7 -> 0 | P7: =O7 -> 0 | Q7: =P7 -> 0 | R7: =Q7 -> 0 | ... U7: =T7 -> 0
B8: Sub-total Revenue | F8: =SUM(F4:F7) -> 0 | G8: =SUM(G4:G7) -> 0 | H8: =SUM(H4:H7) -> 5150000 | I8: =SUM(I4:I7) -> 5150000 | J8: =SUM(J4:J7) -> 5150000 | K8: =SUM(K4:K7) -> 5150000 | L8: =SUM(L4:L7) -> 5150000 | M8: =SUM(M4:M7) -> 5150000 | ... U8: =SUM(U4:U7) -> 5150000
B10: COSTS
B11: Investment Costs
B12: Fixed Capital, buliding construction and other equipment | C12: ha | D12: 10 | E12: 300000 | F12: =D12*E12 -> 3000000 | G12: =D12*E12 -> 3000000 | H12: =G12 -> 3000000 | I12: 0 | L12: 10000 | O12: 10000 | R12: 10000 | U12: 10000
B13: Sub-total Investment | F13: =SUM(F12:F12) -> 3000000 | G13: =SUM(G12:G12) -> 3000000 | H13: =SUM(H12:H12) -> 3000000 | I13: =SUM(I12:I12) -> 0 | J13: =SUM(J12:J12) -> 0 | K13: =SUM(K12:K12) -> 0 | L13: =SUM(L12:L12) -> 10000 | M13: =SUM(M12:M12) -> 0 | ... U13: =SUM(U12:U12) -> 10000
F14: =D14*E14 -> 0
B15: Operating costs | F15: =D15*E15 -> 0
B16: Raw materials | C16: G$ | D16: 10 | E16: 1000 | F16: =E16*D16 -> 10000 | G16: =F16 -> 10000 | H16: =G16 -> 10000 | I16: =H16 -> 10000 | J16: =I16 -> 10000 | K16: =J16 -> 10000 | L16: =K16 -> 10000 | M16: =L16 -> 10000 | N16: =M16 -> 10000 | ... U16: =T16 -> 10000
B17: Wages and salary | C17: G$ | D17: 200 | E17: 1500 | F17: =D17*E17 -> 300000 | G17: =F17 -> 300000 | H17: =G17 -> 300000 | I17: =H17 -> 300000 | J17: =I17 -> 300000 | K17: =J17 -> 300000 | L17: =K17 -> 300000 | M17: =L17 -> 300000 | N17: =M17 -> 300000 | ... U17: =T17 -> 300000
B18: other | C18: G$ | F18: =J4*0.4 -> 1920000 | G18: =F18 -> 1920000 | H18: =G18 -> 1920000 | I18: =H18 -> 1920000 | J18: =J4*0.75 -> 3600000 | K18: =J18 -> 3600000 | L18: =K18 -> 3600000 | M18: =L18 -> 3600000 | N18: =M18 -> 3600000 | O18: =N18 -> 3600000 | P18: =O18 -> 3600000 | Q18: =P18 -> 3600000 | R18: =Q18 -> 3600000 | ... U18: =T18 -> 3600000
B19: Transportation | C19: G$ | F19: 905000 | G19: =F19 -> 905000 | H19: =G19 -> 905000 | I19: =H19 -> 905000 | J19: 10000 | K19: =J19 -> 10000 | L19: =K19 -> 10000 | M19: =L19 -> 10000 | N19: =M19 -> 10000 | O19: =N19 -> 10000 | P19: =O19 -> 10000 | Q19: =P19 -> 10000 | R19: =Q19 -> 10000 | ... U19: =T19 -> 10000
B20: equipment | C20: G$ | F20: 900000 | G20: =F20 -> 900000 | H20: =G20 -> 900000 | I20: =H20 -> 900000 | J20: =I20 -> 900000 | K20: =J20 -> 900000 | L20: =K20 -> 900000 | M20: =L20 -> 900000 | N20: =M20 -> 900000 | ... U20: =T20 -> 900000
B21: Damage | C21: G$ | F21: 8900 | G21: =F21 -> 8900 | H21: =G21 -> 8900 | I21: =H21 -> 8900 | J21: =I21 -> 8900 | K21: =J21 -> 8900 | L21: =K21 -> 8900 | M21: =L21 -> 8900 | N21: =M21 -> 8900 | ... U21: =T21 -> 8900
B23: Sub-total for Operating costs | F23: =SUM(F16:F22) -> 4043900 | G23: =SUM(G16:G22) -> 4043900 | H23: =SUM(H16:H22) -> 4043900 | I23: =SUM(I16:I22) -> 4043900 | J23: =SUM(J16:J22) -> 4828900 | K23: =SUM(K16:K22) -> 4828900 | L23: =SUM(L16:L22) -> 4828900 | M23: =SUM(M16:M22) -> 4828900 | ... U23: =SUM(U16:U22) -> 4828900
B25: Fixed costs
B26: Depreciation | C26: G$/anuum | D26: 1 | E26: =E12/15 -> 20000 | F26: =D26*E26 -> 20000 | H26: =D26*E26 -> 20000 | I26: =H26 -> 20000 | J26: =I26 -> 20000 | K26: =J26 -> 20000 | L26: =K26 -> 20000 | M26: =L26 -> 20000 | N26: =M26 -> 20000 | O26: =N26 -> 20000 | P26: =O26 -> 20000 | ... U26: =T26 -> 20000 | V26: =SUM(H26:U26) -> 280000
B27: Sub-total for Fixed costs | F27: =SUM(F26:F26) -> 20000 | G27: =SUM(G26:G26) -> 0 | H27: =SUM(H26:H26) -> 20000 | I27: =SUM(I26:I26) -> 20000 | J27: =SUM(J26:J26) -> 20000 | K27: =SUM(K26:K26) -> 20000 | L27: =SUM(L26:L26) -> 20000 | M27: =SUM(M26:M26) -> 20000 | ... U27: =SUM(U26:U26) -> 20000
B28: TOTAL COSTS | F28: =F13+F23+F27 -> 7063900 | G28: =G13+G23+G27 -> 7043900 | H28: =H13+H23+H27 -> 7063900 | I28: =I13+I23+I27 -> 4063900 | J28: =J13+J23+J27 -> 4848900 | K28: =K13+K23+K27 -> 4848900 | L28: =L13+L23+L27 -> 4858900 | M28: =M13+M23+M27 -> 4848900 | ... U28: =U13+U23+U27 -> 4858900
B30: GROSS MARGIN | C30: G$s/annum | G30: =G8-G13-G23 -> -7043900 | H30: =H8-H13-H23 -> -1893900 | I30: =I8-I13-I23 -> 1106100 | J30: =J8-J13-J23 -> 321100 | K30: =K8-K13-K23 -> 321100 | L30: =L8-L13-L23 -> 311100 | M30: =M8-M13-M23 -> 321100 | N30: =N8-N13-N23 -> 321100 | ... U30: =U8-U13-U23 -> 311100
B31: NET MARGIN BEFORE PROFIT TAX | C31: G$s/annum | G31: =G30-G27 -> -7043900 | H31: =H30-H27 -> -1913900 | I31: =I30-I27 -> 1086100 | J31: =J30-J27 -> 301100 | K31: =K30-K27 -> 301100 | L31: =L30-L27 -> 291100 | M31: =M30-M27 -> 301100 | N31: =N30-N27 -> 301100 | ... U31: =U30-U27 -> 291100
B32: FIRR | G32: =IRR(H31:U31) -> 0.21726914
B33: FNPV | G33: =NPV(0.1,G31:U31) -> -5643344.5
B36: ECONOMIC
C37: Unit | D37: Quantity | E37: Price | F37: Amount | G37: Year
B38: REVENUE | G38: 1 | H38: =G38+1 -> 2 | I38: =H38+1 -> 3 | J38: =I38+1 -> 4 | K38: =J38+1 -> 5 | L38: =K38+1 -> 6 | M38: =L38+1 -> 7 | N38: =M38+1 -> 8 | O38: =N38+1 -> 9 | P38: =O38+1 -> 10 | Q38: 11 | R38: 12 | S38: 13 | T38: 14 | U38: 15
B39: Sales | C39: lumpsum | D39: =D4 -> 8000 | E39: =E4*1.1 -> 660 | F39: =F4*0.9 -> 0 | G39: =F39 -> 0 | H39: =J39 -> 4320000 | I39: =J39 -> 4320000 | J39: =J4*0.9 -> 4320000 | K39: =J39 -> 4320000 | L39: =K39 -> 4320000 | M39: =L39 -> 4320000 | N39: =M39 -> 4320000 | O39: =N39 -> 4320000 | P39: =O39 -> 4320000 | Q39: =P39 -> 4320000 | R39: =Q39 -> 4320000 | ... U39: =T39 -> 4320000
B40: Income from gum arabic export | C40: lumpsum | D40: 1 | E40: =E5 -> 350000 | F40: =F7*0.9 -> 0 | G40: =F40 -> 0 | H40: =J40 -> 315000 | I40: =H40 -> 315000 | J40: =E40*0.9 -> 315000 | K40: =J40 -> 315000 | L40: =K40 -> 315000 | M40: =L40 -> 315000 | N40: =M40 -> 315000 | O40: =N40 -> 315000 | P40: =O40 -> 315000 | Q40: =P40 -> 315000 | R40: =Q40 -> 315000 | ... U40: =T40 -> 315000
J41: =E41*0.9 -> 0 | K41: =F41*0.9 -> 0 | L41: =G41*0.9 -> 0 | M41: =H41*0.9 -> 0 | N41: =I41*0.9 -> 0 | O41: =J41*0.9 -> 0 | P41: =K41*0.9 -> 0 | Q41: =L41*0.9 -> 0 | ... U41: =P41*0.9 -> 0
B42: Sub-total Revenue | D42: =D8 -> 0 | E42: =E8*0.9 -> 0 | F42: =SUM(F39:F41) -> 0 | G42: =SUM(G39:G41) -> 0 | H42: =SUM(H39:H41) -> 4635000 | I42: =I8 -> 5150000 | J42: =SUM(J39:J41) -> 4635000 | K42: =SUM(K39:K41) -> 4635000 | L42: =SUM(L39:L41) -> 4635000 | M42: =SUM(M39:M41) -> 4635000 | N42: =SUM(N39:N41) -> 4635000 | O42: =SUM(O39:O41) -> 4635000 | P42: =SUM(P39:P41) -> 4635000 | Q42: =SUM(Q39:Q41) -> 4635000 | ... U42: =SUM(U39:U41) -> 4635000
D43: =D9 -> 0 | E43: =E9*0.9 -> 0
B44: COSTS | D44: =D10 -> 0 | E44: =E10*0.9 -> 0
B45: Investment Costs | D45: =D11 -> 0 | E45: =E11*0.9 -> 0
B46: Fixed Capital, buliding construction and other equipment | C46: Nos. | D46: 10 | E46: =E12*0.9 -> 270000 | F46: =F12*0.9 -> 2700000 | G46: =G12 -> 3000000 | I46: 0 | J46: 0 | P46: =K46 -> 0
B48: Sub-total Investment | D48: =D13 -> 0 | E48: =E13*0.9 -> 0 | F48: =SUM(F46:F47) -> 2700000 | G48: =SUM(G46:G47) -> 3000000 | H48: =SUM(H46:H47) -> 0 | J48: =SUM(J46:J47) -> 0 | K48: =SUM(K46:K47) -> 0 | M48: =SUM(M46:M47) -> 0 | N48: =SUM(N46:N47) -> 0 | P48: =SUM(P46:P47) -> 0 | Q48: =SUM(Q46:Q47) -> 0 | R48: 10000 | S48: =SUM(S46:S47) -> 0 | T48: =SUM(T46:T47) -> 0 | U48: 10000
D49: =D14 -> 0 | E49: =E14*0.9 -> 0 | F49: =D49*E49 -> 0
B50: Operating costs | D50: =D15 -> 0 | E50: =E15*0.9 -> 0 | F50: =D50*E50 -> 0
B51: Raw materials | C51: G$ | F51: =F16*0.9 -> 9000 | G51: =F51 -> 9000 | H51: =G51 -> 9000 | I51: =H51 -> 9000 | J51: =I51 -> 9000 | K51: =J51 -> 9000 | L51: =K51 -> 9000 | M51: =L51 -> 9000 | N51: =M51 -> 9000 | ... U51: =T51 -> 9000
B52: Black tanks | C52: G$ | F52: =F17*0.9 -> 270000 | G52: =F52 -> 270000 | H52: =G52 -> 270000 | I52: =H52 -> 270000 | J52: =I52 -> 270000 | K52: =J52 -> 270000 | L52: =K52 -> 270000 | M52: =L52 -> 270000 | N52: =M52 -> 270000 | ... U52: =T52 -> 270000
B53: Wage and salary | C53: G$ | F53: =F18*0.9 -> 1728000 | G53: =F53 -> 1728000 | H53: =F53 -> 1728000 | I53: =H53 -> 1728000 | J53: =J42*0.6 -> 2781000 | K53: =J53 -> 2781000 | L53: =K53 -> 2781000 | M53: =L53 -> 2781000 | N53: =M53 -> 2781000 | O53: =N53 -> 2781000 | P53: =O53 -> 2781000 | Q53: =P53 -> 2781000 | R53: =Q53 -> 2781000 | ... U53: =T53 -> 2781000
B54: Transportation | C54: G$ | F54: =F19*0.8 -> 724000 | G54: =F54 -> 724000 | H54: =F54 -> 724000 | I54: =F54 -> 724000 | J54: =F54 -> 724000 | K54: =J54 -> 724000 | L54: =K54 -> 724000 | M54: =L54 -> 724000 | N54: =M54 -> 724000 | O54: =N54 -> 724000 | P54: =O54 -> 724000 | Q54: =P54 -> 724000 | R54: =Q54 -> 724000 | ... U54: =T54 -> 724000
G55: =F55 -> 0 | H55: =F55 -> 0 | I55: =F55 -> 0 | J55: =F55 -> 0 | K55: =J55 -> 0 | L55: =K55 -> 0 | M55: =L55 -> 0 | N55: =M55 -> 0 | O55: =N55 -> 0 | P55: =O55 -> 0 | Q55: =P55 -> 0 | R55: =Q55 -> 0 | ... U55: =T55 -> 0
B56: Buildling and equipment maintenance | C56: G$ | F56: =F21*0.9 -> 8010 | G56: =F56 -> 8010 | H56: =F56 -> 8010 | I56: =F56 -> 8010 | J56: =F56 -> 8010 | K56: =J56 -> 8010 | L56: =K56 -> 8010 | M56: =L56 -> 8010 | N56: =M56 -> 8010 | O56: =N56 -> 8010 | P56: =O56 -> 8010 | Q56: =P56 -> 8010 | R56: =Q56 -> 8010 | ... U56: =T56 -> 8010
B57: Sub-total for Operating costs | D57: =D23 -> 0 | F57: =SUM(F51:F56) -> 2739010 | G57: =SUM(G51:G56) -> 2739010 | H57: =SUM(H51:H56) -> 2739010 | I57: =SUM(I51:I56) -> 2739010 | J57: =SUM(J51:J56) -> 3792010 | K57: =SUM(K51:K56) -> 3792010 | L57: =SUM(L51:L56) -> 3792010 | M57: =SUM(M51:M56) -> 3792010 | ... U57: =SUM(U51:U56) -> 3792010
D58: =D24 -> 0
B59: Fixed costs | D59: =D25 -> 0
B60: Depreciation | C60: G$s/annum | D60: =D26 -> 1 | F60: =D60*E60 -> 0 | G60: =F26*0.9 -> 18000 | H60: =G26*0.9 -> 0 | I60: =H26*0.9 -> 18000 | J60: =I26*0.9 -> 18000 | K60: =J26*0.9 -> 18000 | L60: =K26*0.9 -> 18000 | M60: =L26*0.9 -> 18000 | N60: =M26*0.9 -> 18000 | ... U60: =T26*0.9 -> 18000 | V60: =SUM(H60:U60) -> 234000
B61: Sub-total for Fixed costs | F61: =SUM(F60:F60) -> 0 | G61: =SUM(G60:G60) -> 18000 | H61: =SUM(H60:H60) -> 0 | I61: =SUM(I60:I60) -> 18000 | J61: =SUM(J60:J60) -> 18000 | K61: =SUM(K60:K60) -> 18000 | L61: =SUM(L60:L60) -> 18000 | M61: =SUM(M60:M60) -> 18000 | ... U61: =SUM(U60:U60) -> 18000
B62: TOTAL COSTS | F62: =F48+F57+F61 -> 5439010 | G62: =G48+G57+G61 -> 5757010 | H62: =H48+H57+H61 -> 2739010 | I62: =I48+I57+I61 -> 2757010 | J62: =J48+J57+J61 -> 3810010 | K62: =K48+K57+K61 -> 3810010 | L62: =L48+L57+L61 -> 3810010 | M62: =M48+M57+M61 -> 3810010 | ... U62: =U48+U57+U61 -> 3820010
B64: GROSS MARGIN | C64: G$/annum | G64: =G42-G48-G57 -> -5739010 | H64: =H42-H48-H57 -> 1895990 | I64: =I42-I48-I57 -> 2410990 | J64: =J42-J48-J57 -> 842990 | K64: =K42-K48-K57 -> 842990 | L64: =L42-L48-L57 -> 842990 | M64: =M42-M48-M57 -> 842990 | N64: =N42-N48-N57 -> 842990 | ... U64: =U42-U48-U57 -> 832990
B65: NET MARGIN | C65: G$/annum | G65: =G64-G61 -> -5757010 | H65: =H64-H61 -> 1895990 | I65: =I64-I61 -> 2392990 | J65: =J64-J61 -> 824990 | K65: =K64-K61 -> 824990 | L65: =L64-L61 -> 824990 | M65: =M64-M61 -> 824990 | N65: =N64-N61 -> 824990 | ... U65: =U64-U61 -> 814990
B66: EIRR | G66: =IRR(G65:U65) -> 0.20146258
B67: ENPV | G67: =NPV(0.1,G65:U65) -> 2348908.5

Sheet Honey
B1: FINANCIAL
C2: Unit | D2: Quantity | E2: Price | F2: Amount | G2: Year
B3: REVENUE | G3: 1 | H3: =G3+1 -> 2 | I3: =H3+1 -> 3 | J3: =I3+1 -> 4 | K3: =J3+1 -> 5 | L3: =K3+1 -> 6 | M3: =L3+1 -> 7 | N3: =M3+1 -> 8 | O3: =N3+1 -> 9 | P3: =O3+1 -> 10 | Q3: 11 | R3: 12 | S3: 13 | T3: 14 | U3: 15
B4: Sales | C4: lumpsum | F4: 600000 | G4: =F4*0.5 -> 300000 | H4: =F4 -> 600000 | I4: =F4 -> 600000 | J4: =F4 -> 600000 | K4: =J4 -> 600000 | L4: =K4 -> 600000 | M4: =L4 -> 600000 | N4: =M4 -> 600000 | O4: =N4 -> 600000 | P4: =O4 -> 600000 | Q4: =P4 -> 600000 | R4: =Q4 -> 600000 | ... U4: =T4 -> 600000
B5: Other income | C5: lumpsum | F5: 50000 | H5: =F5 -> 50000 | I5: =H5 -> 50000 | J5: =H5 -> 50000 | K5: =J5 -> 50000 | L5: =K5 -> 50000 | M5: =L5 -> 50000 | N5: =M5 -> 50000 | O5: =N5 -> 50000 | P5: =O5 -> 50000 | Q5: =P5 -> 50000 | R5: =Q5 -> 50000 | ... U5: =T5 -> 50000
B6: Sub-total Revenue | F6: =SUM(F4:F5) -> 650000 | G6: =SUM(G4:G5) -> 300000 | H6: =SUM(H4:H5) -> 650000 | I6: =SUM(I4:I5) -> 650000 | J6: =SUM(J4:J5) -> 650000 | K6: =SUM(K4:K5) -> 650000 | L6: =SUM(L4:L5) -> 650000 | M6: =SUM(M4:M5) -> 650000 | ... U6: =SUM(U4:U5) -> 650000
B8: COSTS
B9: Investment Costs
B10: Fixed Capital | C10: lumpsum | D10: 1 | E10: 100000 | F10: =D10*E10 -> 100000 | G10: =D10*E10 -> 100000 | H10: 0 | I10: 0 | J10: 0 | P10: =K10 -> 0
B11: Cash in hand | C11: lumpsum | D11: 1 | E11: 20000 | F11: =D11*E11 -> 20000 | G11: =D11*E11 -> 20000 | H11: 0 | I11: 0 | J11: 0 | K11: 0
B12: Sub-total Investment | F12: =SUM(F10:F11) -> 120000 | G12: =SUM(G10:G11) -> 120000 | H12: =SUM(H10:H11) -> 0 | I12: =SUM(I10:I11) -> 0 | J12: =SUM(J10:J11) -> 0 | K12: =SUM(K10:K11) -> 0 | L12: =SUM(L10:L11) -> 0 | M12: =SUM(M10:M11) -> 0 | ... U12: =SUM(U10:U11) -> 0
F13: =D13*E13 -> 0
B14: Operating costs | F14: =D14*E14 -> 0
B15: Material Cost | C15: G$ | F15: =F4*0.75 -> 450000 | G15: =F15*0.5 -> 225000 | H15: =F15 -> 450000 | I15: =H15 -> 450000 | J15: =I15 -> 450000 | K15: =J15 -> 450000 | L15: =K15 -> 450000 | M15: =L15 -> 450000 | N15: =M15 -> 450000 | O15: =N15 -> 450000 | P15: =O15 -> 450000 | ... U15: =T15 -> 450000
B16: Other direct cost | C16: G$ | F16: 30000 | H16: =F16 -> 30000 | I16: =H16 -> 30000 | J16: =I16 -> 30000 | K16: =J16 -> 30000 | L16: =K16 -> 30000 | M16: =L16 -> 30000 | N16: =M16 -> 30000 | O16: =N16 -> 30000 | P16: =O16 -> 30000 | ... U16: =T16 -> 30000
B17: Wages and Salary | C17: G$ | D17: 200 | E17: 450 | F17: =D17*E17 -> 90000 | G17: =F17*0.75 -> 67500 | H17: =F17 -> 90000 | I17: =H17 -> 90000 | J17: =I17 -> 90000 | K17: =J17 -> 90000 | L17: =K17 -> 90000 | M17: =L17 -> 90000 | N17: =M17 -> 90000 | O17: =N17 -> 90000 | P17: =O17 -> 90000 | ... U17: =T17 -> 90000
B18: Rent | C18: G$ | F18: 10000 | G18: =F18 -> 10000 | H18: =G18 -> 10000 | I18: =H18 -> 10000 | J18: =I18 -> 10000 | K18: =J18 -> 10000 | L18: =K18 -> 10000 | M18: =L18 -> 10000 | N18: =M18 -> 10000 | ... U18: =T18 -> 10000
B19: Other equipment cost | C19: G$ | F19: =F4*0.01 -> 6000 | G19: =F19 -> 6000 | H19: =F19 -> 6000 | I19: =H19 -> 6000 | J19: =I19 -> 6000 | K19: =J19 -> 6000 | L19: =K19 -> 6000 | M19: =L19 -> 6000 | N19: =M19 -> 6000 | O19: =N19 -> 6000 | P19: =O19 -> 6000 | ... U19: =T19 -> 6000
B20: Damage | C20: G$ | F20: =F4*0.01 -> 6000 | G20: =F20 -> 6000 | H20: =G20 -> 6000 | I20: =H20 -> 6000 | J20: =I20 -> 6000 | K20: =J20 -> 6000 | L20: =K20 -> 6000 | M20: =L20 -> 6000 | N20: =M20 -> 6000 | ... U20: =T20 -> 6000
B22: Sub-total for Operating costs | F22: =SUM(F15:F21) -> 592000 | G22: =SUM(G15:G21) -> 314500 | H22: =SUM(H15:H21) -> 592000 | I22: =SUM(I15:I21) -> 592000 | J22: =SUM(J15:J21) -> 592000 | K22: =SUM(K15:K21) -> 592000 | L22: =SUM(L15:L21) -> 592000 | M22: =SUM(M15:M21) -> 592000 | ... U22: =SUM(U15:U21) -> 592000
B24: Fixed costs
B25: Depreciation | C25: G$/annum | D25: 1 | E25: =E10/15 -> 6666.6667 | F25: =D25*E25 -> 6666.6667 | G25: =F25 -> 6666.6667 | H25: =D25*E25 -> 6666.6667 | I25: =H25 -> 6666.6667 | J25: =I25 -> 6666.6667 | K25: =J25 -> 6666.6667 | L25: =K25 -> 6666.6667 | M25: =L25 -> 6666.6667 | N25: =M25 -> 6666.6667 | O25: =N25 -> 6666.6667 | P25: =O25 -> 6666.6667 | ... U25: =T25 -> 6666.6667 | V25: =SUM(H25:U25) -> 93333.333
B26: Sub-total for Fixed costs | F26: =SUM(F25:F25) -> 6666.6667 | G26: =SUM(G25:G25) -> 6666.6667 | H26: =SUM(H25:H25) -> 6666.6667 | I26: =SUM(I25:I25) -> 6666.6667 | J26: =SUM(J25:J25) -> 6666.6667 | K26: =SUM(K25:K25) -> 6666.6667 | L26: =SUM(L25:L25) -> 6666.6667 | M26: =SUM(M25:M25) -> 6666.6667 | ... U26: =SUM(U25:U25) -> 6666.6667
B27: TOTAL COSTS | F27: =F12+F22+F26 -> 718666.67 | G27: =G12+G22+G26 -> 441166.67 | H27: =H12+H22+H26 -> 598666.67 | I27: =I12+I22+I26 -> 598666.67 | J27: =J12+J22+J26 -> 598666.67 | K27: =K12+K22+K26 -> 598666.67 | L27: =L12+L22+L26 -> 598666.67 | M27: =M12+M22+M26 -> 598666.67 | ... U27: =U12+U22+U26 -> 598666.67
B29: GROSS MARGIN | C29: G$/annum | G29: =G6-G12-G22 -> -134500 | H29: =H6-H12-H22 -> 58000 | I29: =I6-I12-I22 -> 58000 | J29: =J6-J12-J22 -> 58000 | K29: =K6-K12-K22 -> 58000 | L29: =L6-L12-L22 -> 58000 | M29: =M6-M12-M22 -> 58000 | N29: =N6-N12-N22 -> 58000 | ... U29: =U6-U12-U22 -> 58000
B30: NET MARGIN BEFORE PROFIT TAX | C30: G$/annum | G30: =G29-G26 -> -141166.67 | H30: =H29-H26 -> 51333.333 | I30: =I29-I26 -> 51333.333 | J30: =J29-J26 -> 51333.333 | K30: =K29-K26 -> 51333.333 | L30: =L29-L26 -> 51333.333 | M30: =M29-M26 -> 51333.333 | N30: =N29-N26 -> 51333.333 | ... U30: =U29-U26 -> 51333.333
B31: FIRR | G31: =IRR(G30:U30) -> 0.35865753
B32: FNPV | G32: =NPV(0.1,G30:U30) -> 215445.41
B40: ECONOMIC
C41: Unit | D41: Quantity | E41: Price | F41: Amount | G41: Year
B42: REVENUE | G42: 1 | H42: =G42+1 -> 2 | I42: =H42+1 -> 3 | J42: =I42+1 -> 4 | K42: =J42+1 -> 5 | L42: =K42+1 -> 6 | M42: =L42+1 -> 7 | N42: =M42+1 -> 8 | O42: =N42+1 -> 9 | P42: =O42+1 -> 10 | Q42: 11 | R42: 12 | S42: 13 | T42: 14 | U42: 15
B43: Sales | C43: lumpsum | F43: =F4*0.9 -> 540000 | G43: =F43*0.5 -> 270000 | H43: =F43 -> 540000 | I43: =F43 -> 540000 | J43: =F43 -> 540000 | K43: =J43 -> 540000 | L43: =K43 -> 540000 | M43: =L43 -> 540000 | N43: =M43 -> 540000 | O43: =N43 -> 540000 | P43: =O43 -> 540000 | Q43: =P43 -> 540000 | R43: =Q43 -> 540000 | ... U43: =T43 -> 540000
B44: Other income | C44: lumpsum | F44: =F5*0.9 -> 45000 | H44: =F44 -> 45000 | I44: =H44 -> 45000 | J44: =I44 -> 45000 | K44: =J44 -> 45000 | L44: =K44 -> 45000 | M44: =L44 -> 45000 | N44: =M44 -> 45000 | O44: =N44 -> 45000 | P44: =O44 -> 45000 | ... U44: =T44 -> 45000
B46: Sub-total Revenue | D46: =D6 -> 0 | E46: =E6*0.9 -> 0 | F46: =SUM(F43:F45) -> 585000 | G46: =SUM(G43:G45) -> 270000 | H46: =SUM(H43:H45) -> 585000 | I46: =SUM(I43:I45) -> 585000 | J46: =SUM(J43:J45) -> 585000 | K46: =SUM(K43:K45) -> 585000 | L46: =SUM(L43:L45) -> 585000 | M46: =SUM(M43:M45) -> 585000 | ... U46: =SUM(U43:U45) -> 585000
D47: =D7 -> 0 | E47: =E7*0.9 -> 0
B48: COSTS | D48: =D8 -> 0 | E48: =E8*0.9 -> 0
B49: Investment Costs | D49: =D9 -> 0 | E49: =E9*0.9 -> 0
B50: Fixed Capital | C50: Nos. | D50: =D10 -> 1 | E50: =E10*0.9 -> 90000 | F50: =D50*E50 -> 90000 | G50: =D50*E50 -> 90000 | H50: 0 | I50: 0 | J50: 0 | P50: =K50 -> 0
B51: Cash in hand | C51: lumpsum | D51: =D11 -> 1 | E51: =E11*0.9 -> 18000 | F51: =D51*E51 -> 18000 | G51: =D51*E51 -> 18000 | H51: 0 | I51: 0 | J51: 0 | K51: 0
B52: Sub-total Investment | D52: =D12 -> 0 | E52: =E12*0.9 -> 0 | F52: =SUM(F50:F51) -> 108000 | G52: =SUM(G50:G51) -> 108000 | H52: =SUM(H50:H51) -> 0 | I52: =SUM(I50:I51) -> 0 | J52: =SUM(J50:J51) -> 0 | K52: =SUM(K50:K51) -> 0 | L52: =SUM(L50:L51) -> 0 | M52: =SUM(M50:M51) -> 0 | ... U52: =SUM(U50:U51) -> 0
D53: =D13 -> 0 | E53: =E13*0.9 -> 0 | F53: =D53*E53 -> 0
B54: Operating costs | D54: =D14 -> 0 | E54: =E14*0.9 -> 0 | F54: =D54*E54 -> 0
B55: Material Cost | C55: G$ | F55: =F15*0.9 -> 405000 | G55: =F55*0.5 -> 202500 | H55: =F55 -> 405000 | I55: =H55 -> 405000 | J55: =I55 -> 405000 | K55: =J55 -> 405000 | L55: =K55 -> 405000 | M55: =L55 -> 405000 | N55: =M55 -> 405000 | O55: =N55 -> 405000 | P55: =O55 -> 405000 | ... U55: =T55 -> 405000
B56: Other direct cost | C56: G$ | F56: =F16*0.8 -> 24000 | H56: =F56 -> 24000 | I56: =H56 -> 24000 | J56: =I56 -> 24000 | K56: =J56 -> 24000 | L56: =K56 -> 24000 | M56: =L56 -> 24000 | N56: =M56 -> 24000 | O56: =N56 -> 24000 | P56: =O56 -> 24000 | ... U56: =T56 -> 24000
B57: Wages and Salary | C57: G$ | F57: =F17 -> 90000 | G57: =F57*0.75 -> 67500 | H57: =F57 -> 90000 | I57: =H57 -> 90000 | J57: =I57 -> 90000 | K57: =J57 -> 90000 | L57: =K57 -> 90000 | M57: =L57 -> 90000 | N57: =M57 -> 90000 | O57: =N57 -> 90000 | P57: =O57 -> 90000 | ... U57: =T57 -> 90000
B58: Rent | C58: G$ | F58: =F18*0.9 -> 9000 | G58: =F58 -> 9000 | H58: =F58 -> 9000 | I58: =F58 -> 9000 | J58: =F58 -> 9000 | K58: =J58 -> 9000 | L58: =K58 -> 9000 | M58: =L58 -> 9000 | N58: =M58 -> 9000 | O58: =N58 -> 9000 | P58: =O58 -> 9000 | Q58: =P58 -> 9000 | R58: =Q58 -> 9000 | ... U58: =T58 -> 9000
B59: Other equipment cost | C59: G$ | F59: =F19*0.9 -> 5400 | G59: =F59 -> 5400 | H59: =F59 -> 5400 | I59: =F59 -> 5400 | J59: =F59 -> 5400 | K59: =J59 -> 5400 | L59: =K59 -> 5400 | M59: =L59 -> 5400 | N59: =M59 -> 5400 | O59: =N59 -> 5400 | P59: =O59 -> 5400 | Q59: =P59 -> 5400 | R59: =Q59 -> 5400 | ... U59: =T59 -> 5400
B60: Damage | C60: G$ | F60: =F20*0.8 -> 4800 | G60: =F60 -> 4800 | H60: =F60 -> 4800 | I60: =F60 -> 4800 | J60: =F60 -> 4800 | K60: =J60 -> 4800 | L60: =K60 -> 4800 | M60: =L60 -> 4800 | N60: =M60 -> 4800 | O60: =N60 -> 4800 | P60: =O60 -> 4800 | Q60: =P60 -> 4800 | R60: =Q60 -> 4800 | ... U60: =T60 -> 4800
B61: Sub-total for Operating costs | D61: =D22 -> 0 | F61: =SUM(F55:F60) -> 538200 | G61: =SUM(G55:G60) -> 289200 | H61: =SUM(H55:H60) -> 538200 | I61: =SUM(I55:I60) -> 538200 | J61: =SUM(J55:J60) -> 538200 | K61: =SUM(K55:K60) -> 538200 | L61: =SUM(L55:L60) -> 538200 | M61: =SUM(M55:M60) -> 538200 | ... U61: =SUM(U55:U60) -> 538200
D62: =D23 -> 0
B63: Fixed costs | D63: =D24 -> 0
B64: Depreciation | C64: G$/annum | D64: =D25 -> 1 | F64: =D64*E64 -> 0 | G64: 0 | H64: =D64*E64 -> 0 | I64: =H64 -> 0 | J64: =I64 -> 0 | K64: =J64 -> 0 | L64: =K64 -> 0 | M64: =L64 -> 0 | N64: =M64 -> 0 | O64: =N64 -> 0 | P64: =O64 -> 0 | ... U64: =T64 -> 0 | V64: =SUM(H64:U64) -> 0
B65: Sub-total for Fixed costs | F65: =SUM(F64:F64) -> 0 | G65: =SUM(G64:G64) -> 0 | H65: =SUM(H64:H64) -> 0 | I65: =SUM(I64:I64) -> 0 | J65: =SUM(J64:J64) -> 0 | K65: =SUM(K64:K64) -> 0 | L65: =SUM(L64:L64) -> 0 | M65: =SUM(M64:M64) -> 0 | ... U65: =SUM(U64:U64) -> 0
B66: TOTAL COSTS | F66: =F52+F61+F65 -> 646200 | G66: =G52+G61+G65 -> 397200 | H66: =H52+H61+H65 -> 538200 | I66: =I52+I61+I65 -> 538200 | J66: =J52+J61+J65 -> 538200 | K66: =K52+K61+K65 -> 538200 | L66: =L52+L61+L65 -> 538200 | M66: =M52+M61+M65 -> 538200 | ... U66: =U52+U61+U65 -> 538200
B68: GROSS MARGIN | C68: G$/annum | G68: =G46-G52-G61 -> -127200 | H68: =H46-H52-H61 -> 46800 | I68: =I46-I52-I61 -> 46800 | J68: =J46-J52-J61 -> 46800 | K68: =K46-K52-K61 -> 46800 | L68: =L46-L52-L61 -> 46800 | M68: =M46-M52-M61 -> 46800 | N68: =N46-N52-N61 -> 46800 | ... U68: =U46-U52-U61 -> 46800
B69: NET MARGIN | C69: G$/annum | G69: =G68-G65 -> -127200 | H69: =H68-H65 -> 46800 | I69: =I68-I65 -> 46800 | J69: =J68-J65 -> 46800 | K69: =K68-K65 -> 46800 | L69: =L68-L65 -> 46800 | M69: =M68-M65 -> 46800 | N69: =N68-N65 -> 46800 | ... U69: =U68-U65 -> 46800
B70: EIRR | G70: =IRR(G69:U69) -> 0.36311265
B71: ENPV | G71: =NPV(0.1,G69:U69) -> 197782.7

Sheet School kitchen gardening
B1: FINANCIAL
C2: Unit | D2: Quantity | E2: Price | F2: Amount | G2: Year
B3: REVENUE | G3: 1 | H3: =G3+1 -> 2 | I3: =H3+1 -> 3 | J3: =I3+1 -> 4 | K3: =J3+1 -> 5 | L3: =K3+1 -> 6 | M3: =L3+1 -> 7 | N3: =M3+1 -> 8 | O3: =N3+1 -> 9 | P3: =O3+1 -> 10 | Q3: 11 | R3: 12 | S3: 13 | T3: 14 | U3: 15
B4: Sales of vegetable | C4: lumpsum | F4: 200000 | G4: =F4 -> 200000 | H4: =F4 -> 200000 | I4: =F4 -> 200000 | J4: =F4 -> 200000 | K4: =J4 -> 200000 | L4: =K4 -> 200000 | M4: =L4 -> 200000 | N4: =M4 -> 200000 | O4: =N4 -> 200000 | P4: =O4 -> 200000 | Q4: =P4 -> 200000 | R4: =Q4 -> 200000 | ... U4: =T4 -> 200000
B5: Sub-total Revenue | F5: =SUM(F4:F4) -> 200000 | G5: =SUM(G4:G4) -> 200000 | H5: =SUM(H4:H4) -> 200000 | I5: =SUM(I4:I4) -> 200000 | J5: =SUM(J4:J4) -> 200000 | K5: =SUM(K4:K4) -> 200000 | L5: =SUM(L4:L4) -> 200000 | M5: =SUM(M4:M4) -> 200000 | ... U5: =SUM(U4:U4) -> 200000
B7: COSTS
B8: Investment Costs
B9: Fixed Capital | C9: lumpsum | D9: 1 | E9: 400000 | F9: =D9*E9 -> 400000 | G9: =D9*E9 -> 400000 | H9: 0 | I9: 10000 | L9: 10000 | O9: 10000 | R9: 10000 | U9: 10000
B10: Sub-total Investment | F10: =SUM(F9:F9) -> 400000 | G10: =SUM(G9:G9) -> 400000 | H10: =SUM(H9:H9) -> 0 | I10: =SUM(I9:I9) -> 10000 | J10: =SUM(J9:J9) -> 0 | K10: =SUM(K9:K9) -> 0 | L10: =SUM(L9:L9) -> 10000 | M10: =SUM(M9:M9) -> 0 | ... U10: =SUM(U9:U9) -> 10000
F11: =D11*E11 -> 0
B12: Operating costs | F12: =D12*E12 -> 0
B13: Seed cost | C13: G$ | F13: 15000 | G13: =F13 -> 15000 | H13: =G13 -> 15000 | I13: =H13 -> 15000 | J13: =I13 -> 15000 | K13: =J13 -> 15000 | L13: =K13 -> 15000 | M13: =L13 -> 15000 | N13: =M13 -> 15000 | ... U13: =T13 -> 15000
B14: Irrigation | C14: G$ | F14: 15000 | G14: =F14 -> 15000 | H14: =G14 -> 15000 | I14: =H14 -> 15000 | J14: =I14 -> 15000 | K14: =J14 -> 15000 | L14: =K14 -> 15000 | M14: =L14 -> 15000 | N14: =M14 -> 15000 | ... U14: =T14 -> 15000
B15: Wages and Salary | C15: G$ | F15: 10000 | G15: =F15 -> 10000 | H15: =G15 -> 10000 | I15: =H15 -> 10000 | J15: =I15 -> 10000 | K15: =J15 -> 10000 | L15: =K15 -> 10000 | M15: =L15 -> 10000 | N15: =M15 -> 10000 | ... U15: =T15 -> 10000
B16: Transportation | C16: G$ | F16: 56000 | G16: =F16 -> 56000 | H16: =G16 -> 56000 | I16: =H16 -> 56000 | J16: =I16 -> 56000 | K16: =J16 -> 56000 | L16: =K16 -> 56000 | M16: =L16 -> 56000 | N16: =M16 -> 56000 | ... U16: =T16 -> 56000
B18: Damage | C18: G$ | F18: 8900 | G18: =F18 -> 8900 | H18: =G18 -> 8900 | I18: =H18 -> 8900 | J18: =I18 -> 8900 | K18: =J18 -> 8900 | L18: =K18 -> 8900 | M18: =L18 -> 8900 | N18: =M18 -> 8900 | ... U18: =T18 -> 8900
B20: Sub-total for Operating costs | F20: =SUM(F13:F19) -> 104900 | G20: =SUM(G13:G19) -> 104900 | H20: =SUM(H13:H19) -> 104900 | I20: =SUM(I13:I19) -> 104900 | J20: =SUM(J13:J19) -> 104900 | K20: =SUM(K13:K19) -> 104900 | L20: =SUM(L13:L19) -> 104900 | M20: =SUM(M13:M19) -> 104900 | ... U20: =SUM(U13:U19) -> 104900
B22: Fixed costs
B23: Depreciation | C23: G$/annum | D23: 1 | E23: =E9/15 -> 26666.667 | F23: =D23*E23 -> 26666.667 | H23: =D23*E23 -> 26666.667 | I23: =H23 -> 26666.667 | J23: =I23 -> 26666.667 | K23: =J23 -> 26666.667 | L23: =K23 -> 26666.667 | M23: =L23 -> 26666.667 | N23: =M23 -> 26666.667 | O23: =N23 -> 26666.667 | P23: =O23 -> 26666.667 | ... U23: =T23 -> 26666.667 | V23: =SUM(H23:U23) -> 373333.33
B24: Land Rent | C24: Lumpsum | E24: 10000 | F24: =E24 -> 10000 | G24: =F24 -> 10000 | H24: =G24 -> 10000 | I24: =H24 -> 10000 | J24: =I24 -> 10000 | K24: =J24 -> 10000 | L24: =K24 -> 10000 | M24: =L24 -> 10000 | ... U24: =T24 -> 10000
B25: Sub-total for Fixed costs | F25: =SUM(F23:F23) -> 26666.667 | G25: =SUM(G23:G23) -> 0 | H25: =SUM(H23:H24) -> 36666.667 | I25: =SUM(I23:I23) -> 26666.667 | J25: =SUM(J23:J23) -> 26666.667 | K25: =SUM(K23:K23) -> 26666.667 | L25: =SUM(L23:L23) -> 26666.667 | M25: =SUM(M23:M23) -> 26666.667 | N25: =SUM(N23:N23) -> 26666.667 | O25: =SUM(O23:O23) -> 26666.667 | P25: =SUM(P23:P23) -> 26666.667 | ... U25: =SUM(U23:U23) -> 26666.667
B26: TOTAL COSTS | F26: =F10+F20+F25 -> 531566.67 | G26: =G10+G20+G25 -> 504900 | H26: =H10+H20+H25 -> 141566.67 | I26: =I10+I20+I25 -> 141566.67 | J26: =J10+J20+J25 -> 131566.67 | K26: =K10+K20+K25 -> 131566.67 | L26: =L10+L20+L25 -> 141566.67 | M26: =M10+M20+M25 -> 131566.67 | ... U26: =U10+U20+U25 -> 141566.67
B28: GROSS MARGIN | C28: G$/annum | G28: =G5-G10-G20 -> -304900 | H28: =H5-H10-H20 -> 95100 | I28: =I5-I10-I20 -> 85100 | J28: =J5-J10-J20 -> 95100 | K28: =K5-K10-K20 -> 95100 | L28: =L5-L10-L20 -> 85100 | M28: =M5-M10-M20 -> 95100 | N28: =N5-N10-N20 -> 95100 | ... U28: =U5-U10-U20 -> 85100
B29: NET MARGIN BEFORE PROFIT TAX | C29: G$s/annum | G29: =G28-G25 -> -304900 | H29: =H28-H25 -> 58433.333 | I29: =I28-I25 -> 58433.333 | J29: =J28-J25 -> 68433.333 | K29: =K28-K25 -> 68433.333 | L29: =L28-L25 -> 58433.333 | M29: =M28-M25 -> 68433.333 | N29: =N28-N25 -> 68433.333 | ... U29: =U28-U25 -> 58433.333
B30: FIRR | G30: =IRR(G29:U29) -> 0.18940992
B31: FNPV | G31: =NPV(0.1,G29:U29) -> 149871.88
B34: ECONOMIC
C35: Unit | D35: Quantity | E35: Price | F35: Amount | G35: Year
B36: REVENUE | G36: 1 | H36: =G36+1 -> 2 | I36: =H36+1 -> 3 | J36: =I36+1 -> 4 | K36: =J36+1 -> 5 | L36: =K36+1 -> 6 | M36: =L36+1 -> 7 | N36: =M36+1 -> 8 | O36: =N36+1 -> 9 | P36: =O36+1 -> 10 | Q36: 11 | R36: 12 | S36: 13 | T36: 14 | U36: 15
B37: Sales of vegetable | C37: lumpsum | F37: =F4*0.87 -> 174000 | G37: =F37 -> 174000 | H37: =F37 -> 174000 | I37: =F37 -> 174000 | J37: =F37 -> 174000 | K37: =J37 -> 174000 | L37: =K37 -> 174000 | M37: =L37 -> 174000 | N37: =M37 -> 174000 | O37: =N37 -> 174000 | P37: =O37 -> 174000 | Q37: =P37 -> 174000 | R37: =Q37 -> 174000 | ... U37: =T37 -> 174000
B39: Sub-total Revenue | D39: =D5 -> 0 | E39: =E5*0.9 -> 0 | F39: =SUM(F37:F38) -> 174000 | G39: =SUM(G37:G38) -> 174000 | H39: =SUM(H37:H38) -> 174000 | I39: =SUM(I37:I38) -> 174000 | J39: =SUM(J37:J38) -> 174000 | K39: =SUM(K37:K38) -> 174000 | L39: =SUM(L37:L38) -> 174000 | M39: =SUM(M37:M38) -> 174000 | ... U39: =SUM(U37:U38) -> 174000
D40: =D6 -> 0 | E40: =E6*0.9 -> 0
B41: COSTS | D41: =D7 -> 0 | E41: =E7*0.9 -> 0
B42: Investment Costs | D42: =D8 -> 0 | E42: =E8*0.9 -> 0
B43: Fixed Capital | C43: Nos. | D43: =D9 -> 1 | E43: =E9*0.9 -> 360000 | F43: =D43*E43 -> 360000 | G43: =D43*E43 -> 360000 | H43: 0 | I43: 0 | J43: 0 | P43: =K43 -> 0
B45: Sub-total Investment | D45: =D10 -> 0 | E45: =E10*0.9 -> 0 | F45: =SUM(F43:F44) -> 360000 | G45: =SUM(G43:G44) -> 360000 | H45: =SUM(H43:H44) -> 0 | I45: =SUM(I43:I44) -> 0 | J45: =SUM(J43:J44) -> 0 | K45: =SUM(K43:K44) -> 0 | L45: =SUM(L43:L44) -> 0 | M45: =SUM(M43:M44) -> 0 | ... U45: =SUM(U43:U44) -> 0
D46: =D11 -> 0 | E46: =E11*0.9 -> 0 | F46: =D46*E46 -> 0
B47: Operating costs | D47: =D12 -> 0 | E47: =E12*0.9 -> 0 | F47: =D47*E47 -> 0
B48: Seed cost | C48: G$ | F48: =F13*0.9 -> 13500 | G48: =F48 -> 13500 | H48: =G48 -> 13500 | I48: =H48 -> 13500 | J48: =I48 -> 13500 | K48: =J48 -> 13500 | L48: =K48 -> 13500 | M48: =L48 -> 13500 | N48: =M48 -> 13500 | ... U48: =T48 -> 13500
B49: Irrigation | C49: G$ | F49: =F14*0.9 -> 13500 | G49: =F49 -> 13500 | H49: =G49 -> 13500 | I49: =H49 -> 13500 | J49: =I49 -> 13500 | K49: =J49 -> 13500 | L49: =K49 -> 13500 | M49: =L49 -> 13500 | N49: =M49 -> 13500 | ... U49: =T49 -> 13500
B50: Wages and Salary | C50: G$ | F50: =F15*0.9 -> 9000 | G50: =F50 -> 9000 | H50: =F50 -> 9000 | I50: =H50 -> 9000 | J50: =I50 -> 9000 | K50: =J50 -> 9000 | L50: =K50 -> 9000 | M50: =L50 -> 9000 | N50: =M50 -> 9000 | O50: =N50 -> 9000 | P50: =O50 -> 9000 | ... U50: =T50 -> 9000
B51: Transportation | C51: G$ | F51: =F16*0.9 -> 50400 | G51: =F51 -> 50400 | H51: =F51 -> 50400 | I51: =F51 -> 50400 | J51: =F51 -> 50400 | K51: =J51 -> 50400 | L51: =K51 -> 50400 | M51: =L51 -> 50400 | N51: =M51 -> 50400 | O51: =N51 -> 50400 | P51: =O51 -> 50400 | Q51: =P51 -> 50400 | R51: =Q51 -> 50400 | ... U51: =T51 -> 50400
G52: =F52 -> 0 | H52: =F52 -> 0 | I52: =F52 -> 0 | J52: =F52 -> 0 | K52: =J52 -> 0 | L52: =K52 -> 0 | M52: =L52 -> 0 | N52: =M52 -> 0 | O52: =N52 -> 0 | P52: =O52 -> 0 | Q52: =P52 -> 0 | R52: =Q52 -> 0 | ... U52: =T52 -> 0
B53: Damage | C53: G$ | F53: =F18*0.9 -> 8010 | G53: =F53 -> 8010 | H53: =F53 -> 8010 | I53: =F53 -> 8010 | J53: =F53 -> 8010 | K53: =J53 -> 8010 | L53: =K53 -> 8010 | M53: =L53 -> 8010 | N53: =M53 -> 8010 | O53: =N53 -> 8010 | P53: =O53 -> 8010 | Q53: =P53 -> 8010 | R53: =Q53 -> 8010 | ... U53: =T53 -> 8010
B54: Sub-total for Operating costs | D54: =D20 -> 0 | F54: =SUM(F48:F53) -> 94410 | G54: =SUM(G48:G53) -> 94410 | H54: =SUM(H48:H53) -> 94410 | I54: =SUM(I48:I53) -> 94410 | J54: =SUM(J48:J53) -> 94410 | K54: =SUM(K48:K53) -> 94410 | L54: =SUM(L48:L53) -> 94410 | M54: =SUM(M48:M53) -> 94410 | ... U54: =SUM(U48:U53) -> 94410
D55: =D21 -> 0
B56: Fixed costs | D56: =D22 -> 0
B57: Depreciation | C57: G$/annum | D57: =D23 -> 1 | F57: =D57*E57 -> 0 | G57: 0 | H57: =D57*E57 -> 0 | I57: =H57 -> 0 | J57: =I57 -> 0 | K57: =J57 -> 0 | L57: =K57 -> 0 | M57: =L57 -> 0 | N57: =M57 -> 0 | O57: =N57 -> 0 | P57: =O57 -> 0 | ... U57: =T57 -> 0 | V57: =SUM(H57:U57) -> 0
B58: Sub-total for Fixed costs | F58: =SUM(F57:F57) -> 0 | G58: =SUM(G57:G57) -> 0 | H58: =SUM(H57:H57) -> 0 | I58: =SUM(I57:I57) -> 0 | J58: =SUM(J57:J57) -> 0 | K58: =SUM(K57:K57) -> 0 | L58: =SUM(L57:L57) -> 0 | M58: =SUM(M57:M57) -> 0 | ... U58: =SUM(U57:U57) -> 0
B59: TOTAL COSTS | F59: =F45+F54+F58 -> 454410 | G59: =G45+G54+G58 -> 454410 | H59: =H45+H54+H58 -> 94410 | I59: =I45+I54+I58 -> 94410 | J59: =J45+J54+J58 -> 94410 | K59: =K45+K54+K58 -> 94410 | L59: =L45+L54+L58 -> 94410 | M59: =M45+M54+M58 -> 94410 | ... U59: =U45+U54+U58 -> 94410
B61: GROSS MARGIN | C61: G$/annum | G61: =G39-G45-G54 -> -280410 | H61: =H39-H45-H54 -> 79590 | I61: =I39-I45-I54 -> 79590 | J61: =J39-J45-J54 -> 79590 | K61: =K39-K45-K54 -> 79590 | L61: =L39-L45-L54 -> 79590 | M61: =M39-M45-M54 -> 79590 | N61: =N39-N45-N54 -> 79590 | ... U61: =U39-U45-U54 -> 79590
B62: NET MARGIN | C62: G$/annum | G62: =G61-G58 -> -280410 | H62: =-(H61-H58) -> -79590 | I62: =I61-I58 -> 79590 | J62: =J61-J58 -> 79590 | K62: =K61-K58 -> 79590 | L62: =L61-L58 -> 79590 | M62: =M61-M58 -> 79590 | N62: =N61-N58 -> 79590 | O62: =O61-O58 -> 79590 | P62: =P61-P58 -> 79590 | ... U62: =U61-U58 -> 79590
B63: EIRR | G63: =IRR(G62:U62) -> 0.16984724
B64: ENPV | G64: =NPV(0.1,G62:U62) -> 146541.42

Sheet Additional financing total
A1: Financial
A2: Net Margins | B2: Particulars | C2: Year 1 | D2: Year 2 | E2: Year 3 | F2: Year 4 | G2: Year 5 | H2: Year 6 | I2: Year 7 | J2: Year 8 | K2: Year 9 | L2: Year 10 | M2: Year 11 | N2: Year 12 | O2: Year 13 | P2: Year 14 | Q2: Year 15
B3: Cassava | C3: ='Cool Reflective Roof Coating'!G29 -> -1954166.7 | D3: ='Cool Reflective Roof Coating'!H29 -> -895833.33 | E3: ='Cool Reflective Roof Coating'!I29 -> -1895833.3 | F3: ='Cool Reflective Roof Coating'!J29 -> 1895833.3 | G3: ='Cool Reflective Roof Coating'!K29 -> 1895833.3 | H3: ='Cool Reflective Roof Coating'!L29 -> 1895833.3 | I3: ='Cool Reflective Roof Coating'!M29 -> 1895833.3 | J3: ='Cool Reflective Roof Coating'!N29 -> 1895833.3 | ... Q3: ='Cool Reflective Roof Coating'!U29 -> 1895833.3
B4: Spice Processing | C4: ='Ceiling Installation + Roof Ins'!G31 -> -3989666.7 | D4: ='Ceiling Installation + Roof Ins'!H31 -> 1325333.3 | E4: ='Ceiling Installation + Roof Ins'!I31 -> 1325333.3 | F4: ='Ceiling Installation + Roof Ins'!J31 -> 1325333.3 | G4: ='Ceiling Installation + Roof Ins'!K31 -> 1325333.3 | H4: ='Ceiling Installation + Roof Ins'!L31 -> 1325333.3 | I4: ='Ceiling Installation + Roof Ins'!M31 -> 1325333.3 | J4: ='Ceiling Installation + Roof Ins'!N31 -> 1325333.3 | ... Q4: ='Ceiling Installation + Roof Ins'!U31 -> 1325333.3
B5: Poultry | C5: ='Cross Ventilation Improvements'!G28 -> -2878000 | D5: ='Cross Ventilation Improvements'!H28 -> -2878000 | E5: ='Cross Ventilation Improvements'!I28 -> -2878000 | F5: ='Cross Ventilation Improvements'!J28 -> -2878000 | G5: ='Cross Ventilation Improvements'!K28 -> -2399420 | H5: ='Cross Ventilation Improvements'!L28 -> -1799420 | I5: ='Cross Ventilation Improvements'!M28 -> -1079420 | J5: ='Cross Ventilation Improvements'!N28 -> -215420 | ... Q5: ='Cross Ventilation Improvements'!U28 -> 13186499
B6: cattle | C6: ='External Shading (Awnings, Over'!G30 -> -384933.33 | D6: ='External Shading (Awnings, Over'!H30 -> -41933.333 | E6: ='External Shading (Awnings, Over'!I30 -> -41933.333 | F6: ='External Shading (Awnings, Over'!J30 -> 258066.67 | G6: ='External Shading (Awnings, Over'!K30 -> 258066.67 | H6: ='External Shading (Awnings, Over'!L30 -> 258066.67 | I6: ='External Shading (Awnings, Over'!M30 -> 258066.67 | J6: ='External Shading (Awnings, Over'!N30 -> 258066.67 | ... S6: ='External Shading (Awnings, Over'!W30 -> 0
B7: Cassava processing | C7: ='Efficient Fans (DC or Energy-Ef'!G31 -> -7043900 | D7: ='Efficient Fans (DC or Energy-Ef'!H31 -> -1913900 | E7: ='Efficient Fans (DC or Energy-Ef'!I31 -> 1086100 | F7: ='Efficient Fans (DC or Energy-Ef'!J31 -> 301100 | G7: ='Efficient Fans (DC or Energy-Ef'!K31 -> 301100 | H7: ='Efficient Fans (DC or Energy-Ef'!L31 -> 291100 | I7: ='Efficient Fans (DC or Energy-Ef'!M31 -> 301100 | J7: ='Efficient Fans (DC or Energy-Ef'!N31 -> 301100 | ... Q7: ='Efficient Fans (DC or Energy-Ef'!U31 -> 291100
B8: Honey | C8: =Honey!G30 -> -141166.67 | D8: =Honey!H30 -> 51333.333 | E8: =Honey!I30 -> 51333.333 | F8: =Honey!J30 -> 51333.333 | G8: =Honey!K30 -> 51333.333 | H8: =Honey!L30 -> 51333.333 | I8: =Honey!M30 -> 51333.333 | J8: =Honey!N30 -> 51333.333 | ... Q8: =Honey!U30 -> 51333.333
B9: School kitchen gardening | C9: ='School kitchen gardening'!G29 -> -304900 | D9: ='School kitchen gardening'!H29 -> 58433.333 | E9: ='School kitchen gardening'!I29 -> 58433.333 | F9: ='School kitchen gardening'!J29 -> 68433.333 | G9: ='School kitchen gardening'!K29 -> 68433.333 | H9: ='School kitchen gardening'!L29 -> 58433.333 | I9: ='School kitchen gardening'!M29 -> 68433.333 | J9: ='School kitchen gardening'!N29 -> 68433.333 | ... Q9: ='School kitchen gardening'!U29 -> 58433.333
B10: Total | C10: =SUM(C3:C9) -> -16696733 | D10: =SUM(D3:D9) -> -4294566.7 | E10: =SUM(E3:E9) -> -2294566.7 | F10: =SUM(F3:F9) -> 1022100 | G10: =SUM(G3:G9) -> 1500680 | H10: =SUM(H3:H9) -> 2080680 | I10: =SUM(I3:I9) -> 2820680 | J10: =SUM(J3:J9) -> 3684680 | ... Q10: =SUM(Q3:Q9) -> 17066599
B11: Total investment | C11: =Summary!B11 -> 28836177 | T11: Total investment | V11: 11 | W11: Million
B12: Total component cost | C12: =V13 -> 2299000000 | U12: US$ | V12: =11000000 -> 11000000
B13: Net margins for the additional financing | C13: =C10*($C$12/$C$11) -> -1.3311678e+09 | D13: =-(D10*($C$12/$C$11)) -> 3.4238966e+08 | E13: =-(E10*($C$12/$C$11)) -> 1.8293718e+08 | F13: =-(F10*($C$12/$C$11)) -> -81488192 | G13: =G10*($C$12/$C$11) -> 1.1964358e+08 | H13: =H10*($C$12/$C$11) -> 1.658848e+08 | I13: =I10*($C$12/$C$11) -> 2.2488222e+08 | J13: =J10*($C$12/$C$11) -> 2.9376569e+08 | K13: =K10*($C$12/$C$11) -> 3.7483133e+08 | L13: =L10*($C$12/$C$11) -> 4.7561806e+08 | M13: =M10*($C$12/$C$11) -> 5.946487e+08 | N13: =N10*($C$12/$C$11) -> 7.3589095e+08 | ... Q13: =Q10*($C$12/$C$11) -> 1.3606558e+09 | U13: G$ | V13: 2299000000
B14: FIRR | C14: =IRR(C13:Q13) -> 0.19934323
B15: FNPV | C15: =NPV(0.1,C13:Q13) -> 1.2217166e+09
C18: =V13 -> 2299000000
C22: =NPV(0.1,C20:Q20) -> 0
A25: Economic
A26: Net Margins | B26: Particulars | C26: Year 1 | D26: Year 2 | E26: Year 3 | F26: Year 4 | G26: Year 5 | H26: Year 6 | I26: Year 7 | J26: Year 8 | K26: Year 9 | L26: Year 10 | M26: Year 11 | N26: Year 12 | O26: Year 13 | P26: Year 14 | Q26: Year 15
B27: Cassava | C27: ='Cool Reflective Roof Coating'!G66 -> -1690000 | D27: ='Cool Reflective Roof Coating'!H66 -> -1836250 | E27: ='Cool Reflective Roof Coating'!I66 -> -1836250 | F27: ='Cool Reflective Roof Coating'!J66 -> 1836250 | G27: ='Cool Reflective Roof Coating'!K66 -> 1836250 | H27: ='Cool Reflective Roof Coating'!L66 -> 1836250 | I27: ='Cool Reflective Roof Coating'!M66 -> 1836250 | J27: ='Cool Reflective Roof Coating'!N66 -> 1836250 | ... Q27: ='Cool Reflective Roof Coating'!U66 -> 1836250
B28: Spice processing | C28: ='Ceiling Installation + Roof Ins'!G70 -> -1722300 | D28: ='Ceiling Installation + Roof Ins'!H70 -> -905200 | E28: ='Ceiling Installation + Roof Ins'!I70 -> 905200 | F28: ='Ceiling Installation + Roof Ins'!J70 -> 905200 | G28: ='Ceiling Installation + Roof Ins'!K70 -> 905200 | H28: ='Ceiling Installation + Roof Ins'!L70 -> 905200 | I28: ='Ceiling Installation + Roof Ins'!M70 -> 905200 | J28: ='Ceiling Installation + Roof Ins'!N70 -> 905200 | ... Q28: ='Ceiling Installation + Roof Ins'!U70 -> 905200
B29: poultry | C29: ='Cross Ventilation Improvements'!G68 -> 17639461 | D29: ='Cross Ventilation Improvements'!H68 -> 17639461 | E29: ='Cross Ventilation Improvements'!I68 -> 17639461 | F29: ='Cross Ventilation Improvements'!J68 -> -17639461 | G29: ='Cross Ventilation Improvements'!K68 -> 17639461 | H29: ='Cross Ventilation Improvements'!L68 -> -17639461 | I29: ='Cross Ventilation Improvements'!M68 -> -17639461 | J29: ='Cross Ventilation Improvements'!N68 -> -17639461 | ... Q29: ='Cross Ventilation Improvements'!U68 -> -17639461
B30: cattle | C30: ='External Shading (Awnings, Over'!G63 -> -36440 | D30: ='External Shading (Awnings, Over'!H63 -> -278560 | E30: ='External Shading (Awnings, Over'!I63 -> -278560 | F30: ='External Shading (Awnings, Over'!J63 -> 278560 | G30: ='External Shading (Awnings, Over'!K63 -> 278560 | H30: ='External Shading (Awnings, Over'!L63 -> 278560 | I30: ='External Shading (Awnings, Over'!M63 -> 278560 | J30: ='External Shading (Awnings, Over'!N63 -> 278560 | ... Q30: ='External Shading (Awnings, Over'!U63 -> 278560
B31: Cassava processing | C31: ='Efficient Fans (DC or Energy-Ef'!G65 -> -5757010 | D31: ='Efficient Fans (DC or Energy-Ef'!H65 -> 1895990 | E31: ='Efficient Fans (DC or Energy-Ef'!I65 -> 2392990 | F31: ='Efficient Fans (DC or Energy-Ef'!J65 -> 824990 | G31: ='Efficient Fans (DC or Energy-Ef'!K65 -> 824990 | H31: ='Efficient Fans (DC or Energy-Ef'!L65 -> 824990 | I31: ='Efficient Fans (DC or Energy-Ef'!M65 -> 824990 | J31: ='Efficient Fans (DC or Energy-Ef'!N65 -> 824990 | ... Q31: ='Efficient Fans (DC or Energy-Ef'!U65 -> 814990
B32: Honey | C32: =Honey!G69 -> -127200 | D32: =Honey!H69 -> 46800 | E32: =Honey!I69 -> 46800 | F32: =Honey!J69 -> 46800 | G32: =Honey!K69 -> 46800 | H32: =Honey!L69 -> 46800 | I32: =Honey!M69 -> 46800 | J32: =Honey!N69 -> 46800 | ... Q32: =Honey!U69 -> 46800
B33: School kitchen gardening | C33: ='School kitchen gardening'!G62 -> -280410 | D33: ='School kitchen gardening'!H62 -> -79590 | E33: ='School kitchen gardening'!I62 -> 79590 | F33: ='School kitchen gardening'!J62 -> 79590 | G33: ='School kitchen gardening'!K62 -> 79590 | H33: ='School kitchen gardening'!L62 -> 79590 | I33: ='School kitchen gardening'!M62 -> 79590 | J33: ='School kitchen gardening'!N62 -> 79590 | ... Q33: ='School kitchen gardening'!U62 -> 79590
B34: Total | C34: =SUM(C27:C33) -> 8026101 | D34: =SUM(D27:D33) -> 16482651 | E34: =SUM(E27:E33) -> 18949231 | F34: =SUM(F27:F33) -> -13668071 | G34: =SUM(G27:G33) -> 21610851 | H34: =SUM(H27:H33) -> -13668071 | I34: =SUM(I27:I33) -> -13668071 | J34: =SUM(J27:J33) -> -13668071 | ... Q34: =SUM(Q27:Q33) -> -13678071
B35: Total investment | C35: =C11 -> 28836177
B36: Total component cost | C36: =C12 -> 2299000000
B37: Net margins for additional financing | C37: =-(C34*($C$12/$C$11)) -> -6.3989087e+08 | D37: =(D34*($C$12/$C$11)) -> 1.3140998e+09 | E37: =E34*($C$12/$C$11) -> 1.510751e+09 | F37: =F34*($C$12/$C$11) -> -1.0897039e+09 | G37: =(G34*($C$12/$C$11)) -> 1.7229519e+09 | H37: =H34*($C$12/$C$11) -> -1.0897039e+09 | I37: =I34*($C$12/$C$11) -> -1.0897039e+09 | J37: =J34*($C$12/$C$11) -> -1.0897039e+09 | K37: =K34*($C$12/$C$11) -> -1.0897039e+09 | L37: =L34*($C$12/$C$11) -> -1.0897039e+09 | M37: =M34*($C$12/$C$11) -> -1.1136218e+09 | N37: =N34*($C$12/$C$11) -> -1.1144191e+09 | O37: =O34*($C$12/$C$11) -> -1.1136218e+09 | ... Q37: =Q34*($C$12/$C$11) -> -1.0905012e+09
B38: EIRR | C38: =IRR(C37:Q37) -> 0.26192151
B39: ENPV | C39: =NPV(0.1,C37:Q37) -> -2.2223163e+09
C49: =NPV(0.1,C47:Q47) -> 0

Sheet Peanut TF
B1: FINANCIAL
C2: Unit | D2: Quantity | E2: Price | F2: Amount | G2: Year
B3: REVENUE | G3: 1 | H3: =G3+1 -> 2 | I3: =H3+1 -> 3 | J3: =I3+1 -> 4 | K3: =J3+1 -> 5 | L3: =K3+1 -> 6 | M3: =L3+1 -> 7 | N3: =M3+1 -> 8 | O3: =N3+1 -> 9 | P3: =O3+1 -> 10 | Q3: 11 | R3: 12 | S3: 13 | T3: 14 | U3: 15
B4: Sales | C4: lumpsum | D4: 1300 | E4: 200 | F4: 0 | G4: 0 | H4: =L4*0.3 -> 78000 | I4: =K4*0.5 -> 130000 | J4: =K4*7 -> 1820000 | K4: =D4*E4 -> 260000 | L4: =K4 -> 260000 | M4: =L4 -> 260000 | N4: =M4 -> 260000 | O4: =N4 -> 260000 | P4: =O4 -> 260000 | Q4: =P4 -> 260000 | R4: =Q4 -> 260000 | S4: =R4 -> 260000 | ... U4: =T4 -> 260000
B5: Other income | C5: lumpsum | G5: =F5 -> 0 | H5: =F5 -> 0 | I5: =G5 -> 0 | J5: =H5 -> 0 | K5: =J5 -> 0 | L5: =K5 -> 0 | M5: =L5 -> 0 | N5: =M5 -> 0 | O5: =N5 -> 0 | P5: =O5 -> 0 | Q5: =P5 -> 0 | R5: =Q5 -> 0 | ... U5: =T5 -> 0
B6: Sub-total Revenue | F6: =SUM(F4:F5) -> 0 | G6: =SUM(G4:G5) -> 0 | H6: =SUM(H4:H5) -> 78000 | I6: =SUM(I4:I5) -> 130000 | J6: =SUM(J4:J5) -> 1820000 | K6: =SUM(K4:K5) -> 260000 | L6: =SUM(L4:L5) -> 260000 | M6: =SUM(M4:M5) -> 260000 | ... U6: =SUM(U4:U5) -> 260000
B8: COSTS
B9: Investment Costs
B10: Fixed Capital | C10: lumpsum | D10: 1 | E10: 500000 | F10: =D10*E10 -> 500000 | G10: =D10*E10 -> 500000 | H10: 0 | I10: 10000 | L10: 10000 | O10: 10000 | R10: 10000 | U10: 10000
B11: Sub-total Investment | F11: =SUM(F10:F10) -> 500000 | G11: =SUM(G10:G10) -> 500000 | H11: =SUM(H10:H10) -> 0 | I11: =SUM(I10:I10) -> 10000 | J11: =SUM(J10:J10) -> 0 | K11: =SUM(K10:K10) -> 0 | L11: =SUM(L10:L10) -> 10000 | M11: =SUM(M10:M10) -> 0 | ... U11: =SUM(U10:U10) -> 10000
F12: =D12*E12 -> 0
B13: Operating costs | F13: =D13*E13 -> 0
B14: Seed and improved cost | C14: G$ | F14: 7000 | G14: =F14 -> 7000 | H14: =G14 -> 7000 | I14: =H14 -> 7000 | J14: =I14 -> 7000 | K14: =J14 -> 7000 | L14: =K14 -> 7000 | M14: =L14 -> 7000 | N14: =M14 -> 7000 | ... U14: =T14 -> 7000
B15: Irrigation | C15: G$ | F15: 150000 | G15: =F15 -> 150000 | H15: =G15 -> 150000 | I15: =H15 -> 150000 | J15: =I15 -> 150000 | K15: =J15 -> 150000 | L15: =K15 -> 150000 | M15: =L15 -> 150000 | N15: =M15 -> 150000 | ... U15: =T15 -> 150000
B16: Wages and Salary | C16: G$ | F16: =F4*0.6 -> 0 | G16: =F16 -> 0 | H16: =G16 -> 0 | I16: =H16 -> 0 | J16: =I16 -> 0 | K16: =J16 -> 0 | L16: =K16 -> 0 | M16: =L16 -> 0 | N16: =M16 -> 0 | ... U16: =T16 -> 0
B17: Transportation | C17: G$ | F17: 5600 | G17: =F17 -> 5600 | H17: =G17 -> 5600 | I17: =H17 -> 5600 | J17: =I17 -> 5600 | K17: =J17 -> 5600 | L17: =K17 -> 5600 | M17: =L17 -> 5600 | N17: =M17 -> 5600 | ... U17: =T17 -> 5600
B19: Damage | C19: G$ | F19: 8900 | G19: =F19 -> 8900 | H19: =G19 -> 8900 | I19: =H19 -> 8900 | J19: =I19 -> 8900 | K19: =J19 -> 8900 | L19: =K19 -> 8900 | M19: =L19 -> 8900 | N19: =M19 -> 8900 | ... U19: =T19 -> 8900
B21: Sub-total for Operating costs | F21: =SUM(F14:F20) -> 171500 | G21: =SUM(G14:G20) -> 171500 | H21: =SUM(H14:H20) -> 171500 | I21: =SUM(I14:I20) -> 171500 | J21: =SUM(J14:J20) -> 171500 | K21: =SUM(K14:K20) -> 171500 | L21: =SUM(L14:L20) -> 171500 | M21: =SUM(M14:M20) -> 171500 | ... U21: =SUM(U14:U20) -> 171500
B23: Fixed costs
B24: Depreciation | C24: G$/annum | D24: 1 | E24: =E10/15 -> 33333.333 | F24: =D24*E24 -> 33333.333 | H24: =D24*E24 -> 33333.333 | I24: =H24 -> 33333.333 | J24: =I24 -> 33333.333 | K24: =J24 -> 33333.333 | L24: =K24 -> 33333.333 | M24: =L24 -> 33333.333 | N24: =M24 -> 33333.333 | O24: =N24 -> 33333.333 | P24: =O24 -> 33333.333 | ... U24: =T24 -> 33333.333 | V24: =SUM(H24:U24) -> 466666.67
B25: Land Rent | C25: Lumpsum | E25: 10000 | F25: =E25 -> 10000 | G25: =F25 -> 10000 | H25: =G25 -> 10000 | I25: =H25 -> 10000 | J25: =I25 -> 10000 | K25: =J25 -> 10000 | L25: =K25 -> 10000 | M25: =L25 -> 10000 | ... U25: =T25 -> 10000
B26: Sub-total for Fixed costs | F26: =SUM(F24:F24) -> 33333.333 | G26: =SUM(G24:G24) -> 0 | H26: =SUM(H24:H25) -> 43333.333 | I26: =SUM(I24:I24) -> 33333.333 | J26: =SUM(J24:J24) -> 33333.333 | K26: =SUM(K24:K24) -> 33333.333 | L26: =SUM(L24:L24) -> 33333.333 | M26: =SUM(M24:M24) -> 33333.333 | N26: =SUM(N24:N24) -> 33333.333 | O26: =SUM(O24:O24) -> 33333.333 | P26: =SUM(P24:P24) -> 33333.333 | ... U26: =SUM(U24:U24) -> 33333.333
B27: TOTAL COSTS | F27: =F11+F21+F26 -> 704833.33 | G27: =G11+G21+G26 -> 671500 | H27: =H11+H21+H26 -> 214833.33 | I27: =I11+I21+I26 -> 214833.33 | J27: =J11+J21+J26 -> 204833.33 | K27: =K11+K21+K26 -> 204833.33 | L27: =L11+L21+L26 -> 214833.33 | M27: =M11+M21+M26 -> 204833.33 | ... U27: =U11+U21+U26 -> 214833.33
B29: GROSS MARGIN | C29: G$s/annum | G29: =G6-G11-G21 -> -671500 | H29: =H6-H11-H21 -> -93500 | I29: =I6-I11-I21 -> -51500 | J29: =J6-J11-J21 -> 1648500 | K29: =K6-K11-K21 -> 88500 | L29: =L6-L11-L21 -> 78500 | M29: =M6-M11-M21 -> 88500 | N29: =N6-N11-N21 -> 88500 | ... U29: =U6-U11-U21 -> 78500
B30: NET MARGIN BEFORE PROFIT TAX | C30: G$s/annum | G30: =G29-G26 -> -671500 | H30: =H29-H26 -> -136833.33 | I30: =I29-I26 -> -84833.333 | J30: =J29-J26 -> 1615166.7 | K30: =K29-K26 -> 55166.667 | L30: =L29-L26 -> 45166.667 | M30: =M29-M26 -> 55166.667 | N30: =N29-N26 -> 55166.667 | ... U30: =U29-U26 -> 45166.667
B31: FIRR | G31: =IRR(G30:U30) -> 0.29104771
B32: FNPV | G32: =NPV(0.1,G30:U30) -> 545169.28
B35: ECONOMIC
C36: Unit | D36: Quantity | E36: Price | F36: Amount | G36: Year
B37: REVENUE | G37: 1 | H37: =G37+1 -> 2 | I37: =H37+1 -> 3 | J37: =I37+1 -> 4 | K37: =J37+1 -> 5 | L37: =K37+1 -> 6 | M37: =L37+1 -> 7 | N37: =M37+1 -> 8 | O37: =N37+1 -> 9 | P37: =O37+1 -> 10 | Q37: 11 | R37: 12 | S37: 13 | T37: 14 | U37: 15
B38: Sales | C38: lumpsum | D38: =D4 -> 1300 | E38: =E4 -> 200 | F38: =F4*0.9 -> 0 | G38: =F38 -> 0 | H38: =H4*0.9 -> 70200 | I38: =I4*0.9 -> 117000 | J38: =J4*0.9 -> 1638000 | K38: =K4*0.9 -> 234000 | L38: =L4*0.9 -> 234000 | M38: =M4*0.9 -> 234000 | N38: =N4*0.9 -> 234000 | O38: =O4*0.9 -> 234000 | ... U38: =U4*0.9 -> 234000
B39: Other income | C39: lumpsum | F39: =F5*0.9 -> 0 | G39: =F39 -> 0 | H39: =G39 -> 0 | I39: =H39 -> 0 | J39: =I39 -> 0 | K39: =J39 -> 0 | L39: =K39 -> 0 | M39: =L39 -> 0 | N39: =M39 -> 0 | ... U39: =T39 -> 0
B41: Sub-total Revenue | D41: =D6 -> 0 | E41: =E6*0.9 -> 0 | F41: =SUM(F38:F40) -> 0 | G41: =SUM(G38:G40) -> 0 | H41: =SUM(H38:H40) -> 70200 | I41: =SUM(I38:I40) -> 117000 | J41: =SUM(J38:J40) -> 1638000 | K41: =SUM(K38:K40) -> 234000 | L41: =SUM(L38:L40) -> 234000 | M41: =SUM(M38:M40) -> 234000 | ... U41: =SUM(U38:U40) -> 234000
D42: =D7 -> 0 | E42: =E7*0.9 -> 0
B43: COSTS | D43: =D8 -> 0 | E43: =E8*0.9 -> 0
B44: Investment Costs | D44: =D9 -> 0 | E44: =E9*0.9 -> 0
B45: Fixed Capital | C45: Nos. | D45: =D10 -> 1 | E45: =E10*1.2 -> 600000 | F45: =D45*E45 -> 600000 | G45: =D45*E45 -> 600000 | H45: 0 | I45: 0 | J45: 0 | P45: =K45 -> 0
B47: Sub-total Investment | D47: =D11 -> 0 | E47: =E11*0.9 -> 0 | F47: =SUM(F45:F46) -> 600000 | G47: =SUM(G45:G46) -> 600000 | H47: =SUM(H45:H46) -> 0 | I47: =SUM(I45:I46) -> 0 | J47: =SUM(J45:J46) -> 0 | K47: =SUM(K45:K46) -> 0 | L47: =SUM(L45:L46) -> 0 | M47: =SUM(M45:M46) -> 0 | ... U47: =SUM(U45:U46) -> 0
D48: =D12 -> 0 | E48: =E12*0.9 -> 0 | F48: =D48*E48 -> 0
B49: Operating costs | D49: =D13 -> 0 | E49: =E13*0.9 -> 0 | F49: =D49*E49 -> 0
B50: Seed and improved cost | C50: G$ | F50: =F14*0.9 -> 6300 | G50: =F50 -> 6300 | H50: =G50 -> 6300 | I50: =H50 -> 6300 | J50: =I50 -> 6300 | K50: =J50 -> 6300 | L50: =K50 -> 6300 | M50: =L50 -> 6300 | N50: =M50 -> 6300 | ... U50: =T50 -> 6300
B51: Irrigation | C51: G$ | F51: =F15*0.9 -> 135000 | G51: =F51 -> 135000 | H51: =G51 -> 135000 | I51: =H51 -> 135000 | J51: =I51 -> 135000 | K51: =J51 -> 135000 | L51: =K51 -> 135000 | M51: =L51 -> 135000 | N51: =M51 -> 135000 | ... U51: =T51 -> 135000
B52: Wages and Salary | C52: G$ | F52: =F16 -> 0 | G52: =F52 -> 0 | H52: =F52 -> 0 | I52: =H52 -> 0 | J52: =I52 -> 0 | K52: =J52 -> 0 | L52: =K52 -> 0 | M52: =L52 -> 0 | N52: =M52 -> 0 | O52: =N52 -> 0 | P52: =O52 -> 0 | ... U52: =T52 -> 0
B53: Transportation | C53: G$ | F53: =F17*0.8 -> 4480 | G53: =F53 -> 4480 | H53: =F53 -> 4480 | I53: =F53 -> 4480 | J53: =F53 -> 4480 | K53: =J53 -> 4480 | L53: =K53 -> 4480 | M53: =L53 -> 4480 | N53: =M53 -> 4480 | O53: =N53 -> 4480 | P53: =O53 -> 4480 | Q53: =P53 -> 4480 | R53: =Q53 -> 4480 | ... U53: =T53 -> 4480
G54: =F54 -> 0 | H54: =F54 -> 0 | I54: =F54 -> 0 | J54: =F54 -> 0 | K54: =J54 -> 0 | L54: =K54 -> 0 | M54: =L54 -> 0 | N54: =M54 -> 0 | O54: =N54 -> 0 | P54: =O54 -> 0 | Q54: =P54 -> 0 | R54: =Q54 -> 0 | ... U54: =T54 -> 0
B55: Damage | C55: G$ | F55: =F19*0.9 -> 8010 | G55: =F55 -> 8010 | H55: =F55 -> 8010 | I55: =F55 -> 8010 | J55: =F55 -> 8010 | K55: =J55 -> 8010 | L55: =K55 -> 8010 | M55: =L55 -> 8010 | N55: =M55 -> 8010 | O55: =N55 -> 8010 | P55: =O55 -> 8010 | Q55: =P55 -> 8010 | R55: =Q55 -> 8010 | ... U55: =T55 -> 8010
B56: Sub-total for Operating costs | D56: =D21 -> 0 | F56: =SUM(F50:F55) -> 153790 | G56: =SUM(G50:G55) -> 153790 | H56: =SUM(H50:H55) -> 153790 | I56: =SUM(I50:I55) -> 153790 | J56: =SUM(J50:J55) -> 153790 | K56: =SUM(K50:K55) -> 153790 | L56: =SUM(L50:L55) -> 153790 | M56: =SUM(M50:M55) -> 153790 | ... U56: =SUM(U50:U55) -> 153790
D57: =D22 -> 0
B58: Fixed costs | D58: =D23 -> 0
B59: Depreciation | C59: G$s/annum | D59: =D24 -> 1 | F59: =D59*E59 -> 0 | G59: 0 | H59: =D59*E59 -> 0 | I59: =H59 -> 0 | J59: =I59 -> 0 | K59: =J59 -> 0 | L59: =K59 -> 0 | M59: =L59 -> 0 | N59: =M59 -> 0 | O59: =N59 -> 0 | P59: =O59 -> 0 | ... U59: =T59 -> 0 | V59: =SUM(H59:U59) -> 0
B60: Sub-total for Fixed costs | F60: =SUM(F59:F59) -> 0 | G60: =SUM(G59:G59) -> 0 | H60: =SUM(H59:H59) -> 0 | I60: =SUM(I59:I59) -> 0 | J60: =SUM(J59:J59) -> 0 | K60: =SUM(K59:K59) -> 0 | L60: =SUM(L59:L59) -> 0 | M60: =SUM(M59:M59) -> 0 | ... U60: =SUM(U59:U59) -> 0
B61: TOTAL COSTS | F61: =F47+F56+F60 -> 753790 | G61: =G47+G56+G60 -> 753790 | H61: =H47+H56+H60 -> 153790 | I61: =I47+I56+I60 -> 153790 | J61: =J47+J56+J60 -> 153790 | K61: =K47+K56+K60 -> 153790 | L61: =L47+L56+L60 -> 153790 | M61: =M47+M56+M60 -> 153790 | ... U61: =U47+U56+U60 -> 153790
B63: GROSS MARGIN | C63: G$/annum | G63: =G41-G47-G56 -> -753790 | H63: =H41-H47-H56 -> -83590 | I63: =I41-I47-I56 -> -36790 | J63: =J41-J47-J56 -> 1484210 | K63: =K41-K47-K56 -> 80210 | L63: =L41-L47-L56 -> 80210 | M63: =M41-M47-M56 -> 80210 | N63: =N41-N47-N56 -> 80210 | ... U63: =U41-U47-U56 -> 80210
B64: NET MARGIN | C64: G$/annum | G64: =G63-G60 -> -753790 | H64: =H63-H60 -> -83590 | I64: =I63-I60 -> -36790 | J64: =J63-J60 -> 1484210 | K64: =K63-K60 -> 80210 | L64: =L63-L60 -> 80210 | M64: =M63-M60 -> 80210 | N64: =N63-N60 -> 80210 | ... U64: =U63-U60 -> 80210
B65: EIRR | G65: =IRR(G64:U64) -> 0.27723132
B66: ENPV | G66: =NPV(0.1,G64:U64) -> 587576.98

Sheet Cassava TF
B1: FINANCIAL
C2: Unit | D2: Quantity | E2: Price | F2: Amount | G2: Year
B3: REVENUE | G3: 1 | H3: =G3+1 -> 2 | I3: =H3+1 -> 3 | J3: =I3+1 -> 4 | K3: =J3+1 -> 5 | L3: =K3+1 -> 6 | M3: =L3+1 -> 7 | N3: =M3+1 -> 8 | O3: =N3+1 -> 9 | P3: =O3+1 -> 10 | Q3: 11 | R3: 12 | S3: 13 | T3: 14 | U3: 15
B4: Cassava | C4: lbs | D4: 10000 | E4: 520 | F4: =D4*E4 -> 5200000 | G4: =F4*0.3 -> 1560000 | H4: =F4*0.2 -> 1040000 | I4: =F4 -> 5200000 | J4: =F4 -> 5200000 | K4: =J4 -> 5200000 | L4: =K4 -> 5200000 | M4: =L4 -> 5200000 | N4: =M4 -> 5200000 | O4: =N4 -> 5200000 | P4: =O4 -> 5200000 | Q4: =P4 -> 5200000 | R4: =Q4 -> 5200000 | ... U4: =T4 -> 5200000
B6: Sub-total Revenue | F6: =SUM(F4:F5) -> 5200000 | G6: =SUM(G4:G5) -> 1560000 | H6: =SUM(H4:H5) -> 1040000 | I6: =SUM(I4:I5) -> 5200000 | J6: =SUM(J4:J5) -> 5200000 | K6: =SUM(K4:K5) -> 5200000 | L6: =SUM(L4:L5) -> 5200000 | M6: =SUM(M4:M5) -> 5200000 | ... U6: =SUM(U4:U5) -> 5200000
B8: COSTS
B9: Investment Costs
B10: Land cost | C10: lumpsum | D10: 10 | E10: 100000 | F10: =D10*E10 -> 1000000 | G10: =D10*E10 -> 1000000 | H10: =G10 -> 1000000 | I10: 0 | J10: 0 | L10: =G10 -> 1000000 | O10: =L10 -> 1000000 | P10: =K10 -> 0 | T10: =O10 -> 1000000
B11: Other Fixed Cost | C11: lumpsum | D11: 1 | E11: 50000 | F11: =D11*E11 -> 50000 | G11: =D11*E11 -> 50000 | H11: 0 | I11: 0 | J11: 0 | K11: 0
B12: Sub-total Investment | F12: =SUM(F10:F11) -> 1050000 | G12: =SUM(G10:G11) -> 1050000 | H12: =SUM(H10:H11) -> 1000000 | I12: =SUM(I10:I11) -> 0 | J12: =SUM(J10:J11) -> 0 | K12: =SUM(K10:K11) -> 0 | M12: =SUM(M10:M11) -> 0 | N12: =SUM(N10:N11) -> 0 | P12: =SUM(P10:P11) -> 0 | R12: =SUM(R10:R11) -> 0 | S12: =SUM(S10:S11) -> 0 | T12: =SUM(T10:T11) -> 1000000 | U12: =SUM(U10:U11) -> 0
F13: =D13*E13 -> 0
B14: Operating costs | F14: =D14*E14 -> 0
B15: Land prepare cultivation | C15: G$ | F15: =E15 -> 0 | G15: =F15 -> 0 | H15: =F15 -> 0 | I15: =H15 -> 0 | J15: =I15 -> 0 | K15: =J15 -> 0 | L15: =K15 -> 0 | M15: =L15 -> 0 | N15: =M15 -> 0 | O15: =N15 -> 0 | P15: =O15 -> 0 | ... U15: =T15 -> 0
B16: Wages and Salary | C16: G$ | D16: 2000 | E16: 900 | F16: =D16*E16 -> 1800000 | G16: =F16*0.75 -> 1350000 | H16: =F16 -> 1800000 | I16: =H16 -> 1800000 | J16: =I16 -> 1800000 | K16: =J16 -> 1800000 | L16: =K16 -> 1800000 | M16: =L16 -> 1800000 | N16: =M16 -> 1800000 | O16: =N16 -> 1800000 | P16: =O16 -> 1800000 | ... U16: =T16 -> 1800000
B17: Irrigation Expenses | C17: G$ | D17: 12 | E17: 45000 | F17: =D17*E17 -> 540000 | G17: =F17 -> 540000 | H17: =D17*E17*1 -> 540000 | I17: =D17*E17*1 -> 540000 | J17: =D17*E17 -> 540000 | K17: =J17 -> 540000 | L17: =K17 -> 540000 | M17: =L17 -> 540000 | N17: =M17 -> 540000 | O17: =N17 -> 540000 | P17: =O17 -> 540000 | Q17: =P17 -> 540000 | R17: =Q17 -> 540000 | ... U17: =T17 -> 540000
B18: Fertilizer and weed control | C18: G$ | D18: 12 | E18: 55000 | F18: =D18*E18 -> 660000 | G18: =F18 -> 660000 | H18: =F18 -> 660000 | I18: =H18 -> 660000 | J18: =I18 -> 660000 | K18: =J18 -> 660000 | L18: =K18 -> 660000 | M18: =L18 -> 660000 | N18: =M18 -> 660000 | O18: =N18 -> 660000 | P18: =O18 -> 660000 | ... U18: =T18 -> 660000
B19: Seed and plant | C19: G$ | D19: 100 | E19: 1000 | F19: =D19*E19 -> 100000 | G19: =F19 -> 100000 | H19: =G19 -> 100000 | I19: =H19 -> 100000 | J19: =I19 -> 100000 | K19: =J19 -> 100000 | L19: =K19 -> 100000 | M19: =L19 -> 100000 | N19: =M19 -> 100000 | ... U19: =T19 -> 100000
B20: Harvest | C20: G$ | D20: 1 | E20: 500000 | F20: =D20*E20 -> 500000 | G20: =F20 -> 500000 | H20: =F20 -> 500000 | I20: =F20 -> 500000 | J20: =F20 -> 500000 | K20: =J20 -> 500000 | L20: =K20 -> 500000 | M20: =L20 -> 500000 | N20: =M20 -> 500000 | O20: =N20 -> 500000 | P20: =O20 -> 500000 | Q20: =P20 -> 500000 | R20: =Q20 -> 500000 | ... U20: =T20 -> 500000
B21: Sub-total for Operating costs | F21: =SUM(F15:F20) -> 3600000 | G21: =SUM(G15:G20) -> 3150000 | H21: =SUM(H15:H20) -> 3600000 | I21: =SUM(I15:I20) -> 3600000 | J21: =SUM(J15:J20) -> 3600000 | K21: =SUM(K15:K20) -> 3600000 | L21: =SUM(L15:L20) -> 3600000 | M21: =SUM(M15:M20) -> 3600000 | ... U21: =SUM(U15:U20) -> 3600000
B23: Fixed costs
B24: Depreciation | C24: G$/annum | D24: 1 | E24: =E11/12 -> 4166.6667 | F24: =D24*E24 -> 4166.6667 | G24: =F24 -> 4166.6667 | H24: =D24*E24 -> 4166.6667 | I24: =H24 -> 4166.6667 | J24: =I24 -> 4166.6667 | K24: =J24 -> 4166.6667 | L24: =K24 -> 4166.6667 | M24: =L24 -> 4166.6667 | N24: =M24 -> 4166.6667 | O24: =N24 -> 4166.6667 | P24: =O24 -> 4166.6667 | ... U24: =T24 -> 4166.6667 | V24: =SUM(H24:U24) -> 58333.333
B25: Sub-total for Fixed costs | F25: =SUM(F24:F24) -> 4166.6667 | G25: =SUM(G24:G24) -> 4166.6667 | H25: =SUM(H24:H24) -> 4166.6667 | I25: =SUM(I24:I24) -> 4166.6667 | J25: =SUM(J24:J24) -> 4166.6667 | K25: =SUM(K24:K24) -> 4166.6667 | L25: =SUM(L24:L24) -> 4166.6667 | M25: =SUM(M24:M24) -> 4166.6667 | ... U25: =SUM(U24:U24) -> 4166.6667
B26: TOTAL COSTS | F26: =F12+F21+F25 -> 4654166.7 | G26: =G12+G21+G25 -> 4204166.7 | H26: =H12+H21+H25 -> 4604166.7 | I26: =I12+I21+I25 -> 3604166.7 | J26: =J12+J21+J25 -> 3604166.7 | K26: =K12+K21+K25 -> 3604166.7 | L26: =L12+L21+L25 -> 3604166.7 | M26: =M12+M21+M25 -> 3604166.7 | ... U26: =U12+U21+U25 -> 3604166.7
B28: GROSS MARGIN | C28: G$/annum | G28: =G6-G12-G21 -> -2640000 | H28: =H6-H12-H21 -> -3560000 | I28: =I6-I12-I21 -> 1600000 | J28: =J6-J12-J21 -> 1600000 | K28: =K6-K12-K21 -> 1600000 | L28: =L6-L12-L21 -> 1600000 | M28: =M6-M12-M21 -> 1600000 | N28: =N6-N12-N21 -> 1600000 | ... U28: =U6-U12-U21 -> 1600000
B29: NET MARGIN BEFORE PROFIT TAX | C29: G$/annum | G29: =G28-G25 -> -2644166.7 | H29: =(H28-H25) -> -3564166.7 | I29: =(I28-I25) -> 1595833.3 | J29: =J28-J25 -> 1595833.3 | K29: =K28-K25 -> 1595833.3 | L29: =L28-L25 -> 1595833.3 | M29: =M28-M25 -> 1595833.3 | N29: =N28-N25 -> 1595833.3 | O29: =O28-O25 -> 1595833.3 | P29: =P28-P25 -> 1595833.3 | Q29: =Q28-Q25 -> 1595833.3 | ... U29: =U28-U25 -> 1595833.3
B30: FIRR | G30: =IRR(G29:U29) -> 0.21348721
B31: FNPV | G31: =NPV(0.1,G29:U29) -> 3755695.7
B39: ECONOMIC
C40: Unit | D40: Quantity | E40: Price | F40: Amount | G40: Year
B41: REVENUE | G41: 1 | H41: =G41+1 -> 2 | I41: =H41+1 -> 3 | J41: =I41+1 -> 4 | K41: =J41+1 -> 5 | L41: =K41+1 -> 6 | M41: =L41+1 -> 7 | N41: =M41+1 -> 8 | O41: =N41+1 -> 9 | P41: =O41+1 -> 10 | Q41: 11 | R41: 12 | S41: 13 | T41: 14 | U41: 15
B42: Cassava | C42: lbs | D42: =D4 -> 10000 | E42: =E4*0.92 -> 478.4 | F42: =D42*E42 -> 4784000 | G42: =F42*0.3 -> 1435200 | H42: =F42*0.2 -> 956800 | I42: =F42 -> 4784000 | J42: =F42 -> 4784000 | K42: =J42 -> 4784000 | L42: =K42 -> 4784000 | M42: =L42 -> 4784000 | N42: =M42 -> 4784000 | O42: =N42 -> 4784000 | P42: =O42 -> 4784000 | Q42: =P42 -> 4784000 | R42: =Q42 -> 4784000 | ... U42: =T42 -> 4784000
B43: Sub-total Revenue | D43: =D6 -> 0 | E43: =E6*0.9 -> 0 | F43: =SUM(F42:F42) -> 4784000 | G43: =SUM(G42:G42) -> 1435200 | H43: =SUM(H42:H42) -> 956800 | I43: =SUM(I42:I42) -> 4784000 | J43: =SUM(J42:J42) -> 4784000 | K43: =SUM(K42:K42) -> 4784000 | L43: =SUM(L42:L42) -> 4784000 | M43: =SUM(M42:M42) -> 4784000 | ... U43: =SUM(U42:U42) -> 4784000
D44: =D7 -> 0 | E44: =E7*0.9 -> 0
B45: COSTS | D45: =D8 -> 0 | E45: =E8*0.9 -> 0
B46: Investment Costs | D46: =D9 -> 0 | E46: =E9*0.9 -> 0
B47: Land cost | C47: lumpsum | D47: =D10 -> 10 | E47: =E10*0.9 -> 90000 | F47: =D47*E47 -> 900000 | G47: =D47*E47 -> 900000 | H47: 0 | I47: 0 | J47: 0 | P47: =K47 -> 0
B48: Other Fixed Cost | C48: lumpsum | D48: =D11 -> 1 | E48: =E11*0.9 -> 45000 | F48: =D48*E48 -> 45000 | G48: =D48*E48 -> 45000 | H48: 0 | I48: 0 | J48: 0 | K48: 0
B49: Sub-total Investment | D49: =D12 -> 0 | E49: =E12*0.9 -> 0 | F49: =SUM(F47:F48) -> 945000 | G49: =SUM(G47:G48) -> 945000 | H49: =SUM(H47:H48) -> 0 | I49: =SUM(I47:I48) -> 0 | J49: =SUM(J47:J48) -> 0 | K49: =SUM(K47:K48) -> 0 | L49: =SUM(L47:L48) -> 0 | M49: =SUM(M47:M48) -> 0 | ... U49: =SUM(U47:U48) -> 0
D50: =D13 -> 0 | E50: =E13*0.9 -> 0 | F50: =D50*E50 -> 0
B51: Operating costs | D51: =D14 -> 0 | E51: =E14*0.9 -> 0 | F51: =D51*E51 -> 0
B52: Land prepare and cultivation | C52: G$ | D52: =D15 -> 0 | E52: =E15*0.9 -> 0 | F52: =E52 -> 0 | G52: =F52 -> 0 | H52: =F52 -> 0 | I52: =H52 -> 0 | J52: =I52 -> 0 | K52: =J52 -> 0 | L52: =K52 -> 0 | M52: =L52 -> 0 | N52: =M52 -> 0 | O52: =N52 -> 0 | P52: =O52 -> 0 | ... U52: =T52 -> 0
B53: Wages and Salary | C53: G$ | D53: =D16 -> 2000 | E53: =E16*0.9 -> 810 | F53: =D53*E53 -> 1620000 | G53: =F53*0.75 -> 1215000 | H53: =D53*E53*1 -> 1620000 | I53: =D53*E53*1 -> 1620000 | J53: =D53*E53 -> 1620000 | K53: =J53 -> 1620000 | L53: =K53 -> 1620000 | M53: =L53 -> 1620000 | N53: =M53 -> 1620000 | O53: =N53 -> 1620000 | P53: =O53 -> 1620000 | Q53: =P53 -> 1620000 | R53: =Q53 -> 1620000 | ... U53: =T53 -> 1620000
B54: Irrigation Expenses | C54: G$ | D54: =D17 -> 12 | E54: =E17*0.9 -> 40500 | F54: =D54*E54 -> 486000 | G54: =F54 -> 486000 | H54: =F54 -> 486000 | I54: =H54 -> 486000 | J54: =I54 -> 486000 | K54: =J54 -> 486000 | L54: =K54 -> 486000 | M54: =L54 -> 486000 | N54: =M54 -> 486000 | O54: =N54 -> 486000 | P54: =O54 -> 486000 | ... U54: =T54 -> 486000
B55: Fertilizer and weed control | C55: G$ | D55: =D18 -> 12 | E55: =E18*0.9 -> 49500 | F55: =D55*E55 -> 594000 | G55: =F55 -> 594000 | H55: =F55 -> 594000 | I55: =F55 -> 594000 | J55: =F55 -> 594000 | K55: =J55 -> 594000 | L55: =K55 -> 594000 | M55: =L55 -> 594000 | N55: =M55 -> 594000 | O55: =N55 -> 594000 | P55: =O55 -> 594000 | Q55: =P55 -> 594000 | R55: =Q55 -> 594000 | ... U55: =T55 -> 594000
B56: Seed and Plant | C56: G$ | D56: =D19 -> 100 | E56: =E19*0.9 -> 900 | F56: =D56*E56 -> 90000 | G56: =F56 -> 90000 | H56: =D56*E56*1 -> 90000 | I56: =D56*E56*1 -> 90000 | J56: =D56*E56 -> 90000 | K56: =J56 -> 90000 | L56: =K56 -> 90000 | M56: =L56 -> 90000 | N56: =M56 -> 90000 | O56: =N56 -> 90000 | P56: =O56 -> 90000 | Q56: =P56 -> 90000 | R56: =Q56 -> 90000 | ... U56: =T56 -> 90000
B57: Harvest | C57: G$ | D57: =D20 -> 1 | E57: =E20*0.9 -> 450000 | F57: =D57*E57 -> 450000 | G57: =F57 -> 450000 | H57: =D57*E57*1 -> 450000 | I57: =D57*E57*1 -> 450000 | J57: =D57*E57 -> 450000 | K57: =J57 -> 450000 | L57: =K57 -> 450000 | M57: =L57 -> 450000 | N57: =M57 -> 450000 | O57: =N57 -> 450000 | P57: =O57 -> 450000 | Q57: =P57 -> 450000 | R57: =Q57 -> 450000 | ... U57: =T57 -> 450000
B58: Sub-total for Operating costs | D58: =D21 -> 0 | F58: =SUM(F52:F57) -> 3240000 | G58: =SUM(G52:G57) -> 2835000 | H58: =SUM(H52:H57) -> 3240000 | I58: =SUM(I52:I57) -> 3240000 | J58: =SUM(J52:J57) -> 3240000 | K58: =SUM(K52:K57) -> 3240000 | L58: =SUM(L52:L57) -> 3240000 | M58: =SUM(M52:M57) -> 3240000 | ... U58: =SUM(U52:U57) -> 3240000
D59: =D22 -> 0
B60: Fixed costs | D60: =D23 -> 0
B61: Depreciation (Shed) | C61: G$/annum | D61: =D24 -> 1 | E61: =E24*0.9 -> 3750 | F61: =D61*E61 -> 3750 | G61: 0 | H61: =D61*E61 -> 3750 | I61: =H61 -> 3750 | J61: =I61 -> 3750 | K61: =J61 -> 3750 | L61: =K61 -> 3750 | M61: =L61 -> 3750 | N61: =M61 -> 3750 | O61: =N61 -> 3750 | P61: =O61 -> 3750 | ... U61: =T61 -> 3750 | V61: =SUM(H61:U61) -> 52500
B62: Sub-total for Fixed costs | F62: =SUM(F61:F61) -> 3750 | G62: =SUM(G61:G61) -> 0 | H62: =SUM(H61:H61) -> 3750 | I62: =SUM(I61:I61) -> 3750 | J62: =SUM(J61:J61) -> 3750 | K62: =SUM(K61:K61) -> 3750 | L62: =SUM(L61:L61) -> 3750 | M62: =SUM(M61:M61) -> 3750 | ... U62: =SUM(U61:U61) -> 3750
B63: TOTAL COSTS | F63: =F49+F58+F62 -> 4188750 | G63: =G49+G58+G62 -> 3780000 | H63: =H49+H58+H62 -> 3243750 | I63: =I49+I58+I62 -> 3243750 | J63: =J49+J58+J62 -> 3243750 | K63: =K49+K58+K62 -> 3243750 | L63: =L49+L58+L62 -> 3243750 | M63: =M49+M58+M62 -> 3243750 | ... U63: =U49+U58+U62 -> 3243750
B65: GROSS MARGIN | C65: G$/annum | G65: =G43-G49-G58 -> -2344800 | H65: =H43-H49-H58 -> -2283200 | I65: =I43-I49-I58 -> 1544000 | J65: =J43-J49-J58 -> 1544000 | K65: =K43-K49-K58 -> 1544000 | L65: =L43-L49-L58 -> 1544000 | M65: =M43-M49-M58 -> 1544000 | N65: =N43-N49-N58 -> 1544000 | ... U65: =U43-U49-U58 -> 1544000
B66: NET MARGIN | C66: G$/annum | G66: =G65-G62 -> -2344800 | H66: =(H65-H62) -> -2286950 | I66: =-(I65-I62) -> -1540250 | J66: =J65-J62 -> 1540250 | K66: =K65-K62 -> 1540250 | L66: =L65-L62 -> 1540250 | M66: =M65-M62 -> 1540250 | N66: =N65-N62 -> 1540250 | O66: =O65-O62 -> 1540250 | P66: =P65-P62 -> 1540250 | Q66: =Q65-Q62 -> 1540250 | ... U66: =U65-U62 -> 1540250
B67: EIRR | G67: =IRR(G66:U66) -> 0.17674786
B68: ENPV | G68: =NPV(0.1,G66:U66) -> 2705999.9

Sheet Cassava processing TF
B1: FINANCIAL
C2: Unit | D2: Quantity | E2: Price | F2: Amount | G2: Year
B3: REVENUE | G3: 1 | H3: =G3+1 -> 2 | I3: =H3+1 -> 3 | J3: =I3+1 -> 4 | K3: =J3+1 -> 5 | L3: =K3+1 -> 6 | M3: =L3+1 -> 7 | N3: =M3+1 -> 8 | O3: =N3+1 -> 9 | P3: =O3+1 -> 10 | Q3: 11 | R3: 12 | S3: 13 | T3: 14 | U3: 15
B4: Sales from cassava bread | C4: bags | D4: 2363 | E4: 4750 | F4: 0 | G4: 0 | H4: =I4*0.2 -> 134691 | I4: =J4*0.2 -> 673455 | J4: =K4*0.3 -> 3367275 | K4: =D4*E4 -> 11224250 | L4: =K4*0.6 -> 6734550 | M4: =L4 -> 6734550 | N4: =M4 -> 6734550 | O4: =N4 -> 6734550 | P4: =O4 -> 6734550 | Q4: =P4 -> 6734550 | R4: =Q4 -> 6734550 | S4: =R4 -> 6734550 | T4: =S4 -> 6734550 | U4: =T4 -> 6734550
B5: Sales from other diversification (Cassava jam, Cassava chips, Cassava cake) | C5: Lumpsum | D5: 1 | E5: 0 | F5: 0 | H5: =E5 -> 0 | I5: =E5 -> 0 | J5: =I5 -> 0 | K5: =J5 -> 0 | L5: =K5 -> 0 | M5: =L5 -> 0 | N5: =M5 -> 0 | O5: =N5 -> 0 | P5: =O5 -> 0 | Q5: =P5 -> 0 | ... U5: =T5 -> 0
K6: =J6 -> 0 | L6: =K6 -> 0 | M6: =L6 -> 0 | N6: =M6 -> 0 | O6: =N6 -> 0 | P6: =O6 -> 0 | Q6: =P6 -> 0 | R6: =Q6 -> 0 | ... U6: =T6 -> 0
G7: =F7 -> 0 | H7: =F7 -> 0 | I7: =G7 -> 0 | J7: =H7 -> 0 | K7: =J7 -> 0 | L7: =K7 -> 0 | M7: =L7 -> 0 | N7: =M7 -> 0 | O7: =N7 -> 0 | P7: =O7 -> 0 | Q7: =P7 -> 0 | R7: =Q7 -> 0 | ... U7: =T7 -> 0
B8: Sub-total Revenue | F8: =SUM(F4:F7) -> 0 | G8: =SUM(G4:G7) -> 0 | H8: =SUM(H4:H7) -> 134691 | I8: =SUM(I4:I7) -> 673455 | J8: =SUM(J4:J7) -> 3367275 | K8: =SUM(K4:K7) -> 11224250 | L8: =SUM(L4:L7) -> 6734550 | M8: =SUM(M4:M7) -> 6734550 | ... U8: =SUM(U4:U7) -> 6734550
B10: COSTS
B11: Investment Costs
B12: Fixed Capital | C12: ha | D12: 10 | E12: 300000 | F12: =D12*E12 -> 3000000 | G12: =D12*E12 -> 3000000 | H12: =G12 -> 3000000 | I12: 0 | L12: 10000 | O12: 10000 | R12: 10000 | U12: 10000
B13: Sub-total Investment | F13: =SUM(F12:F12) -> 3000000 | G13: =SUM(G12:G12) -> 3000000 | H13: =SUM(H12:H12) -> 3000000 | I13: =SUM(I12:I12) -> 0 | J13: =SUM(J12:J12) -> 0 | K13: =SUM(K12:K12) -> 0 | L13: =SUM(L12:L12) -> 10000 | M13: =SUM(M12:M12) -> 0 | ... U13: =SUM(U12:U12) -> 10000
F14: =D14*E14 -> 0
B15: Operating costs | F15: =D15*E15 -> 0
B16: Raw materials | C16: G$ | D16: 10 | E16: 1000 | F16: =E16*D16 -> 10000 | G16: =F16 -> 10000 | H16: =G16 -> 10000 | I16: =H16 -> 10000 | J16: =I16 -> 10000 | K16: =J16 -> 10000 | L16: =K16 -> 10000 | M16: =L16 -> 10000 | N16: =M16 -> 10000 | ... U16: =T16 -> 10000
B17: Wages and salary | C17: G$ | D17: 200 | E17: 1500 | F17: =D17*E17 -> 300000 | G17: =F17 -> 300000 | H17: =G17 -> 300000 | I17: =H17 -> 300000 | J17: =I17 -> 300000 | K17: =J17 -> 300000 | L17: =K17 -> 300000 | M17: =L17 -> 300000 | N17: =M17 -> 300000 | ... U17: =T17 -> 300000
B18: Black tanks | C18: G$ | F18: =J4*0.4 -> 1346910 | G18: =F18 -> 1346910 | H18: =G18 -> 1346910 | I18: =H18 -> 1346910 | J18: =J4*0.75 -> 2525456.2 | K18: =J18 -> 2525456.2 | L18: =K18 -> 2525456.2 | M18: =L18 -> 2525456.2 | N18: =M18 -> 2525456.2 | O18: =N18 -> 2525456.2 | P18: =O18 -> 2525456.2 | Q18: =P18 -> 2525456.2 | R18: =Q18 -> 2525456.2 | ... U18: =T18 -> 2525456.2
B19: Transportation | C19: G$ | F19: 905000 | G19: =F19 -> 905000 | H19: =G19 -> 905000 | I19: =H19 -> 905000 | J19: 10000 | K19: =J19 -> 10000 | L19: =K19 -> 10000 | M19: =L19 -> 10000 | N19: =M19 -> 10000 | O19: =N19 -> 10000 | P19: =O19 -> 10000 | Q19: =P19 -> 10000 | R19: =Q19 -> 10000 | ... U19: =T19 -> 10000
B20: Electric equipment | C20: G$ | F20: 900000 | G20: =F20 -> 900000 | H20: =G20 -> 900000 | I20: =H20 -> 900000 | J20: =I20 -> 900000 | K20: =J20 -> 900000 | L20: =K20 -> 900000 | M20: =L20 -> 900000 | N20: =M20 -> 900000 | ... U20: =T20 -> 900000
B21: Damage | C21: G$ | F21: 8900 | G21: =F21 -> 8900 | H21: =G21 -> 8900 | I21: =H21 -> 8900 | J21: =I21 -> 8900 | K21: =J21 -> 8900 | L21: =K21 -> 8900 | M21: =L21 -> 8900 | N21: =M21 -> 8900 | ... U21: =T21 -> 8900
B23: Sub-total for Operating costs | F23: =SUM(F16:F22) -> 3470810 | G23: =SUM(G16:G22) -> 3470810 | H23: =SUM(H16:H22) -> 3470810 | I23: =SUM(I16:I22) -> 3470810 | J23: =SUM(J16:J22) -> 3754356.2 | K23: =SUM(K16:K22) -> 3754356.2 | L23: =SUM(L16:L22) -> 3754356.2 | M23: =SUM(M16:M22) -> 3754356.2 | ... U23: =SUM(U16:U22) -> 3754356.2
B25: Fixed costs
B26: Depreciation | C26: G$/anuum | D26: 1 | E26: =E12/15 -> 20000 | F26: =D26*E26 -> 20000 | H26: =D26*E26 -> 20000 | I26: =H26 -> 20000 | J26: =I26 -> 20000 | K26: =J26 -> 20000 | L26: =K26 -> 20000 | M26: =L26 -> 20000 | N26: =M26 -> 20000 | O26: =N26 -> 20000 | P26: =O26 -> 20000 | ... U26: =T26 -> 20000 | V26: =SUM(H26:U26) -> 280000
B27: Sub-total for Fixed costs | F27: =SUM(F26:F26) -> 20000 | G27: =SUM(G26:G26) -> 0 | H27: =SUM(H26:H26) -> 20000 | I27: =SUM(I26:I26) -> 20000 | J27: =SUM(J26:J26) -> 20000 | K27: =SUM(K26:K26) -> 20000 | L27: =SUM(L26:L26) -> 20000 | M27: =SUM(M26:M26) -> 20000 | ... U27: =SUM(U26:U26) -> 20000
B28: TOTAL COSTS | F28: =F13+F23+F27 -> 6490810 | G28: =G13+G23+G27 -> 6470810 | H28: =H13+H23+H27 -> 6490810 | I28: =I13+I23+I27 -> 3490810 | J28: =J13+J23+J27 -> 3774356.2 | K28: =K13+K23+K27 -> 3774356.2 | L28: =L13+L23+L27 -> 3784356.2 | M28: =M13+M23+M27 -> 3774356.2 | ... U28: =U13+U23+U27 -> 3784356.2
B30: GROSS MARGIN | C30: G$s/annum | G30: =G8-G13-G23 -> -6470810 | H30: =H8-H13-H23 -> -6336119 | I30: =I8-I13-I23 -> -2797355 | J30: =J8-J13-J23 -> -387081.25 | K30: =K8-K13-K23 -> 7469893.8 | L30: =L8-L13-L23 -> 2970193.8 | M30: =M8-M13-M23 -> 2980193.8 | N30: =N8-N13-N23 -> 2980193.8 | ... U30: =U8-U13-U23 -> 2970193.8
B31: NET MARGIN BEFORE PROFIT TAX | C31: G$s/annum | G31: =G30-G27 -> -6470810 | H31: =H30-H27 -> -6356119 | I31: =I30-I27 -> -2817355 | J31: =J30-J27 -> -407081.25 | K31: =K30-K27 -> 7449893.8 | L31: =L30-L27 -> 2950193.8 | M31: =M30-M27 -> 2960193.8 | N31: =N30-N27 -> 2960193.8 | ... U31: =U30-U27 -> 2950193.8
B32: FIRR | G32: =IRR(H31:U31) -> 0.25987
B33: FNPV | G33: =NPV(0.1,G31:U31) -> 2374029.7
B36: ECONOMIC
C37: Unit | D37: Quantity | E37: Price | F37: Amount | G37: Year
B38: REVENUE | G38: 1 | H38: =G38+1 -> 2 | I38: =H38+1 -> 3 | J38: =I38+1 -> 4 | K38: =J38+1 -> 5 | L38: =K38+1 -> 6 | M38: =L38+1 -> 7 | N38: =M38+1 -> 8 | O38: =N38+1 -> 9 | P38: =O38+1 -> 10 | Q38: 11 | R38: 12 | S38: 13 | T38: 14 | U38: 15
B39: Sales | C39: lumpsum | D39: =D4 -> 2363 | E39: =E4*1.1 -> 5225 | F39: =F4*0.9 -> 0 | G39: =F39 -> 0 | H39: =H4*0.9 -> 121221.9 | I39: =I4*0.9 -> 606109.5 | J39: =J4*0.9 -> 3030547.5 | K39: =K4*0.9 -> 10101825 | L39: =L4*0.9 -> 6061095 | M39: =M4*0.9 -> 6061095 | N39: =N4*0.9 -> 6061095 | O39: =N39*0.9 -> 5454985.5 | P39: =O39 -> 5454985.5 | Q39: =P39 -> 5454985.5 | R39: =Q39 -> 5454985.5 | S39: =R39 -> 5454985.5 | T39: =S39 -> 5454985.5 | U39: =T39 -> 5454985.5
B40: Income from gum arabic export | C40: lumpsum | D40: 1 | E40: =E5 -> 0 | F40: =F7*0.9 -> 0 | G40: =F40 -> 0 | H40: =J40 -> 0 | I40: =H40 -> 0 | J40: =E40*0.9 -> 0 | K40: =J40 -> 0 | L40: =K40 -> 0 | M40: =L40 -> 0 | N40: =M40 -> 0 | O40: =N40 -> 0 | P40: =O40 -> 0 | Q40: =P40 -> 0 | R40: =Q40 -> 0 | ... U40: =T40 -> 0
J41: =E41*0.9 -> 0 | K41: =F41*0.9 -> 0 | L41: =G41*0.9 -> 0 | M41: =H41*0.9 -> 0 | N41: =I41*0.9 -> 0 | O41: =J41*0.9 -> 0 | P41: =K41*0.9 -> 0 | Q41: =L41*0.9 -> 0 | ... U41: =P41*0.9 -> 0
B42: Sub-total Revenue | D42: =D8 -> 0 | E42: =E8*0.9 -> 0 | F42: =SUM(F39:F41) -> 0 | G42: =SUM(G39:G41) -> 0 | H42: =SUM(H39:H41) -> 121221.9 | I42: =I8 -> 673455 | J42: =SUM(J39:J41) -> 3030547.5 | K42: =SUM(K39:K41) -> 10101825 | L42: =SUM(L39:L41) -> 6061095 | M42: =SUM(M39:M41) -> 6061095 | N42: =SUM(N39:N41) -> 6061095 | O42: =SUM(O39:O41) -> 5454985.5 | P42: =SUM(P39:P41) -> 5454985.5 | Q42: =SUM(Q39:Q41) -> 5454985.5 | ... U42: =SUM(U39:U41) -> 5454985.5
D43: =D9 -> 0 | E43: =E9*0.9 -> 0
B44: COSTS | D44: =D10 -> 0 | E44: =E10*0.9 -> 0
B45: Investment Costs | D45: =D11 -> 0 | E45: =E11*0.9 -> 0
B46: Fixed Capital | C46: Nos. | D46: 10 | E46: =E12*0.9 -> 270000 | F46: =F12*0.9 -> 2700000 | G46: =G12 -> 3000000 | I46: 0 | J46: 0 | P46: =K46 -> 0
B48: Sub-total Investment | D48: =D13 -> 0 | E48: =E13*0.9 -> 0 | F48: =SUM(F46:F47) -> 2700000 | G48: =SUM(G46:G47) -> 3000000 | H48: =SUM(H46:H47) -> 0 | J48: =SUM(J46:J47) -> 0 | K48: =SUM(K46:K47) -> 0 | M48: =SUM(M46:M47) -> 0 | N48: =SUM(N46:N47) -> 0 | P48: =SUM(P46:P47) -> 0 | Q48: =SUM(Q46:Q47) -> 0 | R48: 10000 | S48: =SUM(S46:S47) -> 0 | T48: =SUM(T46:T47) -> 0 | U48: 10000
D49: =D14 -> 0 | E49: =E14*0.9 -> 0 | F49: =D49*E49 -> 0
B50: Operating costs | D50: =D15 -> 0 | E50: =E15*0.9 -> 0 | F50: =D50*E50 -> 0
B51: Raw materials | C51: G$ | F51: =F16*0.9 -> 9000 | G51: =F51 -> 9000 | H51: =G51 -> 9000 | I51: =H51 -> 9000 | J51: =I51 -> 9000 | K51: =J51 -> 9000 | L51: =K51 -> 9000 | M51: =L51 -> 9000 | N51: =M51 -> 9000 | ... U51: =T51 -> 9000
B52: Electric equipment | C52: G$ | F52: =F17*0.9 -> 270000 | G52: =F52 -> 270000 | H52: =G52 -> 270000 | I52: =H52 -> 270000 | J52: =I52 -> 270000 | K52: =J52 -> 270000 | L52: =K52 -> 270000 | M52: =L52 -> 270000 | N52: =M52 -> 270000 | ... U52: =T52 -> 270000
B53: Wage and salary | C53: G$ | F53: =F18*0.9 -> 1212219 | G53: =F53 -> 1212219 | H53: =F53 -> 1212219 | I53: =H53 -> 1212219 | J53: =J42*0.6 -> 1818328.5 | K53: =J53 -> 1818328.5 | L53: =K53 -> 1818328.5 | M53: =L53 -> 1818328.5 | N53: =M53 -> 1818328.5 | O53: =N53 -> 1818328.5 | P53: =O53 -> 1818328.5 | Q53: =P53 -> 1818328.5 | R53: =Q53 -> 1818328.5 | ... U53: =T53 -> 1818328.5
B54: Transportation | C54: G$ | F54: =F19*0.8 -> 724000 | G54: =F54 -> 724000 | H54: =F54 -> 724000 | I54: =F54 -> 724000 | J54: =F54 -> 724000 | K54: =J54 -> 724000 | L54: =K54 -> 724000 | M54: =L54 -> 724000 | N54: =M54 -> 724000 | O54: =N54 -> 724000 | P54: =O54 -> 724000 | Q54: =P54 -> 724000 | R54: =Q54 -> 724000 | ... U54: =T54 -> 724000
G55: =F55 -> 0 | H55: =F55 -> 0 | I55: =F55 -> 0 | J55: =F55 -> 0 | K55: =J55 -> 0 | L55: =K55 -> 0 | M55: =L55 -> 0 | N55: =M55 -> 0 | O55: =N55 -> 0 | P55: =O55 -> 0 | Q55: =P55 -> 0 | R55: =Q55 -> 0 | ... U55: =T55 -> 0
B56: Damage | C56: G$ | F56: =F21*0.9 -> 8010 | G56: =F56 -> 8010 | H56: =F56 -> 8010 | I56: =F56 -> 8010 | J56: =F56 -> 8010 | K56: =J56 -> 8010 | L56: =K56 -> 8010 | M56: =L56 -> 8010 | N56: =M56 -> 8010 | O56: =N56 -> 8010 | P56: =O56 -> 8010 | Q56: =P56 -> 8010 | R56: =Q56 -> 8010 | ... U56: =T56 -> 8010
B57: Sub-total for Operating costs | D57: =D23 -> 0 | F57: =SUM(F51:F56) -> 2223229 | G57: =SUM(G51:G56) -> 2223229 | H57: =SUM(H51:H56) -> 2223229 | I57: =SUM(I51:I56) -> 2223229 | J57: =SUM(J51:J56) -> 2829338.5 | K57: =SUM(K51:K56) -> 2829338.5 | L57: =SUM(L51:L56) -> 2829338.5 | M57: =SUM(M51:M56) -> 2829338.5 | ... U57: =SUM(U51:U56) -> 2829338.5
D58: =D24 -> 0
B59: Fixed costs | D59: =D25 -> 0
B60: Depreciation | C60: G$s/annum | D60: =D26 -> 1 | F60: =D60*E60 -> 0 | G60: =F26*0.9 -> 18000 | H60: =G26*0.9 -> 0 | I60: =H26*0.9 -> 18000 | J60: =I26*0.9 -> 18000 | K60: =J26*0.9 -> 18000 | L60: =K26*0.9 -> 18000 | M60: =L26*0.9 -> 18000 | N60: =M26*0.9 -> 18000 | ... U60: =T26*0.9 -> 18000 | V60: =SUM(H60:U60) -> 234000
B61: Sub-total for Fixed costs | F61: =SUM(F60:F60) -> 0 | G61: =SUM(G60:G60) -> 18000 | H61: =SUM(H60:H60) -> 0 | I61: =SUM(I60:I60) -> 18000 | J61: =SUM(J60:J60) -> 18000 | K61: =SUM(K60:K60) -> 18000 | L61: =SUM(L60:L60) -> 18000 | M61: =SUM(M60:M60) -> 18000 | ... U61: =SUM(U60:U60) -> 18000
B62: TOTAL COSTS | F62: =F48+F57+F61 -> 4923229 | G62: =G48+G57+G61 -> 5241229 | H62: =H48+H57+H61 -> 2223229 | I62: =I48+I57+I61 -> 2241229 | J62: =J48+J57+J61 -> 2847338.5 | K62: =K48+K57+K61 -> 2847338.5 | L62: =L48+L57+L61 -> 2847338.5 | M62: =M48+M57+M61 -> 2847338.5 | ... U62: =U48+U57+U61 -> 2857338.5
B64: GROSS MARGIN | C64: G$/annum | G64: =G42-G48-G57 -> -5223229 | H64: =H42-H48-H57 -> -2102007.1 | I64: =I42-I48-I57 -> -1549774 | J64: =J42-J48-J57 -> 201209 | K64: =K42-K48-K57 -> 7272486.5 | L64: =L42-L48-L57 -> 3231756.5 | M64: =M42-M48-M57 -> 3231756.5 | N64: =N42-N48-N57 -> 3231756.5 | ... U64: =U42-U48-U57 -> 2615647
B65: NET MARGIN | C65: G$/annum | G65: =G64-G61 -> -5241229 | H65: =H64-H61 -> -2102007.1 | I65: =I64-I61 -> -1567774 | J65: =J64-J61 -> 183209 | K65: =K64-K61 -> 7254486.5 | L65: =L64-L61 -> 3213756.5 | M65: =M64-M61 -> 3213756.5 | N65: =N64-N61 -> 3213756.5 | ... U65: =U64-U61 -> 2597647
B66: EIRR | G66: =IRR(G65:U65) -> 0.23377797
B67: ENPV | G67: =NPV(0.1,G65:U65) -> 7829032.2

Sheet cattle breeding TF
B1: FINANCIAL
C2: Unit | D2: Quantity | E2: Price | F2: Amount | G2: Year
B3: REVENUE | G3: 1 | H3: =G3+1 -> 2 | I3: =H3+1 -> 3 | J3: =I3+1 -> 4 | K3: =J3+1 -> 5 | L3: =K3+1 -> 6 | M3: =L3+1 -> 7 | N3: =M3+1 -> 8 | O3: =N3+1 -> 9 | P3: =O3+1 -> 10 | Q3: 11 | R3: 12 | S3: 13 | T3: 14 | U3: 15
B4: Milk | C4: Liter | D4: =2100 -> 2100 | E4: 1400 | F4: =D4*E4 -> 2940000 | H4: =F4*0.3 -> 882000 | I4: =F4*0.5 -> 1470000 | J4: =F4*0.7 -> 2058000 | K4: =J4 -> 2058000 | L4: =K4 -> 2058000 | M4: =L4 -> 2058000 | N4: =M4 -> 2058000 | O4: =N4 -> 2058000 | P4: =O4 -> 2058000 | Q4: =P4 -> 2058000 | R4: =Q4 -> 2058000 | ... U4: =T4 -> 2058000
B5: - Manure | C5: Bags | D5: 50 | E5: 300 | F5: =D5*E5 -> 15000 | G5: =F5 -> 15000 | H5: =D5*E5 -> 15000 | I5: =D5*E5 -> 15000 | J5: =D5*E5 -> 15000 | K5: =J5 -> 15000 | L5: =K5 -> 15000 | M5: =L5 -> 15000 | N5: =M5 -> 15000 | O5: =N5 -> 15000 | P5: =O5 -> 15000 | Q5: =P5 -> 15000 | R5: =Q5 -> 15000 | ... U5: =T5 -> 15000
B6: Selling of animal | C6: Nos | D6: 4 | E6: 50000 | F6: =E6*D6 -> 200000 | J6: =F6 -> 200000 | K6: =J6 -> 200000 | L6: =K6 -> 200000 | M6: =L6 -> 200000 | N6: =J6 -> 200000 | O6: =K6 -> 200000 | P6: =L6 -> 200000 | Q6: =M6 -> 200000 | R6: =N6 -> 200000 | S6: =O6 -> 200000 | T6: =P6 -> 200000 | U6: =Q6 -> 200000
B7: Sub-total Revenue | F7: =SUM(F4:F6) -> 3155000 | G7: =SUM(G4:G6) -> 15000 | H7: =SUM(H4:H6) -> 897000 | I7: =SUM(I4:I6) -> 1485000 | J7: =SUM(J4:J6) -> 2273000 | K7: =SUM(K4:K6) -> 2273000 | L7: =SUM(L4:L6) -> 2273000 | M7: =SUM(M4:M6) -> 2273000 | ... U7: =SUM(U4:U6) -> 2273000
B9: COSTS
B10: Investment Costs
B11: Animal Cost | C11: lumpsum | D11: 20 | E11: 40000 | F11: =D11*E11 -> 800000 | G11: =D11*E11 -> 800000 | H11: 0 | I11: 0 | J11: 0 | P11: =K11 -> 0
B12: Other Fixed Cost | C12: lumpsum | D12: 2 | E12: 800000 | F12: =D12*E12 -> 1600000 | G12: =D12*E12 -> 1600000 | H12: 0 | I12: 0 | J12: 0 | K12: 0
B13: Sub-total Investment | F13: =SUM(F11:F12) -> 2400000 | G13: =SUM(G11:G12) -> 2400000 | H13: =SUM(H11:H12) -> 0 | I13: =SUM(I11:I12) -> 0 | J13: =SUM(J11:J12) -> 0 | K13: =SUM(K11:K12) -> 0 | L13: =SUM(L11:L12) -> 0 | M13: =SUM(M11:M12) -> 0 | ... U13: =SUM(U11:U12) -> 0
F14: =D14*E14 -> 0
B15: Operating costs | F15: =D15*E15 -> 0
B16: Fooder (Hay and Grains & Seeds) | C16: G$ | D16: 2 | E16: 10000 | F16: =D16*E16 -> 20000 | G16: =F16 -> 20000 | H16: =F16 -> 20000 | I16: =H16 -> 20000 | J16: =I16 -> 20000 | K16: =J16 -> 20000 | L16: =K16 -> 20000 | M16: =L16 -> 20000 | N16: =M16 -> 20000 | O16: =N16 -> 20000 | P16: =O16 -> 20000 | ... U16: =T16 -> 20000
B17: Wages and Salary | C17: G$ | D17: 150 | E17: 1000 | F17: =D17*E17 -> 150000 | G17: =F17 -> 150000 | H17: =F17 -> 150000 | I17: =H17 -> 150000 | J17: =I17 -> 150000 | K17: =J17 -> 150000 | L17: =K17 -> 150000 | M17: =L17 -> 150000 | N17: =M17 -> 150000 | O17: =N17 -> 150000 | P17: =O17 -> 150000 | ... U17: =T17 -> 150000
B18: Veterinary Expenses | C18: G$ | D18: 2 | E18: 10000 | F18: 3000 | G18: =F18 -> 3000 | H18: =D18*E18*1 -> 20000 | I18: =D18*E18*1 -> 20000 | J18: =D18*E18 -> 20000 | K18: =J18 -> 20000 | L18: =K18 -> 20000 | M18: =L18 -> 20000 | N18: =M18 -> 20000 | O18: =N18 -> 20000 | P18: =O18 -> 20000 | Q18: =P18 -> 20000 | R18: =Q18 -> 20000 | ... U18: =T18 -> 20000
B19: herd management | C19: G$ | D19: 2 | E19: 300000 | F19: =D19*E19 -> 600000 | G19: =F19 -> 600000 | H19: =F19 -> 600000 | I19: =H19 -> 600000 | J19: =I19 -> 600000 | K19: =J19 -> 600000 | L19: =K19 -> 600000 | M19: =L19 -> 600000 | N19: =M19 -> 600000 | O19: =N19 -> 600000 | P19: =O19 -> 600000 | ... U19: =T19 -> 600000
B20: Vaccination and medication | C20: G$ | D20: 2 | E20: 80000 | F20: =D20*E20 -> 160000 | G20: =F20 -> 160000 | H20: =G20 -> 160000 | I20: =H20 -> 160000 | J20: =I20 -> 160000 | K20: =J20 -> 160000 | L20: =K20 -> 160000 | M20: =L20 -> 160000 | N20: =M20 -> 160000 | ... U20: =T20 -> 160000
B21: coral maintenence | C21: G4 | D21: 1 | E21: 15000 | F21: =D21*E21 -> 15000 | G21: =F21 -> 15000 | H21: =F21 -> 15000 | I21: =F21 -> 15000 | J21: =F21 -> 15000 | K21: =J21 -> 15000 | L21: =K21 -> 15000 | M21: =L21 -> 15000 | N21: =M21 -> 15000 | O21: =N21 -> 15000 | P21: =O21 -> 15000 | Q21: =P21 -> 15000 | R21: =Q21 -> 15000 | ... U21: =T21 -> 15000
B22: Sub-total for Operating costs | F22: =SUM(F16:F21) -> 948000 | G22: =SUM(G16:G21) -> 948000 | H22: =SUM(H16:H21) -> 965000 | I22: =SUM(I16:I21) -> 965000 | J22: =SUM(J16:J21) -> 965000 | K22: =SUM(K16:K21) -> 965000 | L22: =SUM(L16:L21) -> 965000 | M22: =SUM(M16:M21) -> 965000 | ... U22: =SUM(U16:U21) -> 965000
B24: Fixed costs
B25: Depreciation | C25: G$/annum | D25: 1 | E25: =E12/15 -> 53333.333 | F25: =D25*E25 -> 53333.333 | G25: =F25 -> 53333.333 | H25: =D25*E25 -> 53333.333 | I25: =H25 -> 53333.333 | J25: =I25 -> 53333.333 | K25: =J25 -> 53333.333 | L25: =K25 -> 53333.333 | M25: =L25 -> 53333.333 | N25: =M25 -> 53333.333 | O25: =N25 -> 53333.333 | P25: =O25 -> 53333.333 | ... U25: =T25 -> 53333.333 | V25: =SUM(H25:U25) -> 746666.67
B26: Sub-total for Fixed costs | F26: =SUM(F25:F25) -> 53333.333 | G26: =SUM(G25:G25) -> 53333.333 | H26: =SUM(H25:H25) -> 53333.333 | I26: =SUM(I25:I25) -> 53333.333 | J26: =SUM(J25:J25) -> 53333.333 | K26: =SUM(K25:K25) -> 53333.333 | L26: =SUM(L25:L25) -> 53333.333 | M26: =SUM(M25:M25) -> 53333.333 | ... U26: =SUM(U25:U25) -> 53333.333
B27: TOTAL COSTS | F27: =F13+F22+F26 -> 3401333.3 | G27: =G13+G22+G26 -> 3401333.3 | H27: =H13+H22+H26 -> 1018333.3 | I27: =I13+I22+I26 -> 1018333.3 | J27: =J13+J22+J26 -> 1018333.3 | K27: =K13+K22+K26 -> 1018333.3 | L27: =L13+L22+L26 -> 1018333.3 | M27: =M13+M22+M26 -> 1018333.3 | ... U27: =U13+U22+U26 -> 1018333.3
B29: GROSS MARGIN | C29: G$/annum | G29: =G7-G13-G22 -> -3333000 | H29: =H7-H13-H22 -> -68000 | I29: =I7-I13-I22 -> 520000 | J29: =J7-J13-J22 -> 1308000 | K29: =K7-K13-K22 -> 1308000 | L29: =L7-L13-L22 -> 1308000 | M29: =M7-M13-M22 -> 1308000 | N29: =N7-N13-N22 -> 1308000 | ... U29: =U7-U13-U22 -> 1308000
B30: NET MARGIN BEFORE PROFIT TAX | C30: G$/annum | G30: =G29-G26 -> -3386333.3 | H30: =(H29-H26) -> -121333.33 | I30: =(I29-I26) -> 466666.67 | J30: =J29-J26 -> 1254666.7 | K30: =K29-K26 -> 1254666.7 | L30: =L29-L26 -> 1254666.7 | M30: =M29-M26 -> 1254666.7 | N30: =N29-N26 -> 1254666.7 | O30: =O29-O26 -> 1254666.7 | P30: =P29-P26 -> 1254666.7 | Q30: =Q29-Q26 -> 1254666.7 | ... U30: =U29-U26 -> 1254666.7
B31: FIRR | G31: =IRR(G30:U30) -> 0.23765602
B32: FNPV | G32: =NPV(0.1,G30:U30) -> 3594777.4
B34: ECONOMIC
C35: Unit | D35: Quantity | E35: Price | F35: Amount | G35: Year
B36: REVENUE | G36: 1 | H36: =G36+1 -> 2 | I36: =H36+1 -> 3 | J36: =I36+1 -> 4 | K36: =J36+1 -> 5 | L36: =K36+1 -> 6 | M36: =L36+1 -> 7 | N36: =M36+1 -> 8 | O36: =N36+1 -> 9 | P36: =O36+1 -> 10 | Q36: 11 | R36: 12 | S36: 13 | T36: 14 | U36: 15
B37: Milk | C37: Liter | D37: =D4 -> 2100 | E37: =E4*0.9 -> 1260 | F37: =D37*E37 -> 2646000 | H37: =F37 -> 2646000 | I37: =F37 -> 2646000 | J37: =F37 -> 2646000 | K37: =J37 -> 2646000 | L37: =K37 -> 2646000 | M37: =L37 -> 2646000 | N37: =M37 -> 2646000 | O37: =N37 -> 2646000 | P37: =O37 -> 2646000 | Q37: =P37 -> 2646000 | R37: =Q37 -> 2646000 | ... U37: =T37 -> 2646000
B38: - Manure | C38: Bags | D38: =D5 -> 50 | E38: =E5*0.9 -> 270 | F38: =D38*E38 -> 13500 | G38: =F38 -> 13500 | H38: =D38*E38 -> 13500 | I38: =D38*E38 -> 13500 | J38: =D38*E38 -> 13500 | K38: =J38 -> 13500 | L38: =K38 -> 13500 | M38: =L38 -> 13500 | N38: =M38 -> 13500 | O38: =N38 -> 13500 | P38: =O38 -> 13500 | Q38: =P38 -> 13500 | R38: =Q38 -> 13500 | ... U38: =T38 -> 13500
B39: Selling of animal | C39: Nos. | K39: =K6*0.9 -> 180000 | P39: =K39 -> 180000 | U39: =P39 -> 180000
B40: Sub-total Revenue | D40: =D7 -> 0 | E40: =E7*0.9 -> 0 | F40: =SUM(F37:F39) -> 2659500 | G40: =SUM(G37:G39) -> 13500 | H40: =SUM(H37:H39) -> 2659500 | I40: =SUM(I37:I39) -> 2659500 | J40: =SUM(J37:J39) -> 2659500 | K40: =SUM(K37:K39) -> 2839500 | L40: =SUM(L37:L39) -> 2659500 | M40: =SUM(M37:M39) -> 2659500 | ... U40: =SUM(U37:U39) -> 2839500
D41: =D8 -> 0 | E41: =E8*0.9 -> 0
B42: COSTS | D42: =D9 -> 0 | E42: =E9*0.9 -> 0
B43: Investment Costs | D43: =D10 -> 0 | E43: =E10*0.9 -> 0
B44: Animal Cost | C44: Nos. | D44: =D11 -> 20 | E44: =E11*0.9 -> 36000 | F44: =D44*E44 -> 720000 | G44: =D44*E44 -> 720000 | H44: 0 | I44: 0 | J44: 0 | P44: =K44 -> 0
B45: Other Fixed Cost | C45: lumpsum | D45: =D12 -> 2 | E45: =E12*0.9 -> 720000 | F45: =D45*E45 -> 1440000 | G45: =D45*E45 -> 1440000 | H45: 0 | I45: 0 | J45: 0 | K45: 0
B46: Sub-total Investment | D46: =D13 -> 0 | E46: =E13*0.9 -> 0 | F46: =SUM(F44:F45) -> 2160000 | G46: =SUM(G44:G45) -> 2160000 | H46: =SUM(H44:H45) -> 0 | I46: =SUM(I44:I45) -> 0 | J46: =SUM(J44:J45) -> 0 | K46: =SUM(K44:K45) -> 0 | L46: =SUM(L44:L45) -> 0 | M46: =SUM(M44:M45) -> 0 | ... U46: =SUM(U44:U45) -> 0
D47: =D14 -> 0 | E47: =E14*0.9 -> 0 | F47: =D47*E47 -> 0
B48: Operating costs | D48: =D15 -> 0 | E48: =E15*0.9 -> 0 | F48: =D48*E48 -> 0
B49: Fooder (Hay and Grains & Seeds) | D49: 2 | E49: =E16*0.9 -> 9000 | F49: =D49*E49 -> 18000 | G49: =F49 -> 18000 | H49: =G49 -> 18000 | I49: =H49 -> 18000 | J49: =I49 -> 18000 | K49: =J49 -> 18000 | L49: =K49 -> 18000 | M49: =L49 -> 18000 | N49: =M49 -> 18000 | ... U49: =T49 -> 18000
B50: Wages and Salary | C50: G$ | D50: 150 | E50: =E17 -> 1000 | F50: =D50*E50 -> 150000 | G50: =F50 -> 150000 | H50: =D50*E50*1 -> 150000 | I50: =D50*E50*1 -> 150000 | J50: =D50*E50 -> 150000 | K50: =J50 -> 150000 | L50: =K50 -> 150000 | M50: =L50 -> 150000 | N50: =M50 -> 150000 | O50: =N50 -> 150000 | P50: =O50 -> 150000 | Q50: =P50 -> 150000 | R50: =Q50 -> 150000 | ... U50: =T50 -> 150000
B51: Veterinary Expenses | C51: G$ | D51: 2 | E51: =E18*0.9 -> 9000 | F51: =D51*E51 -> 18000 | G51: =F51*0.5 -> 9000 | H51: =F51 -> 18000 | I51: =H51 -> 18000 | J51: =I51 -> 18000 | K51: =J51 -> 18000 | L51: =K51 -> 18000 | M51: =L51 -> 18000 | N51: =M51 -> 18000 | O51: =N51 -> 18000 | P51: =O51 -> 18000 | ... U51: =T51 -> 18000
B52: herd mangement | C52: G$ | D52: 2 | E52: =E19*0.9 -> 270000 | F52: =D52*E52 -> 540000 | G52: =F52 -> 540000 | H52: =F52 -> 540000 | I52: =F52 -> 540000 | J52: =F52 -> 540000 | K52: =J52 -> 540000 | L52: =K52 -> 540000 | M52: =L52 -> 540000 | N52: =M52 -> 540000 | O52: =N52 -> 540000 | P52: =O52 -> 540000 | Q52: =P52 -> 540000 | R52: =Q52 -> 540000 | ... U52: =T52 -> 540000
B53: Vaccination and medication | C53: G$ | D53: 2 | E53: =E20*0.9 -> 72000 | F53: =D53*E53 -> 144000 | G53: =F53 -> 144000 | H53: =D53*E53*1 -> 144000 | I53: =D53*E53*1 -> 144000 | J53: =D53*E53 -> 144000 | K53: =J53 -> 144000 | L53: =K53 -> 144000 | M53: =L53 -> 144000 | N53: =M53 -> 144000 | O53: =N53 -> 144000 | P53: =O53 -> 144000 | Q53: =P53 -> 144000 | R53: =Q53 -> 144000 | ... U53: =T53 -> 144000
B54: coral maintenance | C54: G$ | D54: 1 | E54: =E21*0.9 -> 13500 | F54: =D54*E54 -> 13500 | G54: =F54 -> 13500 | H54: =D54*E54*1 -> 13500 | I54: =D54*E54*1 -> 13500 | J54: =D54*E54 -> 13500 | K54: =J54 -> 13500 | L54: =K54 -> 13500 | M54: =L54 -> 13500 | N54: =M54 -> 13500 | O54: =N54 -> 13500 | P54: =O54 -> 13500 | Q54: =P54 -> 13500 | R54: =Q54 -> 13500 | ... U54: =T54 -> 13500
B55: Sub-total for Operating costs | D55: =D22 -> 0 | F55: =SUM(F49:F54) -> 883500 | G55: =SUM(G49:G54) -> 874500 | H55: =SUM(H49:H54) -> 883500 | I55: =SUM(I49:I54) -> 883500 | J55: =SUM(J49:J54) -> 883500 | K55: =SUM(K49:K54) -> 883500 | L55: =SUM(L49:L54) -> 883500 | M55: =SUM(M49:M54) -> 883500 | ... U55: =SUM(U49:U54) -> 883500
D56: =D23 -> 0
B57: Fixed costs | D57: =D24 -> 0
B58: Depreciation (Shed) | C58: G$/annum | D58: =D25 -> 1 | F58: =D58*E58 -> 0 | G58: 0 | H58: =D58*E58 -> 0 | I58: =H58 -> 0 | J58: =I58 -> 0 | K58: =J58 -> 0 | L58: =K58 -> 0 | M58: =L58 -> 0 | N58: =M58 -> 0 | O58: =N58 -> 0 | P58: =O58 -> 0 | ... U58: =T58 -> 0 | V58: =SUM(H58:U58) -> 0
B59: Sub-total for Fixed costs | F59: =SUM(F58:F58) -> 0 | G59: =SUM(G58:G58) -> 0 | H59: =SUM(H58:H58) -> 0 | I59: =SUM(I58:I58) -> 0 | J59: =SUM(J58:J58) -> 0 | K59: =SUM(K58:K58) -> 0 | L59: =SUM(L58:L58) -> 0 | M59: =SUM(M58:M58) -> 0 | ... U59: =SUM(U58:U58) -> 0
B60: TOTAL COSTS | F60: =F46+F55+F59 -> 3043500 | G60: =G46+G55+G59 -> 3034500 | H60: =H46+H55+H59 -> 883500 | I60: =I46+I55+I59 -> 883500 | J60: =J46+J55+J59 -> 883500 | K60: =K46+K55+K59 -> 883500 | L60: =L46+L55+L59 -> 883500 | M60: =M46+M55+M59 -> 883500 | ... U60: =U46+U55+U59 -> 883500
B62: GROSS MARGIN | C62: G$/annum | G62: =G40-G46-G55 -> -3021000 | H62: =H40-H46-H55 -> 1776000 | I62: =I40-I46-I55 -> 1776000 | J62: =J40-J46-J55 -> 1776000 | K62: =K40-K46-K55 -> 1956000 | L62: =L40-L46-L55 -> 1776000 | M62: =M40-M46-M55 -> 1776000 | N62: =N40-N46-N55 -> 1776000 | ... U62: =U40-U46-U55 -> 1956000
B63: NET MARGIN | C63: G$/annum | G63: =G62-G59 -> -3021000 | H63: =-(H62-H59) -> -1776000 | I63: =-(I62-I59) -> -1776000 | J63: =J62-J59 -> 1776000 | K63: =K62-K59 -> 1956000 | L63: =L62-L59 -> 1776000 | M63: =M62-M59 -> 1776000 | N63: =N62-N59 -> 1776000 | O63: =O62-O59 -> 1776000 | P63: =P62-P59 -> 1956000 | Q63: =Q62-Q59 -> 1776000 | ... U63: =U62-U59 -> 1956000
B64: EIRR | G64: =IRR(G63:U63) -> 0.19550723
B65: ENPV | G65: =NPV(0.1,G63:U63) -> 3767534.9

Sheet Poutry breeding TF
B1: FINANCIAL
C2: Unit | D2: Quantity | E2: Price | F2: Amount | G2: Year
B3: REVENUE | D3: With Project | G3: 1 | H3: =G3+1 -> 2 | I3: =H3+1 -> 3 | J3: =I3+1 -> 4 | K3: =J3+1 -> 5 | L3: =K3+1 -> 6 | M3: =L3+1 -> 7 | N3: =M3+1 -> 8 | O3: =N3+1 -> 9 | P3: =O3+1 -> 10 | Q3: 11 | R3: 12 | S3: 13 | T3: 14 | U3: 15
B4: Units sold anually- no of chickens | C4: kg | D4: 1000 | E4: 3000 | H4: =I4*0.3 -> 450000 | I4: =J4*0.5 -> 1500000 | J4: =D4*E4 -> 3000000 | K4: =J4*1.2 -> 3600000 | L4: =K4*1.2 -> 4320000 | M4: =L4*1.2 -> 5184000 | N4: =M4*1.2 -> 6220800 | O4: =N4*1.2 -> 7464960 | P4: =O4*1.2 -> 8957952 | Q4: =P4*1.2 -> 10749542 | R4: =Q4*1.2 -> 12899451 | ... U4: =T4*1.2 -> 22290251
B5: Units sold anually- no of eggs | C5: number | D5: 1800 | E5: 35 | F5: =D5*E5 -> 63000 | G5: =F5 -> 63000 | H5: =F5*0.3 -> 18900 | I5: =H5*0.5 -> 9450 | J5: =I5 -> 9450 | K5: =J5 -> 9450 | L5: =K5 -> 9450 | M5: =L5 -> 9450 | N5: =M5 -> 9450 | O5: =N5 -> 9450 | P5: =O5 -> 9450 | Q5: =P5 -> 9450 | ... U5: =T5 -> 9450
B6: Sub-total Revenue | F6: =SUM(F4:F5) -> 63000 | G6: =SUM(G4:G5) -> 63000 | H6: =SUM(H4:H5) -> 468900 | I6: =SUM(I4:I5) -> 1509450 | J6: =SUM(J4:J5) -> 3009450 | K6: =SUM(K4:K5) -> 3609450 | L6: =SUM(L4:L5) -> 4329450 | M6: =SUM(M4:M5) -> 5193450 | ... U6: =SUM(U4:U5) -> 22299701
B8: COSTS
B9: Investment Costs
B10: Cost of Chick | C10: Nos. | D10: 500 | E10: 300 | F10: =D10*E10 -> 150000 | G10: =F10 -> 150000 | H10: =G10 -> 150000 | I10: 0 | J10: 0 | K10: 0
B11: Other Fixed Assets | C11: lumpsum | D11: 1 | E11: 60000 | F11: =D11*E11 -> 60000 | G11: =F11 -> 60000 | H11: =G11 -> 60000 | I11: 0 | J11: 0 | K11: 0
B12: Sub-total Investment | F12: 0 | G12: 0 | H12: =SUM(H10:H11) -> 210000 | I12: =SUM(I10:I11) -> 0 | J12: =SUM(J10:J11) -> 0 | K12: =SUM(K10:K11) -> 0
F13: =D13*E13 -> 0
B14: Operating costs | F14: =D14*E14 -> 0
B15: Feeding Cost | C15: G$ | D15: 10710 | E15: 1 | F15: =D15*E15 -> 10710 | G15: =F15 -> 10710 | H15: =F15 -> 10710 | I15: =H15 -> 10710 | J15: =I15 -> 10710 | K15: =J15 -> 10710 | L15: =K15 -> 10710 | M15: =L15 -> 10710 | N15: =M15 -> 10710 | O15: =N15 -> 10710 | P15: =O15 -> 10710 | ... T15: =S15 -> 10710 | U15: =T15*0.5 -> 5355
B16: Wages and Salary | C16: G$ | D16: 2000 | E16: 900 | F16: =D16*E16 -> 1800000 | G16: =F16 -> 1800000 | H16: =F16 -> 1800000 | I16: =H16 -> 1800000 | J16: =H16 -> 1800000 | K16: =J16 -> 1800000 | L16: =J16 -> 1800000 | M16: =L16 -> 1800000 | N16: =L16 -> 1800000 | O16: =N16 -> 1800000 | P16: =N16 -> 1800000 | Q16: =P16 -> 1800000 | R16: =P16 -> 1800000 | S16: =R16 -> 1800000 | T16: =R16 -> 1800000 | U16: =T16 -> 1800000
B17: Veterinary Expenses | C17: G$ | F17: 1000000 | G17: =F17 -> 1000000 | H17: =F17 -> 1000000 | I17: =H17 -> 1000000 | J17: =I17 -> 1000000 | K17: =J17 -> 1000000 | L17: =K17 -> 1000000 | M17: =L17 -> 1000000 | N17: =M17 -> 1000000 | O17: =N17 -> 1000000 | P17: =O17 -> 1000000 | ... U17: =T17 -> 1000000
B18: Balanced diets vitamins | C18: G$ | F18: 2080000 | G18: =F18 -> 2080000 | H18: =G18 -> 2080000 | I18: =H18 -> 2080000 | J18: =I18 -> 2080000 | K18: =J18 -> 2080000 | L18: =K18 -> 2080000 | M18: =L18 -> 2080000 | N18: =M18 -> 2080000 | ... U18: =T18 -> 2080000
B19: Mis. Expense | C19: G$ | F19: 550000 | G19: =F19 -> 550000 | H19: =F19 -> 550000 | I19: =H19 -> 550000 | J19: =I19 -> 550000 | K19: =J19 -> 550000 | L19: =K19 -> 550000 | M19: =L19 -> 550000 | N19: =M19 -> 550000 | O19: =N19 -> 550000 | P19: =O19 -> 550000 | ... U19: =T19 -> 550000
B20: Sub-total for Operating costs | F20: =SUM(F15:F19) -> 5440710 | G20: =SUM(G15:G19) -> 5440710 | H20: =SUM(H15:H19) -> 5440710 | I20: =SUM(I15:I19) -> 5440710 | J20: =SUM(J15:J19) -> 5440710 | K20: =SUM(K15:K19) -> 5440710 | L20: =SUM(L15:L19) -> 5440710 | M20: =SUM(M15:M19) -> 5440710 | ... U20: =SUM(U15:U19) -> 5435355
B22: Fixed costs
B23: Depreciation | C23: G$/annum | D23: 1 | E23: =E11/15 -> 4000 | F23: =D23*E23 -> 4000 | G23: =F23 -> 4000 | H23: =D23*E23 -> 4000 | I23: =H23 -> 4000 | J23: =I23 -> 4000 | K23: =J23 -> 4000 | L23: =K23 -> 4000 | M23: =L23 -> 4000 | N23: =M23 -> 4000 | O23: =N23 -> 4000 | P23: =O23 -> 4000 | ... U23: =T23 -> 4000 | V23: =SUM(H23:U23) -> 56000
B24: Sub-total for Fixed costs | F24: =F15 -> 10710 | G24: =G15 -> 10710 | H24: =H15 -> 10710 | I24: =I15 -> 10710 | J24: =J15 -> 10710 | K24: =K15 -> 10710 | L24: =L15 -> 10710 | M24: =M15 -> 10710 | ... U24: =U15 -> 5355
B25: TOTAL COSTS | F25: =F12+F20+F24 -> 5451420 | G25: =G12+G20+G24 -> 5451420 | H25: =H12+H20+H24 -> 5661420 | I25: =I12+I20+I24 -> 5451420 | J25: =J12+J20+J24 -> 5451420 | K25: =K12+K20+K24 -> 5451420 | L25: =L12+L20+L24 -> 5451420 | M25: =M12+M20+M24 -> 5451420 | ... U25: =U12+U20+U24 -> 5440710
B27: GROSS MARGIN | C27: G$/annum | I27: =-(I6-I12-I20) -> 3931260 | J27: =J6-J12-J20 -> -2431260 | K27: =K6-K12-K20 -> -1831260 | L27: =L6-L12-L20 -> -1111260 | M27: =M6-M12-M20 -> -247260 | N27: =N6-N12-N20 -> 789540 | O27: =O6-O12-O20 -> 2033700 | P27: =P6-P12-P20 -> 3526692 | Q27: =Q6-Q12-Q20 -> 5318282.4 | ... U27: =U6-U12-U20 -> 16864346
B28: NET MARGIN | C28: G$/annum | G28: =H28 -> -3920550 | H28: =I28 -> -3920550 | I28: =-(I27-I24) -> -3920550 | J28: =I28 -> -3920550 | K28: =K27-K24 -> -1841970 | L28: =L27-L24 -> -1121970 | M28: =(M27-M24) -> -257970 | N28: =N27-N24 -> 778830 | O28: =O27-O24 -> 2022990 | P28: =P27-P24 -> 3515982 | Q28: =Q27-Q24 -> 5307572.4 | R28: =R27-R24 -> 7457480.9 | S28: =S27-S24 -> 10037371 | T28: =T27-T24 -> 13133239 | U28: =U27-U24 -> 16858991
B29: FIRR | G29: =IRR(I28:U28) -> 0.21018031
B30: FNPV | G30: =NPV(0.1,G28:U28) -> 2878026.5
B41: ECONOMIC
C42: Unit | D42: Quantity | E42: Price | F42: Amount | G42: Year
B43: REVENUE | D43: With Project | G43: 1 | H43: =G43+1 -> 2 | I43: =H43+1 -> 3 | J43: =I43+1 -> 4 | K43: =J43+1 -> 5 | L43: =K43+1 -> 6 | M43: =L43+1 -> 7 | N43: =M43+1 -> 8 | O43: =N43+1 -> 9 | P43: =O43+1 -> 10 | Q43: 11 | R43: 12 | S43: 13 | T43: 14 | U43: 15
B44: Units sold anually- no of chickens | C44: Nos. | D44: =D4 -> 1000 | E44: =E4*0.9 -> 2700 | G44: 0 | H44: =F44 -> 0 | I44: =D44*E44 -> 2700000 | J44: =I44 -> 2700000 | K44: =J44 -> 2700000 | L44: =K44 -> 2700000 | M44: =L44 -> 2700000 | N44: =M44 -> 2700000 | O44: =N44 -> 2700000 | P44: =O44 -> 2700000 | Q44: =P44 -> 2700000 | ... U44: =T44 -> 2700000
B45: Egg Units sold- No of eggs | C45: Eggs/annum | D45: =D5 -> 1800 | E45: =E5*0.9 -> 31.5 | G45: =F45 -> 0 | H45: =F45 -> 0 | I45: =E45*D45 -> 56700 | J45: =I45 -> 56700 | K45: =J45 -> 56700 | L45: =K45 -> 56700 | M45: =L45 -> 56700 | N45: =M45 -> 56700 | O45: =N45 -> 56700 | P45: =O45 -> 56700 | Q45: =P45 -> 56700 | ... U45: =T45 -> 56700
B46: Sub-total Revenue | F46: =SUM(F44:F45) -> 0 | G46: =SUM(G44:G45) -> 0 | H46: =SUM(H44:H45) -> 0 | I46: =SUM(I44:I45) -> 2756700 | J46: =SUM(J44:J45) -> 2756700 | K46: =SUM(K44:K45) -> 2756700 | L46: =SUM(L44:L45) -> 2756700 | M46: =SUM(M44:M45) -> 2756700 | ... U46: =SUM(U44:U45) -> 2756700
B48: COSTS
B49: Investment Costs
B50: Cost of Chick | C50: Nos. | D50: =D10 -> 500 | E50: =E10*0.9 -> 270 | F50: =D50*E50 -> 135000 | G50: =D50*E50 -> 135000 | H50: =G50 -> 135000 | I50: 0 | J50: 0 | K50: 0
B51: Other Fixed Assets | C51: lumpsum | D51: 1 | E51: =E11*0.9 -> 54000 | F51: =D51*E51 -> 54000 | G51: =D51*E51 -> 54000 | H51: =G51 -> 54000 | I51: 0 | J51: 0 | K51: 0
B52: Sub-total Investment | F52: =SUM(F50:F51) -> 189000 | G52: =SUM(G50:G51) -> 189000 | H52: =SUM(H50:H51) -> 189000 | I52: =SUM(I50:I51) -> 0 | J52: =SUM(J50:J51) -> 0 | K52: =SUM(K50:K51) -> 0
F53: =D53*E53 -> 0
B54: Operating costs | F54: =D54*E54 -> 0
B55: Feeding Cost | C55: G$ | D55: 10700 | E55: =E15 -> 1 | F55: =D55*E55 -> 10700 | G55: =F55 -> 10700 | H55: =F55 -> 10700 | I55: =H55 -> 10700 | J55: =I55 -> 10700 | K55: =J55 -> 10700 | L55: =K55 -> 10700 | M55: =L55 -> 10700 | N55: =M55 -> 10700 | O55: =N55 -> 10700 | P55: =O55 -> 10700 | ... T55: =S55 -> 10700 | U55: =T55*0.5 -> 5350
B56: Wages and Salary | C56: G$ | D56: =D16*0.9 -> 1800 | E56: =E16 -> 900 | F56: =D56*E56 -> 1620000 | G56: =F56 -> 1620000 | H56: =F56 -> 1620000 | I56: =H56 -> 1620000 | J56: =H56 -> 1620000 | K56: =J56 -> 1620000 | L56: =J56 -> 1620000 | M56: =L56 -> 1620000 | N56: =L56 -> 1620000 | O56: =N56 -> 1620000 | P56: =N56 -> 1620000 | Q56: =P56 -> 1620000 | R56: =P56 -> 1620000 | S56: =R56 -> 1620000 | T56: =R56 -> 1620000 | U56: =T56 -> 1620000
B57: Veterinary Expenses | C57: G$ | E57: =E17*0.9 -> 0 | F57: =F17*0.9 -> 900000 | G57: =G17*0.9 -> 900000 | H57: =F57 -> 900000 | I57: =H57 -> 900000 | J57: =I57 -> 900000 | K57: =J57 -> 900000 | L57: =K57 -> 900000 | M57: =L57 -> 900000 | N57: =M57 -> 900000 | O57: =N57 -> 900000 | P57: =O57 -> 900000 | ... U57: =T57 -> 900000
B58: Balanced diet/vitamins | C58: G$ | F58: =F18*0.9 -> 1872000 | G58: =F58 -> 1872000 | H58: =G58 -> 1872000 | I58: =H58 -> 1872000 | J58: =I58 -> 1872000 | K58: =J58 -> 1872000 | L58: =K58 -> 1872000 | M58: =L58 -> 1872000 | N58: =M58 -> 1872000 | ... U58: =T58 -> 1872000
B59: Mis. Expense | C59: G$ | D59: 1 | E59: =E19*0.9 -> 0 | F59: =F19*0.9 -> 495000 | G59: =G19*0.9 -> 495000 | H59: =G59 -> 495000 | I59: =H59 -> 495000 | J59: =I59 -> 495000 | K59: =J59 -> 495000 | L59: =K59 -> 495000 | M59: =L59 -> 495000 | N59: =M59 -> 495000 | O59: =N59 -> 495000 | ... U59: =T59 -> 495000
B60: Sub-total for Operating costs | F60: =SUM(F55:F59) -> 4897700 | G60: =SUM(G55:G59) -> 4897700 | H60: =SUM(H55:H59) -> 4897700 | I60: =SUM(I55:I59) -> 4897700 | J60: =SUM(J55:J59) -> 4897700 | K60: =SUM(K55:K59) -> 4897700 | L60: =SUM(L55:L59) -> 4897700 | M60: =SUM(M55:M59) -> 4897700 | ... U60: =SUM(U55:U59) -> 4892350
B62: Fixed costs
B63: Depreciation | F63: =E23 -> 4000 | G63: =F63 -> 4000 | H63: =G63 -> 4000 | I63: =H63 -> 4000 | J63: =I63 -> 4000 | K63: =J63 -> 4000 | L63: =K63 -> 4000 | M63: =L63 -> 4000 | N63: =M63 -> 4000 | ... U63: =T63 -> 4000 | V63: =SUM(H63:U63) -> 56000
B64: Sub-total for Fixed costs | F64: =F24*0.9 -> 9639 | G64: =F64 -> 9639 | H64: =G64 -> 9639 | I64: =H64 -> 9639 | J64: =I64 -> 9639 | K64: =J64 -> 9639 | L64: =K64 -> 9639 | M64: =L64 -> 9639 | N64: =M64 -> 9639 | ... U64: =T64 -> 9639
B65: TOTAL COSTS | F65: =F52+F60+F64 -> 5096339 | G65: =G52+G60+G64 -> 5096339 | H65: =H52+H60+H64 -> 5096339 | I65: =I52+I60+I64 -> 4907339 | J65: =J52+J60+J64 -> 4907339 | K65: =K52+K60+K64 -> 4907339 | L65: =L52+L60+L64 -> 4907339 | M65: =M52+M60+M64 -> 4907339 | ... U65: =U52+U60+U64 -> 4901989
B67: GROSS MARGIN | C67: G$/annum | I67: =I46-I52-I60 -> -2141000 | J67: =J46-J52-J60 -> -2141000 | K67: =K46-K52-K60 -> -2141000 | L67: =L46-L52-L60 -> -2141000 | M67: =M46-M52-M60 -> -2141000 | N67: =N46-N52-N60 -> -2141000 | O67: =O46-O52-O60 -> -2141000 | P67: =P46-P52-P60 -> -2141000 | ... U67: =U46-U52-U60 -> -2135650
B68: NET MARGIN | C68: G$/annum | G68: =H68 -> -2150639 | H68: =I68 -> -2150639 | I68: =I67-I64 -> -2150639 | J68: =-(J67-J64) -> 2150639 | K68: =K67-K64 -> -2150639 | L68: =-(L67-L64) -> 2150639 | M68: =-(M67-M64) -> 2150639 | N68: =-(N67-N64) -> 2150639 | O68: =N68 -> 2150639 | P68: =O68 -> 2150639 | Q68: =P68 -> 2150639 | R68: =Q68 -> 2150639 | S68: =R68 -> 2150639 | T68: =S68 -> 2150639 | U68: =T68 -> 2150639
B69: EIRR | G69: =IRR(G68:U68) -> 0.16945185
B70: ENPV | G70: =NPV(0.1,G68:U68) -> 2990534.2

Sheet Sensitivity analysis
A1: Financial
A2: Net Margins | B2: Particulars | C2: Year 1 | D2: Year 2 | E2: Year 3 | F2: Year 4 | G2: Year 5 | H2: Year 6 | I2: Year 7 | J2: Year 8 | K2: Year 9 | L2: Year 10 | M2: Year 11 | N2: Year 12 | O2: Year 13 | P2: Year 14 | Q2: Year 15
B3: Peanut TF | C3: ='Peanut TF'!G30 -> -671500 | D3: ='Peanut TF'!H30 -> -136833.33 | E3: ='Peanut TF'!I30 -> -84833.333 | F3: ='Peanut TF'!J30 -> 1615166.7 | G3: ='Peanut TF'!K30 -> 55166.667 | H3: ='Peanut TF'!L30 -> 45166.667 | I3: ='Peanut TF'!M30 -> 55166.667 | J3: ='Peanut TF'!N30 -> 55166.667 | ... Q3: ='Peanut TF'!U30 -> 45166.667
B4: Cassava TF | C4: ='Cassava TF'!G29 -> -2644166.7 | D4: ='Cassava TF'!H29 -> -3564166.7 | E4: ='Cassava TF'!I29 -> 1595833.3 | F4: ='Cassava TF'!J29 -> 1595833.3 | G4: ='Cassava TF'!K29 -> 1595833.3 | H4: ='Cassava TF'!L29 -> 1595833.3 | I4: ='Cassava TF'!M29 -> 1595833.3 | J4: ='Cassava TF'!N29 -> 1595833.3 | ... Q4: ='Cassava TF'!U29 -> 1595833.3
B5: Cassava processing TF | C5: ='Cassava processing TF'!G31 -> -6470810 | D5: ='Cassava processing TF'!H31 -> -6356119 | E5: ='Cassava processing TF'!I31 -> -2817355 | F5: ='Cassava processing TF'!J31 -> -407081.25 | G5: ='Cassava processing TF'!K31 -> 7449893.8 | H5: ='Cassava processing TF'!L31 -> 2950193.8 | I5: ='Cassava processing TF'!M31 -> 2960193.8 | J5: ='Cassava processing TF'!N31 -> 2960193.8 | ... Q5: ='Cassava processing TF'!U31 -> 2950193.8
B6: cattle breeding TF | C6: ='cattle breeding TF'!G30 -> -3386333.3 | D6: ='cattle breeding TF'!H30 -> -121333.33 | E6: ='cattle breeding TF'!I30 -> 466666.67 | F6: ='cattle breeding TF'!J30 -> 1254666.7 | G6: ='cattle breeding TF'!K30 -> 1254666.7 | H6: ='cattle breeding TF'!L30 -> 1254666.7 | I6: ='cattle breeding TF'!M30 -> 1254666.7 | J6: ='cattle breeding TF'!N30 -> 1254666.7 | ... Q6: ='cattle breeding TF'!U30 -> 1254666.7 | R6: ='External Shading (Awnings, Over'!V30 -> 0 | S6: ='External Shading (Awnings, Over'!W30 -> 0
B7: poultry breeding TF | C7: ='Poutry breeding TF'!G28 -> -3920550 | D7: ='Poutry breeding TF'!H28 -> -3920550 | E7: ='Poutry breeding TF'!I28 -> -3920550 | F7: ='Poutry breeding TF'!J28 -> -3920550 | G7: ='Poutry breeding TF'!K28 -> -1841970 | H7: ='Poutry breeding TF'!L28 -> -1121970 | I7: ='Poutry breeding TF'!M28 -> -257970 | J7: ='Poutry breeding TF'!N28 -> 778830 | ... Q7: ='Poutry breeding TF'!U28 -> 16858991
B8: Guest house TF | C8: =GH!D17 -> -400000 | D8: =GH!E17 -> -450000 | E8: =GH!F17 -> -450000 | F8: =GH!G17 -> -450000 | G8: =GH!H17 -> 420000 | H8: =GH!I17 -> 420000 | I8: =GH!J17 -> 420000 | J8: =GH!K17 -> 420000 | ... Q8: =GH!R17 -> 420000
B9: Total | C9: =SUM(C3:C8) -> -17493360 | D9: =SUM(D3:D8) -> -14549002 | E9: =SUM(E3:E8) -> -5210238.3 | F9: =SUM(F3:F8) -> -311964.58 | G9: =SUM(G3:G8) -> 8933590.4 | H9: =SUM(H3:H8) -> 5143890.4 | I9: =SUM(I3:I8) -> 6027890.4 | J9: =SUM(J3:J8) -> 7064690.4 | ... Q9: =SUM(Q3:Q8) -> 23124852
B10: Total investment | C10: =Summary!B11 -> 28836177 | T10: Total investment | V10: 10 | W10: Million
B11: Total component cost | C11: =V13 -> 2299000000 | U11: US$ | V11: =10000000 -> 10000000
B12: NET margins for additional financing | C12: ='Additional financing total'!C13 -> -1.3311678e+09 | D12: ='Additional financing total'!D13 -> 3.4238966e+08 | E12: ='Additional financing total'!E13 -> 1.8293718e+08 | F12: ='Additional financing total'!F13 -> -81488192 | G12: ='Additional financing total'!G13 -> 1.1964358e+08 | H12: ='Additional financing total'!H13 -> 1.658848e+08 | I12: ='Additional financing total'!I13 -> 2.2488222e+08 | J12: ='Additional financing total'!J13 -> 2.9376569e+08 | ... Q12: ='Additional financing total'!Q13 -> 1.3606558e+09
B13: Net margins for the total financing | C13: =C9*($C$11/$C$10) -> -1.3946799e+09 | D13: =-(D9*($C$11/$C$10)) -> 1.1599373e+09 | E13: =E9*($C$11/$C$10) -> -4.1539272e+08 | F13: =(F9*($C$11/$C$10)) -> -24871764 | G13: =-(G9*($C$11/$C$10)) -> -7.1224159e+08 | H13: =-(H9*($C$11/$C$10)) -> -4.1010305e+08 | I13: =I9*($C$11/$C$10) -> 4.8058105e+08 | J13: =J9*($C$11/$C$10) -> 5.6324122e+08 | K13: =K9*($C$11/$C$10) -> 6.6083889e+08 | L13: =L9*($C$11/$C$10) -> 7.8146406e+08 | M13: =M9*($C$11/$C$10) -> 9.2430083e+08 | N13: =N9*($C$11/$C$10) -> 1.0941104e+09 | O13: =O9*($C$11/$C$10) -> 1.3013899e+09 | P13: =P9*($C$11/$C$10) -> 1.4684856e+09 | Q13: =Q9*($C$11/$C$10) -> 1.8436575e+09 | U13: G$ | V13: 2299000000
B14: FIRR(TF) | C14: =IRR(C13:Q13) -> 0.21194584
B15: FNPV(TF) | C15: =NPV(0.1,C13:Q13) -> 1.6564373e+09
C18: =V13 -> 2299000000
B19: Net Margins (total+additional) | C19: =C12+C13 -> -2.7258477e+09 | D19: =(D12+D13) -> 1.5023269e+09 | E19: =-(E12+E13) -> 2.3245554e+08 | F19: =F12+F13 -> -1.0635996e+08 | G19: =G12+G13 -> -5.9259801e+08 | H19: =H12+H13 -> -2.4421826e+08 | I19: =I12+I13 -> 7.0546327e+08 | J19: =J12+J13 -> 8.5700691e+08 | K19: =K12+K13 -> 1.0356702e+09 | L19: =L12+L13 -> 1.2570821e+09 | M19: =M12+M13 -> 1.5189495e+09 | ... Q19: =Q12+Q13 -> 3.2043133e+09
B20: FIRR | C20: =IRR(C19:Q19) -> 0.22667941
B21: FNPV
B23: Net Margins (10% reduced revenue) | C23: =C19 -> -2.7258477e+09 | D23: =D19*0.9 -> 1.3520942e+09 | E23: =E19*0.9 -> 2.0920999e+08 | F23: =F19*0.9 -> -95723960 | G23: =G19*0.9 -> -5.3333821e+08 | H23: =H19*0.9 -> -2.1979643e+08 | I23: =I19*0.9 -> 6.3491694e+08 | J23: =J19*0.9 -> 7.7130622e+08 | K23: =K19*0.9 -> 9.321032e+08 | ... Q23: =Q19*0.9 -> 2.883882e+09
B24: FNPV(10% reduced revenue) | C24: =NPV(0.1,C23:Q23) -> 2.6568993e+09
B25: FIRR (10% reduced revenue) | C25: =IRR(C23:Q23) -> 0.20700349
B28: Net Margins (2 years delayed return) | C28: =C19 -> -2.7258477e+09 | F28: =-(F19) -> 1.0635996e+08 | G28: =G19 -> -5.9259801e+08 | H28: =H19 -> -2.4421826e+08 | I28: =I19 -> 7.0546327e+08 | J28: =J19 -> 8.5700691e+08 | K28: =K19 -> 1.0356702e+09 | L28: =L19 -> 1.2570821e+09 | M28: =M19 -> 1.5189495e+09 | N28: =N19 -> 1.8300014e+09 | ... Q28: =Q19 -> 3.2043133e+09
B30: FNPV(2 years delayed return) | C30: =NPV(0.1,C28:Q28) -> 2.8877532e+09
B32: FIRR(2 years delayed return) | C32: =IRR(C28:Q28) -> 0.19770048
B34: Net Margins (10% increase cost) | C34: =C19*1.1 -> -2.9984324e+09 | D34: =D19 -> 1.5023269e+09 | E34: =E19 -> 2.3245554e+08 | F34: =F19*1.1 -> -1.1699595e+08 | G34: =G19*1.1 -> -6.5185782e+08 | H34: =H19*1.1 -> -2.6864008e+08 | I34: =I19*1.1 -> 7.7600959e+08 | J34: =J19*1.1 -> 9.427076e+08 | K34: =K19*1.1 -> 1.1392372e+09 | L34: =L19*1.1 -> 1.3827903e+09 | M34: =M19*1.1 -> 1.6708445e+09 | ... Q34: =Q19*1.1 -> 3.5247447e+09
B36: FIRR(10% increase cost) | C36: 0.2
B37: Fnpv (10% reduced cost) | C37: =NPV(0.1,C34:Q34) -> 3.4085694e+09
A38: Economic
A39: Net Margins | B39: Particulars | C39: Year 1 | D39: Year 2 | E39: Year 3 | F39: Year 4 | G39: Year 5 | H39: Year 6 | I39: Year 7 | J39: Year 8 | K39: Year 9 | L39: Year 10 | M39: Year 11 | N39: Year 12 | O39: Year 13 | P39: Year 14 | Q39: Year 15
B40: peanut TF | C40: ='Peanut TF'!G64 -> -753790 | D40: ='Peanut TF'!H64 -> -83590 | E40: ='Peanut TF'!I64 -> -36790 | F40: ='Peanut TF'!J64 -> 1484210 | G40: ='Peanut TF'!K64 -> 80210 | H40: ='Peanut TF'!L64 -> 80210 | I40: ='Peanut TF'!M64 -> 80210 | J40: ='Peanut TF'!N64 -> 80210 | ... Q40: ='Peanut TF'!U64 -> 80210
B41: CassavaTF | C41: ='Cassava TF'!G66 -> -2344800 | D41: ='Cassava TF'!H66 -> -2286950 | E41: ='Cassava TF'!I66 -> -1540250 | F41: ='Cassava TF'!J66 -> 1540250 | G41: ='Cassava TF'!K66 -> 1540250 | H41: ='Cassava TF'!L66 -> 1540250 | I41: ='Cassava TF'!M66 -> 1540250 | J41: ='Cassava TF'!N66 -> 1540250 | ... Q41: ='Cassava TF'!U66 -> 1540250
B42: Cassava processing | C42: ='Cassava processing TF'!G65 -> -5241229 | D42: ='Cassava processing TF'!H65 -> -2102007.1 | E42: ='Cassava processing TF'!I65 -> -1567774 | F42: ='Cassava processing TF'!J65 -> 183209 | G42: ='Cassava processing TF'!K65 -> 7254486.5 | H42: ='Cassava processing TF'!L65 -> 3213756.5 | I42: ='Cassava processing TF'!M65 -> 3213756.5 | J42: ='Cassava processing TF'!N65 -> 3213756.5 | ... Q42: ='Cassava processing TF'!U65 -> 2597647
B43: Cattle breeding | C43: ='cattle breeding TF'!G63 -> -3021000 | D43: ='cattle breeding TF'!H63 -> -1776000 | E43: ='cattle breeding TF'!I63 -> -1776000 | F43: ='cattle breeding TF'!J63 -> 1776000 | G43: ='cattle breeding TF'!K63 -> 1956000 | H43: ='cattle breeding TF'!L63 -> 1776000 | I43: ='cattle breeding TF'!M63 -> 1776000 | J43: ='cattle breeding TF'!N63 -> 1776000 | ... Q43: ='cattle breeding TF'!U63 -> 1956000
B44: poultry breeding | C44: ='Poutry breeding TF'!G68 -> -2150639 | D44: ='Poutry breeding TF'!H68 -> -2150639 | E44: ='Poutry breeding TF'!I68 -> -2150639 | F44: ='Poutry breeding TF'!J68 -> 2150639 | G44: ='Poutry breeding TF'!K68 -> -2150639 | H44: ='Poutry breeding TF'!L68 -> 2150639 | I44: ='Poutry breeding TF'!M68 -> 2150639 | J44: ='Poutry breeding TF'!N68 -> 2150639 | ... Q44: ='Poutry breeding TF'!U68 -> 2150639
B45: Guest house TF | C45: =-(GH!D26) -> -400000 | D45: =-(GH!E26) -> -1350000 | E45: =-(GH!F26) -> -1350000 | F45: =-(GH!G26) -> -1350000 | G45: =GH!H26 -> -1350000 | H45: =GH!I26 -> -1350000 | I45: =GH!J26 -> -1350000 | J45: =GH!K26 -> -1350000 | K45: =GH!L26 -> -1350000 | L45: =GH!M26 -> -1350000 | M45: =GH!N26 -> -1350000 | N45: =GH!O26 -> -1350000 | ... Q45: =GH!R26 -> -1350000
B46: Total | C46: =SUM(C40:C45) -> -13911458 | D46: =SUM(D40:D45) -> -9749186.1 | E46: =SUM(E40:E45) -> -8421453 | F46: =SUM(F40:F45) -> 5784308 | G46: =SUM(G40:G45) -> 7330307.5 | H46: =SUM(H40:H45) -> 7410855.5 | I46: =SUM(I40:I45) -> 7410855.5 | J46: =SUM(J40:J45) -> 7410855.5 | ... Q46: =SUM(Q40:Q45) -> 6974746
B47: Total investment | C47: =C10 -> 28836177
B48: Total component cost | C48: =C11 -> 2299000000
B49: Net margins for total financing | C49: =C46*($C$11/$C$10) -> -1.1091083e+09 | D49: =D46*($C$11/$C$10) -> -7.7726597e+08 | E49: =-(E46*($C$11/$C$10)) -> 6.714108e+08 | F49: =F46*($C$11/$C$10) -> 4.6116114e+08 | G49: =G46*($C$11/$C$10) -> 5.8441787e+08 | H49: =H46*($C$11/$C$10) -> 5.9083966e+08 | I49: =I46*($C$11/$C$10) -> 5.9083966e+08 | J49: =J46*($C$11/$C$10) -> 5.9083966e+08 | K49: =K46*($C$11/$C$10) -> 5.4251683e+08 | L49: =L46*($C$11/$C$10) -> 5.5686755e+08 | M49: =M46*($C$11/$C$10) -> 5.4251683e+08 | ... Q49: =Q46*($C$11/$C$10) -> 5.5607029e+08
B50: Net margins for additional financing | C50: ='Additional financing total'!C37 -> -6.3989087e+08 | D50: ='Additional financing total'!D37 -> 1.3140998e+09 | E50: ='Additional financing total'!E37 -> 1.510751e+09 | F50: ='Additional financing total'!F37 -> -1.0897039e+09 | G50: ='Additional financing total'!G37 -> 1.7229519e+09 | H50: ='Additional financing total'!H37 -> -1.0897039e+09 | I50: ='Additional financing total'!I37 -> -1.0897039e+09 | J50: ='Additional financing total'!J37 -> -1.0897039e+09 | ... Q50: ='Additional financing total'!Q37 -> -1.0905012e+09
B51: Net margins(additional+total) | C51: ='TF Total Financing'!C38 -> -1.3991993e+09 | D51: ='TF Total Financing'!D38 -> 2.6841693e+08 | E51: ='TF Total Financing'!E38 -> 1.0910809e+09 | F51: ='TF Total Financing'!F38 -> 6.285428e+08 | G51: ='TF Total Financing'!G38 -> 2.3073698e+09 | H51: ='TF Total Financing'!H38 -> -4.9886428e+08 | I51: ='TF Total Financing'!I38 -> -4.9886428e+08 | J51: ='TF Total Financing'!J38 -> -4.9886428e+08 | ... Q51: ='TF Total Financing'!Q38 -> -5.3443091e+08
B52: EIRR (TF) | C52: =IRR(C49:Q49) -> 0.25132209
B53: ENPV (TF) | C53: =NPV(0.1,C49:Q49) -> 1.6846499e+09
B56: EIRR (AD+TF) | C56: ='TF Total Financing'!C43 -> 0.20640716
B57: ENPV(AD+TF) | C57: ='TF Total Financing'!C44 -> 1.5314999e+09
B60: Net Margins (10% reduced revenue) | C60: =C51*0.9 -> -1.2592794e+09 | D60: =D51*0.9 -> 2.4157523e+08 | E60: =E51*0.9 -> 9.819728e+08 | F60: =F51*0.9 -> 5.6568852e+08 | G60: =G51*0.9 -> 2.0766328e+09 | H60: =H51*0.9 -> -4.4897785e+08 | I60: =I51*0.9 -> -4.4897785e+08 | J60: =J51*0.9 -> -4.4897785e+08 | ... Q60: =Q51*0.9 -> -4.8098782e+08
B61: FNPV(10% reduced revenue) | C61: =-(NPV(0.1,C60:Q60)) -> 3.6237377e+08
B62: FIRR (10% reduced revenue) | C62: =IRR(C60:Q60) -> 0.20640716
B65: Net Margins (2 years delayed return) | C65: =C51 -> -1.3991993e+09 | F65: =F51 -> 6.285428e+08 | G65: =G51 -> 2.3073698e+09 | H65: =H51 -> -4.9886428e+08 | I65: =I51 -> -4.9886428e+08 | J65: =J51 -> -4.9886428e+08 | K65: =K51 -> -5.4718711e+08 | L65: =L51 -> -5.3283639e+08 | M65: =M51 -> -5.7110498e+08 | ... Q65: =Q51 -> -5.3443091e+08
B67: FNPV(2 years delayed return) | C67: =-(NPV(0.1,C65:Q65)) -> 1.4803802e+09
B69: FIRR(2 years delayed return)
B71: Net Margins (10% increase cost) | C71: =C51*1.1 -> -1.5391192e+09 | D71: =D51 -> 2.6841693e+08 | E71: =E51 -> 1.0910809e+09 | F71: =F51 -> 6.285428e+08 | G71: =G51 -> 2.3073698e+09 | H71: =H51 -> -4.9886428e+08 | I71: =I51 -> -4.9886428e+08 | J71: =J51 -> -4.9886428e+08 | K71: =K51 -> -5.4718711e+08 | ... Q71: =Q51 -> -5.3443091e+08
B73: FIRR(10% increase cost) | C73: 0.2
B74: Fnpv (10% reduced cost) | C74: =-(NPV(0.1,C71:Q71)) -> 5.2983746e+08
C77: topic | D77: EIRR | E77: FIRR | F77: FNPV | G77: ENPV
C78: Baseline | D78: =C52 -> 0.25132209 | E78: =C14 -> 0.21194584 | F78: =C15 -> 1.6564373e+09 | G78: =C57 -> 1.5314999e+09
C79: 10% decrease revenue | D79: =C25 -> 0.20700349 | E79: =C25 -> 0.20700349 | F79: =C24 -> 2.6568993e+09 | G79: =C61 -> 3.6237377e+08
C80: 10% increase cost | D80: =C73 -> 0.2 | E80: =C32 -> 0.19770048 | F80: =C37 -> 3.4085694e+09 | G80: =C67 -> 1.4803802e+09
C81: 2 year delayed return | D81: 0.21 | E81: =C36 -> 0.2 | F81: =C37 -> 3.4085694e+09 | G81: =C74 -> 5.2983746e+08

Sheet TF Total Financing
A1: Financial
A2: Net Margins | B2: Particulars | C2: Year 1 | D2: Year 2 | E2: Year 3 | F2: Year 4 | G2: Year 5 | H2: Year 6 | I2: Year 7 | J2: Year 8 | K2: Year 9 | L2: Year 10 | M2: Year 11 | N2: Year 12 | O2: Year 13 | P2: Year 14 | Q2: Year 15
B3: Peanut TF | C3: ='Peanut TF'!G30 -> -671500 | D3: ='Peanut TF'!H30 -> -136833.33 | E3: ='Peanut TF'!I30 -> -84833.333 | F3: ='Peanut TF'!J30 -> 1615166.7 | G3: ='Peanut TF'!K30 -> 55166.667 | H3: ='Peanut TF'!L30 -> 45166.667 | I3: ='Peanut TF'!M30 -> 55166.667 | J3: ='Peanut TF'!N30 -> 55166.667 | ... Q3: ='Peanut TF'!U30 -> 45166.667
B4: Cassava TF | C4: ='Cassava TF'!G29 -> -2644166.7 | D4: ='Cassava TF'!H29 -> -3564166.7 | E4: ='Cassava TF'!I29 -> 1595833.3 | F4: ='Cassava TF'!J29 -> 1595833.3 | G4: ='Cassava TF'!K29 -> 1595833.3 | H4: ='Cassava TF'!L29 -> 1595833.3 | I4: ='Cassava TF'!M29 -> 1595833.3 | J4: ='Cassava TF'!N29 -> 1595833.3 | ... Q4: ='Cassava TF'!U29 -> 1595833.3
B5: Cassava processing TF | C5: ='Cassava processing TF'!G31 -> -6470810 | D5: ='Cassava processing TF'!H31 -> -6356119 | E5: ='Cassava processing TF'!I31 -> -2817355 | F5: ='Cassava processing TF'!J31 -> -407081.25 | G5: ='Cassava processing TF'!K31 -> 7449893.8 | H5: ='Cassava processing TF'!L31 -> 2950193.8 | I5: ='Cassava processing TF'!M31 -> 2960193.8 | J5: ='Cassava processing TF'!N31 -> 2960193.8 | ... Q5: ='Cassava processing TF'!U31 -> 2950193.8
B6: cattle breeding TF | C6: ='cattle breeding TF'!G30 -> -3386333.3 | D6: ='cattle breeding TF'!H30 -> -121333.33 | E6: ='cattle breeding TF'!I30 -> 466666.67 | F6: ='cattle breeding TF'!J30 -> 1254666.7 | G6: ='cattle breeding TF'!K30 -> 1254666.7 | H6: ='cattle breeding TF'!L30 -> 1254666.7 | I6: ='cattle breeding TF'!M30 -> 1254666.7 | J6: ='cattle breeding TF'!N30 -> 1254666.7 | ... Q6: ='cattle breeding TF'!U30 -> 1254666.7 | R6: ='External Shading (Awnings, Over'!V30 -> 0 | S6: ='External Shading (Awnings, Over'!W30 -> 0
B7: poultry breeding TF | C7: ='Poutry breeding TF'!G28 -> -3920550 | D7: ='Poutry breeding TF'!H28 -> -3920550 | E7: ='Poutry breeding TF'!I28 -> -3920550 | F7: ='Poutry breeding TF'!J28 -> -3920550 | G7: ='Poutry breeding TF'!K28 -> -1841970 | H7: ='Poutry breeding TF'!L28 -> -1121970 | I7: ='Poutry breeding TF'!M28 -> -257970 | J7: ='Poutry breeding TF'!N28 -> 778830 | ... Q7: ='Poutry breeding TF'!U28 -> 16858991
B8: Guest house TF | C8: =GH!D17 -> -400000 | D8: =GH!E17 -> -450000 | E8: =GH!F17 -> -450000 | F8: =GH!G17 -> -450000 | G8: =GH!H17 -> 420000 | H8: =GH!I17 -> 420000 | I8: =GH!J17 -> 420000 | J8: =GH!K17 -> 420000 | ... Q8: =GH!R17 -> 420000
B9: Total | C9: =SUM(C3:C8) -> -17493360 | D9: =SUM(D3:D8) -> -14549002 | E9: =SUM(E3:E8) -> -5210238.3 | F9: =SUM(F3:F8) -> -311964.58 | G9: =SUM(G3:G8) -> 8933590.4 | H9: =SUM(H3:H8) -> 5143890.4 | I9: =SUM(I3:I8) -> 6027890.4 | J9: =SUM(J3:J8) -> 7064690.4 | ... Q9: =SUM(Q3:Q8) -> 23124852
B10: Total investment | C10: =Summary!B11 -> 28836177 | T10: Total investment | V10: 10 | W10: Million
B11: Total component cost | C11: =V13 -> 2299000000 | U11: US$ | V11: =10000000 -> 10000000
B12: NET margins for additional financing | C12: ='Additional financing total'!C13 -> -1.3311678e+09 | D12: ='Additional financing total'!D13 -> 3.4238966e+08 | E12: ='Additional financing total'!E13 -> 1.8293718e+08 | F12: ='Additional financing total'!F13 -> -81488192 | G12: ='Additional financing total'!G13 -> 1.1964358e+08 | H12: ='Additional financing total'!H13 -> 1.658848e+08 | I12: ='Additional financing total'!I13 -> 2.2488222e+08 | J12: ='Additional financing total'!J13 -> 2.9376569e+08 | ... Q12: ='Additional financing total'!Q13 -> 1.3606558e+09
B13: Net margins for the total financing | C13: =C9*($C$11/$C$10) -> -1.3946799e+09 | D13: =-(D9*($C$11/$C$10)) -> 1.1599373e+09 | E13: =E9*($C$11/$C$10) -> -4.1539272e+08 | F13: =(F9*($C$11/$C$10)) -> -24871764 | G13: =-(G9*($C$11/$C$10)) -> -7.1224159e+08 | H13: =-(H9*($C$11/$C$10)) -> -4.1010305e+08 | I13: =I9*($C$11/$C$10) -> 4.8058105e+08 | J13: =J9*($C$11/$C$10) -> 5.6324122e+08 | K13: =K9*($C$11/$C$10) -> 6.6083889e+08 | L13: =L9*($C$11/$C$10) -> 7.8146406e+08 | M13: =M9*($C$11/$C$10) -> 9.2430083e+08 | N13: =N9*($C$11/$C$10) -> 1.0941104e+09 | O13: =O9*($C$11/$C$10) -> 1.3013899e+09 | P13: =P9*($C$11/$C$10) -> 1.4684856e+09 | Q13: =Q9*($C$11/$C$10) -> 1.8436575e+09 | U13: G$ | V13: 2299000000
B14: FIRR(TF) | C14: =IRR(C13:Q13) -> 0.21194584
B15: FNPV(TF) | C15: =NPV(0.1,C13:Q13) -> 1.6564373e+09
C18: =V13 -> 2299000000
B19: Net Margins (total+additional) | C19: =C12+C13 -> -2.7258477e+09 | D19: =(D12+D13) -> 1.5023269e+09 | E19: =-(E12+E13) -> 2.3245554e+08 | F19: =F12+F13 -> -1.0635996e+08 | G19: =G12+G13 -> -5.9259801e+08 | H19: =H12+H13 -> -2.4421826e+08 | I19: =I12+I13 -> 7.0546327e+08 | J19: =J12+J13 -> 8.5700691e+08 | K19: =K12+K13 -> 1.0356702e+09 | L19: =L12+L13 -> 1.2570821e+09 | M19: =M12+M13 -> 1.5189495e+09 | ... Q19: =Q12+Q13 -> 3.2043133e+09
B20: FIRR | C20: =IRR(C19:Q19) -> 0.22667941
B21: FNPV
A25: Economic
A26: Net Margins | B26: Particulars | C26: Year 1 | D26: Year 2 | E26: Year 3 | F26: Year 4 | G26: Year 5 | H26: Year 6 | I26: Year 7 | J26: Year 8 | K26: Year 9 | L26: Year 10 | M26: Year 11 | N26: Year 12 | O26: Year 13 | P26: Year 14 | Q26: Year 15
B27: peanut TF | C27: ='Peanut TF'!G64 -> -753790 | D27: ='Peanut TF'!H64 -> -83590 | E27: ='Peanut TF'!I64 -> -36790 | F27: ='Peanut TF'!J64 -> 1484210 | G27: ='Peanut TF'!K64 -> 80210 | H27: ='Peanut TF'!L64 -> 80210 | I27: ='Peanut TF'!M64 -> 80210 | J27: ='Peanut TF'!N64 -> 80210 | ... Q27: ='Peanut TF'!U64 -> 80210
B28: CassavaTF | C28: ='Cassava TF'!G66 -> -2344800 | D28: ='Cassava TF'!H66 -> -2286950 | E28: ='Cassava TF'!I66 -> -1540250 | F28: ='Cassava TF'!J66 -> 1540250 | G28: ='Cassava TF'!K66 -> 1540250 | H28: ='Cassava TF'!L66 -> 1540250 | I28: ='Cassava TF'!M66 -> 1540250 | J28: ='Cassava TF'!N66 -> 1540250 | ... Q28: ='Cassava TF'!U66 -> 1540250
B29: Cassava processing | C29: ='Cassava processing TF'!G65 -> -5241229 | D29: ='Cassava processing TF'!H65 -> -2102007.1 | E29: ='Cassava processing TF'!I65 -> -1567774 | F29: ='Cassava processing TF'!J65 -> 183209 | G29: ='Cassava processing TF'!K65 -> 7254486.5 | H29: ='Cassava processing TF'!L65 -> 3213756.5 | I29: ='Cassava processing TF'!M65 -> 3213756.5 | J29: ='Cassava processing TF'!N65 -> 3213756.5 | ... Q29: ='Cassava processing TF'!U65 -> 2597647
B30: Cattle breeding | C30: ='cattle breeding TF'!G63 -> -3021000 | D30: ='cattle breeding TF'!H63 -> -1776000 | E30: ='cattle breeding TF'!I63 -> -1776000 | F30: ='cattle breeding TF'!J63 -> 1776000 | G30: ='cattle breeding TF'!K63 -> 1956000 | H30: ='cattle breeding TF'!L63 -> 1776000 | I30: ='cattle breeding TF'!M63 -> 1776000 | J30: ='cattle breeding TF'!N63 -> 1776000 | ... Q30: ='cattle breeding TF'!U63 -> 1956000
B31: poultry breeding | C31: ='Poutry breeding TF'!G68 -> -2150639 | D31: ='Poutry breeding TF'!H68 -> -2150639 | E31: ='Poutry breeding TF'!I68 -> -2150639 | F31: ='Poutry breeding TF'!J68 -> 2150639 | G31: ='Poutry breeding TF'!K68 -> -2150639 | H31: ='Poutry breeding TF'!L68 -> 2150639 | I31: ='Poutry breeding TF'!M68 -> 2150639 | J31: ='Poutry breeding TF'!N68 -> 2150639 | ... Q31: ='Poutry breeding TF'!U68 -> 2150639
B32: Guest house TF | C32: =-(GH!D26) -> -400000 | D32: =-(GH!E26) -> -1350000 | E32: =-(GH!F26) -> -1350000 | F32: =-(GH!G26) -> -1350000 | G32: =GH!H26 -> -1350000 | H32: =GH!I26 -> -1350000 | I32: =GH!J26 -> -1350000 | J32: =GH!K26 -> -1350000 | K32: =GH!L26 -> -1350000 | L32: =GH!M26 -> -1350000 | M32: =GH!N26 -> -1350000 | N32: =GH!O26 -> -1350000 | ... Q32: =GH!R26 -> -1350000
B33: Total | C33: =SUM(C27:C32) -> -13911458 | D33: =SUM(D27:D32) -> -9749186.1 | E33: =SUM(E27:E32) -> -8421453 | F33: =SUM(F27:F32) -> 5784308 | G33: =SUM(G27:G32) -> 7330307.5 | H33: =SUM(H27:H32) -> 7410855.5 | I33: =SUM(I27:I32) -> 7410855.5 | J33: =SUM(J27:J32) -> 7410855.5 | ... Q33: =SUM(Q27:Q32) -> 6974746
B34: Total investment | C34: =C10 -> 28836177
B35: Total component cost | C35: =C11 -> 2299000000
B36: Net margins for total financing | C36: =C33*($C$11/$C$10) -> -1.1091083e+09 | D36: =D33*($C$11/$C$10) -> -7.7726597e+08 | E36: =-(E33*($C$11/$C$10)) -> 6.714108e+08 | F36: =F33*($C$11/$C$10) -> 4.6116114e+08 | G36: =G33*($C$11/$C$10) -> 5.8441787e+08 | H36: =H33*($C$11/$C$10) -> 5.9083966e+08 | I36: =I33*($C$11/$C$10) -> 5.9083966e+08 | J36: =J33*($C$11/$C$10) -> 5.9083966e+08 | K36: =K33*($C$11/$C$10) -> 5.4251683e+08 | L36: =L33*($C$11/$C$10) -> 5.5686755e+08 | M36: =M33*($C$11/$C$10) -> 5.4251683e+08 | ... Q36: =Q33*($C$11/$C$10) -> 5.5607029e+08
B37: Net margins for additional financing | C37: ='Additional financing total'!C37 -> -6.3989087e+08 | D37: ='Additional financing total'!D37 -> 1.3140998e+09 | E37: ='Additional financing total'!E37 -> 1.510751e+09 | F37: ='Additional financing total'!F37 -> -1.0897039e+09 | G37: ='Additional financing total'!G37 -> 1.7229519e+09 | H37: ='Additional financing total'!H37 -> -1.0897039e+09 | I37: ='Additional financing total'!I37 -> -1.0897039e+09 | J37: ='Additional financing total'!J37 -> -1.0897039e+09 | ... Q37: ='Additional financing total'!Q37 -> -1.0905012e+09
B38: Net margins(additional+total) | C38: =0.8*(C36+C37) -> -1.3991993e+09 | D38: =0.5*(D36+D37) -> 2.6841693e+08 | E38: =0.5*(E36+E37) -> 1.0910809e+09 | F38: =-(F36+F37) -> 6.285428e+08 | G38: =(G36+G37) -> 2.3073698e+09 | H38: =H36+H37 -> -4.9886428e+08 | I38: =I36+I37 -> -4.9886428e+08 | J38: =J36+J37 -> -4.9886428e+08 | K38: =K36+K37 -> -5.4718711e+08 | L38: =L36+L37 -> -5.3283639e+08 | M38: =M36+M37 -> -5.7110498e+08 | N38: =N36+N37 -> -5.7269951e+08 | O38: =O36+O37 -> -5.7110498e+08 | ... Q38: =Q36+Q37 -> -5.3443091e+08
B39: EIRR (TF) | C39: =IRR(C36:Q36) -> 0.25132209
B40: ENPV (TF) | C40: =NPV(0.1,C36:Q36) -> 1.6846499e+09
B43: EIRR (AD+TF) | C43: =IRR(C38:Q38) -> 0.20640716
B44: ENPV(AD+TF) | C44: =NPV(0.1,C40:Q40) -> 1.5314999e+09
C50: =NPV(0.1,C48:Q48) -> 0

Sheet GH
A1: Infrastructure Activity: Guest House
B4: Particulars | D4: Year 0 | E4: Year 1 | F4: Year 2 | G4: Year 3 | H4: Year 4 | I4: Year 5 | J4: Year 6 | K4: Year 7 | L4: Year 8 | M4: Year 9 | N4: Year 10 | O4: Year 11 | P4: Year 12 | Q4: Year 13 | R4: Year 14 | S4: Year 15
E5: 1 | F5: 2 | G5: 3 | H5: 4 | I5: 5
B6: EBIDT(Earnings Before Interest, Taxes, Depreciation, and Amortization) | E6: -900000 | F6: =E6 -> -900000 | G6: =F6 -> -900000 | H6: -30000 | I6: -30000 | J6: -30000 | K6: -30000 | L6: -30000 | M6: -30000 | N6: -30000 | O6: -30000 | P6: -30000 | Q6: -30000 | R6: -30000 | S6: -30000
B7: Capital Expenditure | D7: -400000 | E7: 0 | F7: 0 | G7: 0 | H7: 0 | I7: 0
B9: Free Cash Flow Before Benefits | D9: =D6+D7 -> -400000 | E9: =E6+E7 -> -900000 | F9: =F6+F7 -> -900000 | G9: =G6+G7 -> -900000 | H9: =H6+H7 -> -30000 | I9: =I6+I7 -> -30000 | J9: =J6+J7 -> -30000 | K9: =K6+K7 -> -30000 | ... S9: =S6+S7 -> -30000
B11: Benefits due to save in time | C11: Yes | E11: 450000 | F11: =E11 -> 450000 | G11: =F11 -> 450000 | H11: =G11 -> 450000 | I11: =H11 -> 450000 | J11: =I11 -> 450000 | K11: =J11 -> 450000 | L11: =K11 -> 450000 | M11: =L11 -> 450000 | ... S11: =R11 -> 450000
B13: Free Cash Flow After Benefits | D13: =-(D11+D9) -> 400000 | E13: =E11+E9 -> -450000 | F13: =F11+F9 -> -450000 | G13: =G11+G9 -> -450000 | H13: =H11+H9 -> 420000 | I13: =I11+I9 -> 420000 | J13: =J11+J9 -> 420000 | K13: =K11+K9 -> 420000 | L13: =L11+L9 -> 420000 | ... S13: =S11+S9 -> 420000
B15: Terminal Value | C15: 0.03 | S15: =S13*(1+C15)/(C16-C15) -> 6180000
B16: WACC(weighted average cost of capital) | C16: 0.1
B17: Net Free cash Flow Value | D17: =-(D13+D15) -> -400000 | E17: =E13+E15 -> -450000 | F17: =F13+F15 -> -450000 | G17: =G13+G15 -> -450000 | H17: =H13+H15 -> 420000 | I17: =I13+I15 -> 420000 | J17: =J13+J15 -> 420000 | K17: =K13+K15 -> 420000 | L17: =L13+L15 -> 420000 | ... S17: =S13+S15 -> 6600000
B22: Net Present Value | C22: ENPV | D22: =NPV(0.1,D17:S17) -> 1918577.3
B23: Economic Rate of Return | C23: EIRR | D23: =IRR(D17:S17) -> 0.21393484
B26: Financial Rate of Return | D26: =-(D9+D15) -> 400000 | E26: =-(E9+E13) -> 1350000 | F26: =-(F9+F13) -> 1350000 | G26: =-(E9+E13) -> 1350000 | H26: =E9+E13 -> -1350000 | I26: =E9+E13 -> -1350000 | J26: =I26 -> -1350000 | K26: =J26 -> -1350000 | L26: =K26 -> -1350000 | M26: =L26 -> -1350000 | N26: =M26 -> -1350000 | O26: =N26 -> -1350000 | P26: =O26 -> -1350000 | Q26: =P26 -> -1350000 | R26: =Q26 -> -1350000 | S26: =S9+S15 -> 6150000
C27: FNPV | D27: =-(NPV(0.1,D26:S26)) -> 1234787.8
C28: FIRR | D28: =IRR(D26:S26) -> 0.17820161
